Workbook

Sheet Empreendimento
A1: Empreendimento | B1: Contrato | C1: APF | D1: Valor Aporte | E1: Total de Unidade | F1: Unidades Comercializadas | G1: Unidades Financiadas Construção | H1: Unidades Complementares | I1: Data Término de Obra | J1: Data Ini - Enc Fiador
A2: CONDOMINIO UP JARDIM PRUDENCIA | B2: 177770016646-5 | C2: 054555008 | D2: 0 | E2: 106 | F2: 0 | G2: 62 | H2: 0 | I2: 04/09/2026 | J2: 04/03/2027

Sheet Emprestimo PJ
A1: Número | B1: Data da Assinatura | C1: Valor Empréstimo | D1: Valor Reduzido | E1: Valor Utilizado | F1: Saldo Devedor | G1: Linha de financiamento | H1: Tipo de financiamento
A2: 878771764647 | B2: 07/08/2023 | C2: 9712092 | D2: 3777094.2 | E2: 1885216.7 | F2: 1265556.1 | G2: 869 | H2: 38

Sheet Consolidado
A1: Período | B1: Unidade | C1: Valor Creditado | D1: Valor Desbloqueado | E1: Valor Amortizado | F1: Encargo Quitado do PJ
A2: 14/09/2023 | B2: Construção | C2: 967837.57 | D2: 0 | E2: 0 | F2: 0
A3: 09/10/2023 | B3: Construção | C3: 0 | D3: 662424.54 | E3: 0 | F3: 0
A4: 10/10/2023 | B4: Construção | C4: 0 | D4: 58145.58 | E4: 0 | F4: 0
A5: 13/10/2023 | B5: Construção | C5: 0 | D5: 125972.98 | E5: 0 | F5: 0
A6: 23/10/2023 | B6: Construção | C6: 0 | D6: 34076.1 | E6: 0 | F6: 0
A7: 25/10/2023 | B7: Construção | C7: 0 | D7: 87218.37 | E7: 0 | F7: 0
A8: 22/11/2023 | B8: Construção | C8: 209068.89 | D8: 0 | E8: 0 | F8: 0
A9: 18/01/2024 | B9: Construção | C9: 145966.23 | D9: 0 | E9: 0 | F9: 0
A10: 24/01/2024 | B10: Construção | C10: 59174.33 | D10: 0 | E10: 0 | F10: 0
A11: 31/01/2024 | B11: Construção | C11: 0 | D11: 209068.89 | E11: 0 | F11: 0
A12: 05/02/2024 | B12: Construção | C12: 58489.25 | D12: 0 | E12: 0 | F12: 0
A13: 15/02/2024 | B13: Construção | C13: 29569.47 | D13: 0 | E13: 0 | F13: 0
... A43: 30/12/2024 | B43: Construção | C43: 474958.81 | D43: 467629.51 | E43: 0 | F43: 0

Sheet Unidades
A1: Contrato | B1: TP | C1: Data de Assinatura | D1: Data de Inclusão | E1: Data de Registro | F1: Financiamento | G1: Desconto Subsídio | H1: FGTS | I1: Recursos Próprios | J1: Compra / Venda | K1: Valor de Avaliação | L1: Valor Liberado Terreno | M1: Valor Liberado Obra | N1: Amortização
A2: 178770249744-0 | B2: 009 | C2: 04/09/2023 | D2: 14/09/2023 | E2: 09/10/2023 | F2: 233550 | G2: 0 | H2: 0 | I2: 0 | J2: 400000 | K2: 259500 | L2: 33961.93 | M2: 74226.78 | N2: 0
A3: 178770249792-0 | B3: 009 | C3: 04/09/2023 | D3: 14/09/2023 | E3: 09/10/2023 | F3: 234900 | G3: 0 | H3: 0 | I3: 0 | J3: 263500 | K3: 263500 | L3: 29569.47 | M3: 76362.38 | N3: 0
A4: 178770249973-6 | B4: 009 | C4: 04/09/2023 | D4: 14/09/2023 | E4: 09/10/2023 | F4: 203607.39 | G4: 0 | H4: 54892.61 | I4: 0 | J4: 258500 | K4: 258500 | L4: 33876.86 | M4: 83537.32 | N4: 0
A5: 178770250115-3 | B5: 009 | C5: 04/09/2023 | D5: 14/09/2023 | E5: 10/10/2023 | F5: 204974.21 | G5: 0 | H5: 12006.99 | I5: 0 | J5: 258500 | K5: 258500 | L5: 29072.79 | M5: 69883.13 | N5: 0
A6: 178770250140-4 | B6: 009 | C6: 04/09/2023 | D6: 14/09/2023 | E6: 09/10/2023 | F6: 234900 | G6: 0 | H6: 0 | I6: 0 | J6: 264000 | K6: 261000 | L6: 34076.1 | M6: 74686.37 | N6: 0
A7: 178770250188-9 | B7: 009 | C7: 04/09/2023 | D7: 14/09/2023 | E7: 09/10/2023 | F7: 214897.45 | G7: 0 | H7: 0 | I7: 0 | J7: 264000 | K7: 258500 | L7: 29072.79 | M7: 69108.18 | N7: 0
A8: 178770250440-3 | B8: 009 | C8: 04/09/2023 | D8: 14/09/2023 | E8: 09/10/2023 | F8: 210800 | G8: 0 | H8: 0 | I8: 0 | J8: 263500 | K8: 263500 | L8: 29569.47 | M8: 67399.59 | N8: 0
A9: 178770251132-9 | B9: 009 | C9: 04/09/2023 | D9: 14/09/2023 | E9: 09/10/2023 | F9: 237150 | G9: 0 | H9: 0 | I9: 0 | J9: 264000 | K9: 263500 | L9: 29569.47 | M9: 77199.19 | N9: 0
A10: 178770251134-5 | B10: 009 | C10: 04/09/2023 | D10: 14/09/2023 | E10: 09/10/2023 | F10: 234900 | G10: 0 | H10: 0 | I10: 0 | J10: 264000 | K10: 261000 | L10: 34076.1 | M10: 74686.37 | N10: 0
A11: 178770251247-3 | B11: 009 | C11: 21/12/2023 | D11: 18/01/2024 | E11: 24/05/2024 | F11: 199233.04 | G11: 0 | H11: 10233.48 | I11: 0 | J11: 264000 | K11: 261000 | L11: 29331.4 | M11: 66992.25 | N11: 8331.23
A12: 178770254390-5 | B12: 009 | C12: 13/10/2023 | D12: 22/11/2023 | E12: 31/01/2024 | F12: 198926.28 | G12: 0 | H12: 42730.81 | I12: 0 | J12: 264000 | K12: 258500 | L12: 29072.79 | M12: 79060.08 | N12: 0
A13: 178770262040-3 | B13: 009 | C13: 25/03/2024 | D13: 26/03/2024 | E13: 30/04/2024 | F13: 307313.4 | G13: 0 | H13: 0 | I13: 0 | J13: 346101 | K13: 346101 | L13: 34076.1 | M13: 101616.94 | N13: 25875.56
... A54: 878771869261-0 | B54: 009 | C54: 21/12/2023 | D54: 18/01/2024 | E54: 24/05/2024 | F54: 207608.15 | G54: 0 | H54: 0 | I54: 0 | J54: 264000 | K54: 303478 | L54: 29072.79 | M54: 66397.29 | N54: 8257.23
A55: 878771872731-6 | B55: 009 | C55: 26/12/2023 | D55: 18/01/2024 | F55: 211200 | G55: 0 | H55: 0 | I55: 0 | J55: 264000 | K55: 306240 | L55: 29331.4 | M55: 67636.88 | N55: 0
A56: 878771874469-5 | B56: 009 | C56: 08/03/2024 | D56: 08/03/2024 | E56: 30/04/2024 | F56: 183440.97 | G56: 0 | H56: 0 | I56: 0 | J56: 264000 | K56: 303478 | L56: 33876.86 | M56: 55622.91 | N56: 14163.73
A57: 878771885931-0 | B57: 009 | C57: 05/02/2024 | D57: 05/02/2024 | E57: 30/04/2024 | F57: 197630.14 | G57: 649 | H57: 0 | I57: 0 | J57: 264000 | K57: 304629 | L57: 29157.85 | M57: 62896.21 | N57: 16015.78
A58: 878771895753-2 | B58: 009 | C58: 05/02/2024 | D58: 05/02/2024 | E58: 10/05/2024 | F58: 216043.5 | G58: 0 | H58: 0 | I58: 0 | J58: 350000 | K58: 306240 | L58: 29331.4 | M58: 69438.22 | N58: 17681.63
A59: 878771951769-2 | B59: 009 | C59: 08/04/2024 | D59: 09/04/2024 | E59: 18/07/2024 | F59: 248368.79 | G59: 0 | H59: 0 | I59: 0 | J59: 350000 | K59: 346101 | L59: 34076.1 | M59: 79695.44 | N59: 20655.19
A60: 878772012311-2 | B60: 009 | C60: 08/07/2024 | D60: 15/07/2024 | E60: 22/08/2024 | F60: 182015.77 | G60: 0 | H60: 52750.97 | I60: 0 | J60: 304629 | K60: 304629 | L60: 29157.85 | M60: 76465.93 | N60: 29155.34
A61: 878772012512-3 | B61: 009 | C61: 08/07/2024 | D61: 15/07/2024 | E61: 22/08/2024 | F61: 235333.45 | G61: 0 | H61: 41066.39 | I61: 0 | J61: 310000 | K61: 310000 | L61: 29569.47 | M61: 91796.23 | N61: 35000.54
A62: 878772065937-3 | B62: 009 | C62: 09/08/2024 | D62: 09/08/2024 | E62: 05/09/2024 | F62: 276874.21 | G62: 0 | H62: 9818.33 | I62: 0 | J62: 350000 | K62: 350000 | L62: 34373.54 | M62: 93837.42 | N62: 42843.76
A63: 878772102175-5 | B63: 009 | C63: 30/09/2024 | D63: 28/10/2024 | E63: 07/11/2024 | F63: 207187.78 | G63: 0 | H63: 11128.42 | I63: 0 | J63: 306240 | K63: 306240 | L63: 29331.4 | M63: 70283.45 | N63: 52707.86

Sheet Planilha1
A1: JPD 2025.01
A2: E | B2: PJ | C2: PJ | D2: PJ | E2: PJ | F2: U | G2: U | H2: U | I2: U | J2: U | K2: U | L2: U | M2: U | N2: U | O2: C | P2: C | Q2: C | R2: C
A3: Valor Aporte | B3: Valor Empréstimo | C3: Valor Reduzido | D3: Valor Utilizado | E3: Saldo Devedor | F3: Financiamento | G3: Desconto Subsídio | H3: FGTS | I3: Recursos Próprios | J3: Compra / Venda | K3: Valor de Avaliação | L3: Valor Liberado Terreno | M3: Valor Liberado Obra | N3: Amortização | O3: Valor creditado | P3: Valor desbloqueado | Q3: Valor amortizado | R3: Encargo quitado do PJ
A4: 0 | B4: 9712092 | C4: 3777094.2 | D4: 1885216.7 | E4: 1265556.1 | F4: =SUM(Unidades!F$2:F$63) -> 12893899 | G4: =SUM(Unidades!G$2:G$63) -> 25182 | H4: =SUM(Unidades!H$2:H$63) -> 756311.77 | I4: =SUM(Unidades!I$2:I$63) -> 0 | J4: =SUM(Unidades!J$2:J$63) -> 17332251 | K4: =SUM(Unidades!K$2:K$63) -> 17374502 | L4: =SUM(Unidades!L$2:L$63) -> 1889811.2 | M4: =SUM(Unidades!M$2:M$63) -> 4383056.8 | N4: =SUM(Unidades!N$2:N$63) -> 622107.75 | O4: =SUM(Consolidado!C2:C43) -> 6272868 | P4: =SUM(Consolidado!D2:D43) -> 6175899.7 | Q4: =SUM(Consolidado!E2:E43) -> 622107.75 | R4: =SUM(Consolidado!F2:F43) -> 0
D6: s.devedor = utilizado + encargos - amortização | G6: =D4+R4-N4 -> 1263108.9
D7: diferença entre s.devedor e fórmula acima | G7: =E4-G6 -> 2447.17 | H7: =G7/E4 -> 0.0019336717 | O7: creditado = l.terreno + l.obra | Q7: =L4+M4 -> 6272868
B9: emprestimo - reduzido | D9: =B4-C4 -> 5934997.8
A12: EVS 2025.01
A13: E | B13: PJ | C13: PJ | D13: PJ | E13: PJ | F13: U | G13: U | H13: U | I13: U | J13: U | K13: U | L13: U | M13: U | N13: U | O13: C | P13: C | Q13: C | R13: C
A14: Valor Aporte | B14: Valor Empréstimo | C14: Valor Reduzido | D14: Valor Utilizado | E14: Saldo Devedor | F14: Financiamento | G14: Desconto Subsídio | H14: FGTS | I14: Recursos Próprios | J14: Compra / Venda | K14: Valor de Avaliação | L14: Valor Liberado Terreno | M14: Valor Liberado Obra | N14: Amortização | O14: Valor creditado | P14: Valor desbloqueado | Q14: Valor amortizado | R14: Encargo quitado do PJ
A15: 0 | B15: 27607680 | C15: 2542543.2 | D15: 928463.72 | E15: 928768.46 | F15: =SUM([1]Unidades!$F$2:$F$73) -> 17354524 | G15: =SUM([1]Unidades!$G$2:$G$73) -> 9351 | H15: =SUM([1]Unidades!$H$2:$H$73) -> 1312607.3 | I15: =SUM([1]Unidades!$I$2:$I$73) -> 0 | J15: =SUM([1]Unidades!$J$2:$J$73) -> 23331000 | K15: =SUM([1]Unidades!$K$2:$K$73) -> 23331000 | L15: =SUM([1]Unidades!$L$2:$L$73) -> 3241716.2 | M15: =SUM([1]Unidades!$M$2:$M$73) -> 546390.6 | N15: =SUM([1]Unidades!$N$2:$N$73) -> 0 | O15: =SUM([1]Consolidado!$C$2:$C$8) -> 3788106.8 | P15: =SUM([1]Consolidado!$D$2:$D$8) -> 3428126.5 | Q15: =SUM([1]Consolidado!$E$2:$E$8) -> 0 | R15: =SUM([1]Consolidado!$F$2:$F$8) -> 0
D17: s.devedor = utilizado + encargos - amortização | G17: =D15+R15-N15 -> 928463.72
D18: diferença entre s.devedor e fórmula acima | G18: =E15-G17 -> 304.74 | H18: =G18/E15 -> 0.00032811192 | O18: creditado = l.terreno + l.obra | Q18: =L15+M15 -> 3788106.8
B20: emprestimo - reduzido | D20: =B15-C15 -> 25065137
