Workbook

Sheet comp
C2: 46023 | D2: 46054 | E2: 46082 | F2: 46113 | G2: 46143 | H2: 46174 | I2: 46204
B3: Extratos | C3: =SUMIFS(comp[Saldo (Extratos)], comp[Mês], ">="&C$2, comp[Mês], "<"&EOMONTH(C$2,0)+1 ) -> 0 | D3: =SUMIFS(comp[Saldo (Extratos)], comp[Mês], ">="&D$2, comp[Mês], "<"&EOMONTH(D$2,0)+1 ) -> 0 | E3: =SUMIFS(comp[Saldo (Extratos)], comp[Mês], ">="&E$2, comp[Mês], "<"&EOMONTH(E$2,0)+1 ) -> 0 | F3: =SUMIFS(comp[Saldo (Extratos)], comp[Mês], ">="&F$2, comp[Mês], "<"&EOMONTH(F$2,0)+1 ) -> 0 | G3: =SUMIFS(comp[Saldo (Extratos)], comp[Mês], ">="&G$2, comp[Mês], "<"&EOMONTH(G$2,0)+1 ) -> 0 | H3: =SUMIFS(comp[Saldo (Extratos)], comp[Mês], ">="&H$2, comp[Mês], "<"&EOMONTH(H$2,0)+1 ) -> 0 | I3: =SUMIFS(comp[Saldo (Extratos)], comp[Mês], ">="&I$2, comp[Mês], "<"&EOMONTH(I$2,0)+1 ) -> 4617374.5
B4: Fechamento | C4: =SUMIFS(comp[Saídas (Fechamento_E)], comp[Mês], ">="&C$2, comp[Mês], "<"&EOMONTH(C$2,0)+1 ) -> 0 | D4: =SUMIFS(comp[Saídas (Fechamento_E)], comp[Mês], ">="&D$2, comp[Mês], "<"&EOMONTH(D$2,0)+1 ) -> 0 | E4: =SUMIFS(comp[Saídas (Fechamento_E)], comp[Mês], ">="&E$2, comp[Mês], "<"&EOMONTH(E$2,0)+1 ) -> 0 | F4: =SUMIFS(comp[Saídas (Fechamento_E)], comp[Mês], ">="&F$2, comp[Mês], "<"&EOMONTH(F$2,0)+1 ) -> 0 | G4: =SUMIFS(comp[Saídas (Fechamento_E)], comp[Mês], ">="&G$2, comp[Mês], "<"&EOMONTH(G$2,0)+1 ) -> 0 | H4: =SUMIFS(comp[Saídas (Fechamento_E)], comp[Mês], ">="&H$2, comp[Mês], "<"&EOMONTH(H$2,0)+1 ) -> 0 | I4: =SUMIFS(comp[Saldo (Fechamento_E)], comp[Mês], ">="&I$2, comp[Mês], "<"&EOMONTH(I$2,0)+1 ) -> 0
B5: Informakon | C5: =SUMIFS(comp[Saídas (Informakon)], comp[Mês], ">="&C$2, comp[Mês], "<"&EOMONTH(C$2,0)+1 ) -> 0 | D5: =SUMIFS(comp[Saídas (Informakon)], comp[Mês], ">="&D$2, comp[Mês], "<"&EOMONTH(D$2,0)+1 ) -> 0 | E5: =SUMIFS(comp[Saídas (Informakon)], comp[Mês], ">="&E$2, comp[Mês], "<"&EOMONTH(E$2,0)+1 ) -> 0 | F5: =SUMIFS(comp[Saídas (Informakon)], comp[Mês], ">="&F$2, comp[Mês], "<"&EOMONTH(F$2,0)+1 ) -> 0 | G5: =SUMIFS(comp[Saídas (Informakon)], comp[Mês], ">="&G$2, comp[Mês], "<"&EOMONTH(G$2,0)+1 ) -> 0 | H5: =SUMIFS(comp[Saídas (Informakon)], comp[Mês], ">="&H$2, comp[Mês], "<"&EOMONTH(H$2,0)+1 ) -> 0 | I5: =SUMIFS(comp[Saídas (Informakon)], comp[Mês], ">="&I$2, comp[Mês], "<"&EOMONTH(I$2,0)+1 ) -> 26613317
B6: F - E | C6: =C4-C3 -> 0 | D6: =D4-D3 -> 0 | E6: =E4-E3 -> 0 | F6: =F4-F3 -> 0 | G6: =G4-G3 -> 0 | H6: =H4-H3 -> 0 | I6: =I4-I3 -> -4617374.5
B7: F - E (%) | C7: =IFERROR(C6/C3,"") | D7: =IFERROR(D6/D3,"") | E7: =IFERROR(E6/E3,"") | F7: =IFERROR(F6/F3,"") | G7: =IFERROR(G6/G3,"") | H7: =IFERROR(H6/H3,"") | I7: =IFERROR(I6/I3,"") -> -1
B8: I - E | C8: =C5-C3 -> 0 | D8: =D5-D3 -> 0 | E8: =E5-E3 -> 0 | F8: =F5-F3 -> 0 | G8: =G5-G3 -> 0 | H8: =H5-H3 -> 0 | I8: =I5-I3 -> 21995943
B9: I - E (%) | C9: =IFERROR(C8/C3,"") | D9: =IFERROR(D8/D3,"") | E9: =IFERROR(E8/E3,"") | F9: =IFERROR(F8/F3,"") | G9: =IFERROR(G8/G3,"") | H9: =IFERROR(H8/H3,"") | I9: =IFERROR(I8/I3,"") -> 4.7637337
B11: Empresa | C11: Mês | D11: Saldo (Extratos) | E11: Entradas (Informakon) | F11: Saídas (Informakon) | G11: Saldo (Informakon) | H11: Entradas (Fechamento_E) | I11: Saídas (Fechamento_E) | J11: Saldo (Fechamento_E) | K11: Saldo (Fechamento_N) | L11: F - E | M11: F - E (%) | N11: I - E | O11: I - E (%)
B12: AHA | C12: 46204 | E12: 5686.7 | F12: 5754.11 | G12: -67.41 | H12: =SUMIFS(tb_rec_uni[2026-07-01], tb_rec_uni[empresa], comp[[#This Row],[Empresa]]) -> 0 | I12: =SUMIFS(tb_desp[valor], tb_desp[empresa], comp[[#This Row],[Empresa]], tb_desp[data.pagamento], ">="&C12, tb_desp[data.pagamento], "<"&EOMONTH(C12,0)+1) -> 0 | J12: =comp[[#This Row],[Entradas (Fechamento_E)]]-comp[[#This Row],[Saídas (Fechamento_E)]] -> 0 | L12: =comp[[#This Row],[Saldo (Fechamento_E)]]-comp[[#This Row],[Saldo (Extratos)]] -> 0 | M12: =IFERROR(comp[[#This Row],[F - E]]/comp[[#This Row],[Saldo (Extratos)]], "") | N12: =comp[[#This Row],[Saldo (Informakon)]]-comp[[#This Row],[Saldo (Extratos)]] -> -67.41 | O12: =IFERROR(comp[[#This Row],[I - E]]/comp[[#This Row],[Saldo (Extratos)]], "")
B13: AMP | C13: 46204 | D13: 206747.71 | E13: 6646267.1 | F13: 6446216.2 | G13: 200050.96 | H13: =SUMIFS(tb_rec_uni[2026-07-01], tb_rec_uni[empresa], comp[[#This Row],[Empresa]]) -> 0 | I13: =SUMIFS(tb_desp[valor], tb_desp[empresa], comp[[#This Row],[Empresa]], tb_desp[data.pagamento], ">="&C13, tb_desp[data.pagamento], "<"&EOMONTH(C13,0)+1) -> 0 | J13: =comp[[#This Row],[Entradas (Fechamento_E)]]-comp[[#This Row],[Saídas (Fechamento_E)]] -> 0 | L13: =comp[[#This Row],[Saldo (Fechamento_E)]]-comp[[#This Row],[Saldo (Extratos)]] -> -206747.71 | M13: =IFERROR(comp[[#This Row],[F - E]]/comp[[#This Row],[Saldo (Extratos)]], "") -> -1 | N13: =comp[[#This Row],[Saldo (Informakon)]]-comp[[#This Row],[Saldo (Extratos)]] -> -6696.75 | O13: =IFERROR(comp[[#This Row],[I - E]]/comp[[#This Row],[Saldo (Extratos)]], "") -> -0.032390927
B14: AVR | C14: 46204 | D14: 0 | E14: 2500 | F14: 3110.63 | G14: -610.63 | H14: =SUMIFS(tb_rec_uni[2026-07-01], tb_rec_uni[empresa], comp[[#This Row],[Empresa]]) -> 0 | I14: =SUMIFS(tb_desp[valor], tb_desp[empresa], comp[[#This Row],[Empresa]], tb_desp[data.pagamento], ">="&C14, tb_desp[data.pagamento], "<"&EOMONTH(C14,0)+1) -> 0 | J14: =comp[[#This Row],[Entradas (Fechamento_E)]]-comp[[#This Row],[Saídas (Fechamento_E)]] -> 0 | L14: =comp[[#This Row],[Saldo (Fechamento_E)]]-comp[[#This Row],[Saldo (Extratos)]] -> 0 | M14: =IFERROR(comp[[#This Row],[F - E]]/comp[[#This Row],[Saldo (Extratos)]], "") | N14: =comp[[#This Row],[Saldo (Informakon)]]-comp[[#This Row],[Saldo (Extratos)]] -> -610.63 | O14: =IFERROR(comp[[#This Row],[I - E]]/comp[[#This Row],[Saldo (Extratos)]], "")
B15: AVS | C15: 46204 | D15: 25312.53 | E15: 274667.58 | F15: 248926.56 | G15: 25741.02 | H15: =SUMIFS(tb_rec_uni[2026-07-01], tb_rec_uni[empresa], comp[[#This Row],[Empresa]]) -> 0 | I15: =SUMIFS(tb_desp[valor], tb_desp[empresa], comp[[#This Row],[Empresa]], tb_desp[data.pagamento], ">="&C15, tb_desp[data.pagamento], "<"&EOMONTH(C15,0)+1) -> 0 | J15: =comp[[#This Row],[Entradas (Fechamento_E)]]-comp[[#This Row],[Saídas (Fechamento_E)]] -> 0 | K15: 3425.14 | L15: =comp[[#This Row],[Saldo (Fechamento_E)]]-comp[[#This Row],[Saldo (Extratos)]] -> -25312.53 | M15: =IFERROR(comp[[#This Row],[F - E]]/comp[[#This Row],[Saldo (Extratos)]], "") -> -1 | N15: =comp[[#This Row],[Saldo (Informakon)]]-comp[[#This Row],[Saldo (Extratos)]] -> 428.49 | O15: =IFERROR(comp[[#This Row],[I - E]]/comp[[#This Row],[Saldo (Extratos)]], "") -> 0.01692798
B16: BUT | C16: 46204 | D16: 11213.36 | E16: 357467.23 | F16: 212249.09 | G16: 145218.14 | H16: =SUMIFS(tb_rec_uni[2026-07-01], tb_rec_uni[empresa], comp[[#This Row],[Empresa]]) -> 0 | I16: =SUMIFS(tb_desp[valor], tb_desp[empresa], comp[[#This Row],[Empresa]], tb_desp[data.pagamento], ">="&C16, tb_desp[data.pagamento], "<"&EOMONTH(C16,0)+1) -> 0 | J16: =comp[[#This Row],[Entradas (Fechamento_E)]]-comp[[#This Row],[Saídas (Fechamento_E)]] -> 0 | L16: =comp[[#This Row],[Saldo (Fechamento_E)]]-comp[[#This Row],[Saldo (Extratos)]] -> -11213.36 | M16: =IFERROR(comp[[#This Row],[F - E]]/comp[[#This Row],[Saldo (Extratos)]], "") -> -1 | N16: =comp[[#This Row],[Saldo (Informakon)]]-comp[[#This Row],[Saldo (Extratos)]] -> 134004.78 | O16: =IFERROR(comp[[#This Row],[I - E]]/comp[[#This Row],[Saldo (Extratos)]], "") -> 11.950457
B17: CBL | C17: 46204 | D17: -4923.08 | E17: 1805276.1 | F17: 1877099.9 | G17: -71823.85 | H17: =SUMIFS(tb_rec_uni[2026-07-01], tb_rec_uni[empresa], comp[[#This Row],[Empresa]]) -> 0 | I17: =SUMIFS(tb_desp[valor], tb_desp[empresa], comp[[#This Row],[Empresa]], tb_desp[data.pagamento], ">="&C17, tb_desp[data.pagamento], "<"&EOMONTH(C17,0)+1) -> 0 | J17: =comp[[#This Row],[Entradas (Fechamento_E)]]-comp[[#This Row],[Saídas (Fechamento_E)]] -> 0 | K17: 1318960.2 | L17: =comp[[#This Row],[Saldo (Fechamento_E)]]-comp[[#This Row],[Saldo (Extratos)]] -> 4923.08 | M17: =IFERROR(comp[[#This Row],[F - E]]/comp[[#This Row],[Saldo (Extratos)]], "") -> -1 | N17: =comp[[#This Row],[Saldo (Informakon)]]-comp[[#This Row],[Saldo (Extratos)]] -> -66900.77 | O17: =IFERROR(comp[[#This Row],[I - E]]/comp[[#This Row],[Saldo (Extratos)]], "") -> 13.58921
B18: CHR | C18: 46204 | D18: 0 | H18: =SUMIFS(tb_rec_uni[2026-07-01], tb_rec_uni[empresa], comp[[#This Row],[Empresa]]) -> 0 | I18: =SUMIFS(tb_desp[valor], tb_desp[empresa], comp[[#This Row],[Empresa]], tb_desp[data.pagamento], ">="&C18, tb_desp[data.pagamento], "<"&EOMONTH(C18,0)+1) -> 0 | J18: =comp[[#This Row],[Entradas (Fechamento_E)]]-comp[[#This Row],[Saídas (Fechamento_E)]] -> 0 | L18: =comp[[#This Row],[Saldo (Fechamento_E)]]-comp[[#This Row],[Saldo (Extratos)]] -> 0 | M18: =IFERROR(comp[[#This Row],[F - E]]/comp[[#This Row],[Saldo (Extratos)]], "") | N18: =comp[[#This Row],[Saldo (Informakon)]]-comp[[#This Row],[Saldo (Extratos)]] -> 0 | O18: =IFERROR(comp[[#This Row],[I - E]]/comp[[#This Row],[Saldo (Extratos)]], "")
B19: CPE | C19: 46204 | D19: 8463.42 | E19: 387400 | F19: 390312.73 | G19: -2912.73 | H19: =SUMIFS(tb_rec_uni[2026-07-01], tb_rec_uni[empresa], comp[[#This Row],[Empresa]]) -> 0 | I19: =SUMIFS(tb_desp[valor], tb_desp[empresa], comp[[#This Row],[Empresa]], tb_desp[data.pagamento], ">="&C19, tb_desp[data.pagamento], "<"&EOMONTH(C19,0)+1) -> 0 | J19: =comp[[#This Row],[Entradas (Fechamento_E)]]-comp[[#This Row],[Saídas (Fechamento_E)]] -> 0 | L19: =comp[[#This Row],[Saldo (Fechamento_E)]]-comp[[#This Row],[Saldo (Extratos)]] -> -8463.42 | M19: =IFERROR(comp[[#This Row],[F - E]]/comp[[#This Row],[Saldo (Extratos)]], "") -> -1 | N19: =comp[[#This Row],[Saldo (Informakon)]]-comp[[#This Row],[Saldo (Extratos)]] -> -11376.15 | O19: =IFERROR(comp[[#This Row],[I - E]]/comp[[#This Row],[Saldo (Extratos)]], "") -> -1.3441552
B20: CXG | C20: 46204 | D20: 1168.4 | E20: 35000 | F20: 33282 | G20: 1718 | H20: =SUMIFS(tb_rec_uni[2026-07-01], tb_rec_uni[empresa], comp[[#This Row],[Empresa]]) -> 0 | I20: =SUMIFS(tb_desp[valor], tb_desp[empresa], comp[[#This Row],[Empresa]], tb_desp[data.pagamento], ">="&C20, tb_desp[data.pagamento], "<"&EOMONTH(C20,0)+1) -> 0 | J20: =comp[[#This Row],[Entradas (Fechamento_E)]]-comp[[#This Row],[Saídas (Fechamento_E)]] -> 0 | L20: =comp[[#This Row],[Saldo (Fechamento_E)]]-comp[[#This Row],[Saldo (Extratos)]] -> -1168.4 | M20: =IFERROR(comp[[#This Row],[F - E]]/comp[[#This Row],[Saldo (Extratos)]], "") -> -1 | N20: =comp[[#This Row],[Saldo (Informakon)]]-comp[[#This Row],[Saldo (Extratos)]] -> 549.6 | O20: =IFERROR(comp[[#This Row],[I - E]]/comp[[#This Row],[Saldo (Extratos)]], "") -> 0.47038685
B21: DPF | C21: 46204 | D21: -21136.73 | E21: 1049000 | F21: 1042223.2 | G21: 6776.83 | H21: =SUMIFS(tb_rec_uni[2026-07-01], tb_rec_uni[empresa], comp[[#This Row],[Empresa]]) -> 0 | I21: =SUMIFS(tb_desp[valor], tb_desp[empresa], comp[[#This Row],[Empresa]], tb_desp[data.pagamento], ">="&C21, tb_desp[data.pagamento], "<"&EOMONTH(C21,0)+1) -> 0 | J21: =comp[[#This Row],[Entradas (Fechamento_E)]]-comp[[#This Row],[Saídas (Fechamento_E)]] -> 0 | L21: =comp[[#This Row],[Saldo (Fechamento_E)]]-comp[[#This Row],[Saldo (Extratos)]] -> 21136.73 | M21: =IFERROR(comp[[#This Row],[F - E]]/comp[[#This Row],[Saldo (Extratos)]], "") -> -1 | N21: =comp[[#This Row],[Saldo (Informakon)]]-comp[[#This Row],[Saldo (Extratos)]] -> 27913.56 | O21: =IFERROR(comp[[#This Row],[I - E]]/comp[[#This Row],[Saldo (Extratos)]], "") -> -1.3206187
B22: ENC | C22: 46204 | D22: 223.48 | E22: 211000 | F22: 131536.3 | G22: 79463.7 | H22: =SUMIFS(tb_rec_uni[2026-07-01], tb_rec_uni[empresa], comp[[#This Row],[Empresa]]) -> 0 | I22: =SUMIFS(tb_desp[valor], tb_desp[empresa], comp[[#This Row],[Empresa]], tb_desp[data.pagamento], ">="&C22, tb_desp[data.pagamento], "<"&EOMONTH(C22,0)+1) -> 0 | J22: =comp[[#This Row],[Entradas (Fechamento_E)]]-comp[[#This Row],[Saídas (Fechamento_E)]] -> 0 | L22: =comp[[#This Row],[Saldo (Fechamento_E)]]-comp[[#This Row],[Saldo (Extratos)]] -> -223.48 | M22: =IFERROR(comp[[#This Row],[F - E]]/comp[[#This Row],[Saldo (Extratos)]], "") -> -1 | N22: =comp[[#This Row],[Saldo (Informakon)]]-comp[[#This Row],[Saldo (Extratos)]] -> 79240.22 | O22: =IFERROR(comp[[#This Row],[I - E]]/comp[[#This Row],[Saldo (Extratos)]], "") -> 354.5741
B23: GRA | C23: 46204 | D23: 1132043 | E23: 4180443 | F23: 2875979.3 | G23: 1304463.7 | H23: =SUMIFS(tb_rec_uni[2026-07-01], tb_rec_uni[empresa], comp[[#This Row],[Empresa]]) -> 0 | I23: =SUMIFS(tb_desp[valor], tb_desp[empresa], comp[[#This Row],[Empresa]], tb_desp[data.pagamento], ">="&C23, tb_desp[data.pagamento], "<"&EOMONTH(C23,0)+1) -> 0 | J23: =comp[[#This Row],[Entradas (Fechamento_E)]]-comp[[#This Row],[Saídas (Fechamento_E)]] -> 0 | K23: 872377.65 | L23: =comp[[#This Row],[Saldo (Fechamento_E)]]-comp[[#This Row],[Saldo (Extratos)]] -> -1132043 | M23: =IFERROR(comp[[#This Row],[F - E]]/comp[[#This Row],[Saldo (Extratos)]], "") -> -1 | N23: =comp[[#This Row],[Saldo (Informakon)]]-comp[[#This Row],[Saldo (Extratos)]] -> 172420.74 | O23: =IFERROR(comp[[#This Row],[I - E]]/comp[[#This Row],[Saldo (Extratos)]], "") -> 0.15230936
B24: INC | C24: 46204 | D24: 17890.28 | E24: 175009.36 | F24: 129335.78 | G24: 45673.58 | H24: =SUMIFS(tb_rec_uni[2026-07-01], tb_rec_uni[empresa], comp[[#This Row],[Empresa]]) -> 0 | I24: =SUMIFS(tb_desp[valor], tb_desp[empresa], comp[[#This Row],[Empresa]], tb_desp[data.pagamento], ">="&C24, tb_desp[data.pagamento], "<"&EOMONTH(C24,0)+1) -> 0 | J24: =comp[[#This Row],[Entradas (Fechamento_E)]]-comp[[#This Row],[Saídas (Fechamento_E)]] -> 0 | L24: =comp[[#This Row],[Saldo (Fechamento_E)]]-comp[[#This Row],[Saldo (Extratos)]] -> -17890.28 | M24: =IFERROR(comp[[#This Row],[F - E]]/comp[[#This Row],[Saldo (Extratos)]], "") -> -1 | N24: =comp[[#This Row],[Saldo (Informakon)]]-comp[[#This Row],[Saldo (Extratos)]] -> 27783.3 | O24: =IFERROR(comp[[#This Row],[I - E]]/comp[[#This Row],[Saldo (Extratos)]], "") -> 1.552983
B25: JRP | C25: 46204 | D25: -67106.97 | E25: 394785.94 | F25: 493109.38 | G25: -98323.44 | H25: =SUMIFS(tb_rec_uni[2026-07-01], tb_rec_uni[empresa], comp[[#This Row],[Empresa]]) -> 0 | I25: =SUMIFS(tb_desp[valor], tb_desp[empresa], comp[[#This Row],[Empresa]], tb_desp[data.pagamento], ">="&C25, tb_desp[data.pagamento], "<"&EOMONTH(C25,0)+1) -> 0 | J25: =comp[[#This Row],[Entradas (Fechamento_E)]]-comp[[#This Row],[Saídas (Fechamento_E)]] -> 0 | L25: =comp[[#This Row],[Saldo (Fechamento_E)]]-comp[[#This Row],[Saldo (Extratos)]] -> 67106.97 | M25: =IFERROR(comp[[#This Row],[F - E]]/comp[[#This Row],[Saldo (Extratos)]], "") -> -1 | N25: =comp[[#This Row],[Saldo (Informakon)]]-comp[[#This Row],[Saldo (Extratos)]] -> -31216.47 | O25: =IFERROR(comp[[#This Row],[I - E]]/comp[[#This Row],[Saldo (Extratos)]], "") -> 0.46517478
B26: JSP | C26: 46204 | D26: -165.28 | E26: 0.03 | F26: 22000 | G26: -21999.97 | H26: =SUMIFS(tb_rec_uni[2026-07-01], tb_rec_uni[empresa], comp[[#This Row],[Empresa]]) -> 0 | I26: =SUMIFS(tb_desp[valor], tb_desp[empresa], comp[[#This Row],[Empresa]], tb_desp[data.pagamento], ">="&C26, tb_desp[data.pagamento], "<"&EOMONTH(C26,0)+1) -> 0 | J26: =comp[[#This Row],[Entradas (Fechamento_E)]]-comp[[#This Row],[Saídas (Fechamento_E)]] -> 0 | L26: =comp[[#This Row],[Saldo (Fechamento_E)]]-comp[[#This Row],[Saldo (Extratos)]] -> 165.28 | M26: =IFERROR(comp[[#This Row],[F - E]]/comp[[#This Row],[Saldo (Extratos)]], "") -> -1 | N26: =comp[[#This Row],[Saldo (Informakon)]]-comp[[#This Row],[Saldo (Extratos)]] -> -21834.69 | O26: =IFERROR(comp[[#This Row],[I - E]]/comp[[#This Row],[Saldo (Extratos)]], "") -> 132.10727
B27: LCG | C27: 46204 | D27: -3036.6 | E27: 0 | F27: 22330.6 | G27: -22330.6 | H27: =SUMIFS(tb_rec_uni[2026-07-01], tb_rec_uni[empresa], comp[[#This Row],[Empresa]]) -> 0 | I27: =SUMIFS(tb_desp[valor], tb_desp[empresa], comp[[#This Row],[Empresa]], tb_desp[data.pagamento], ">="&C27, tb_desp[data.pagamento], "<"&EOMONTH(C27,0)+1) -> 0 | J27: =comp[[#This Row],[Entradas (Fechamento_E)]]-comp[[#This Row],[Saídas (Fechamento_E)]] -> 0 | L27: =comp[[#This Row],[Saldo (Fechamento_E)]]-comp[[#This Row],[Saldo (Extratos)]] -> 3036.6 | M27: =IFERROR(comp[[#This Row],[F - E]]/comp[[#This Row],[Saldo (Extratos)]], "") -> -1 | N27: =comp[[#This Row],[Saldo (Informakon)]]-comp[[#This Row],[Saldo (Extratos)]] -> -19294 | O27: =IFERROR(comp[[#This Row],[I - E]]/comp[[#This Row],[Saldo (Extratos)]], "") -> 6.3538168
B28: LUC | C28: 46204 | D28: -6799.85 | E28: 2588920.7 | F28: 2747449.5 | G28: -158528.78 | H28: =SUMIFS(tb_rec_uni[2026-07-01], tb_rec_uni[empresa], comp[[#This Row],[Empresa]]) -> 0 | I28: =SUMIFS(tb_desp[valor], tb_desp[empresa], comp[[#This Row],[Empresa]], tb_desp[data.pagamento], ">="&C28, tb_desp[data.pagamento], "<"&EOMONTH(C28,0)+1) -> 0 | J28: =comp[[#This Row],[Entradas (Fechamento_E)]]-comp[[#This Row],[Saídas (Fechamento_E)]] -> 0 | K28: -594166.5 | L28: =comp[[#This Row],[Saldo (Fechamento_E)]]-comp[[#This Row],[Saldo (Extratos)]] -> 6799.85 | M28: =IFERROR(comp[[#This Row],[F - E]]/comp[[#This Row],[Saldo (Extratos)]], "") -> -1 | N28: =comp[[#This Row],[Saldo (Informakon)]]-comp[[#This Row],[Saldo (Extratos)]] -> -151728.93 | O28: =IFERROR(comp[[#This Row],[I - E]]/comp[[#This Row],[Saldo (Extratos)]], "") -> 22.31357
B29: LUG | C29: 46204 | D29: 9081.15 | E29: 209000 | F29: 340892.37 | G29: -131892.37 | H29: =SUMIFS(tb_rec_uni[2026-07-01], tb_rec_uni[empresa], comp[[#This Row],[Empresa]]) -> 0 | I29: =SUMIFS(tb_desp[valor], tb_desp[empresa], comp[[#This Row],[Empresa]], tb_desp[data.pagamento], ">="&C29, tb_desp[data.pagamento], "<"&EOMONTH(C29,0)+1) -> 0 | J29: =comp[[#This Row],[Entradas (Fechamento_E)]]-comp[[#This Row],[Saídas (Fechamento_E)]] -> 0 | L29: =comp[[#This Row],[Saldo (Fechamento_E)]]-comp[[#This Row],[Saldo (Extratos)]] -> -9081.15 | M29: =IFERROR(comp[[#This Row],[F - E]]/comp[[#This Row],[Saldo (Extratos)]], "") -> -1 | N29: =comp[[#This Row],[Saldo (Informakon)]]-comp[[#This Row],[Saldo (Extratos)]] -> -140973.52 | O29: =IFERROR(comp[[#This Row],[I - E]]/comp[[#This Row],[Saldo (Extratos)]], "") -> -15.523752
B30: POM | C30: 46204 | D30: 98661.88 | E30: 936909.96 | F30: 738615.98 | G30: 198293.98 | H30: =SUMIFS(tb_rec_uni[2026-07-01], tb_rec_uni[empresa], comp[[#This Row],[Empresa]]) -> 0 | I30: =SUMIFS(tb_desp[valor], tb_desp[empresa], comp[[#This Row],[Empresa]], tb_desp[data.pagamento], ">="&C30, tb_desp[data.pagamento], "<"&EOMONTH(C30,0)+1) -> 0 | J30: =comp[[#This Row],[Entradas (Fechamento_E)]]-comp[[#This Row],[Saídas (Fechamento_E)]] -> 0 | K30: 206515.12 | L30: =comp[[#This Row],[Saldo (Fechamento_E)]]-comp[[#This Row],[Saldo (Extratos)]] -> -98661.88 | M30: =IFERROR(comp[[#This Row],[F - E]]/comp[[#This Row],[Saldo (Extratos)]], "") -> -1 | N30: =comp[[#This Row],[Saldo (Informakon)]]-comp[[#This Row],[Saldo (Extratos)]] -> 99632.1 | O30: =IFERROR(comp[[#This Row],[I - E]]/comp[[#This Row],[Saldo (Extratos)]], "") -> 1.0098338
B31: PRO | C31: 46204 | E31: 45490.55 | F31: 0 | G31: 45490.55 | H31: =SUMIFS(tb_rec_uni[2026-07-01], tb_rec_uni[empresa], comp[[#This Row],[Empresa]]) -> 0 | I31: =SUMIFS(tb_desp[valor], tb_desp[empresa], comp[[#This Row],[Empresa]], tb_desp[data.pagamento], ">="&C31, tb_desp[data.pagamento], "<"&EOMONTH(C31,0)+1) -> 0 | J31: =comp[[#This Row],[Entradas (Fechamento_E)]]-comp[[#This Row],[Saídas (Fechamento_E)]] -> 0 | L31: =comp[[#This Row],[Saldo (Fechamento_E)]]-comp[[#This Row],[Saldo (Extratos)]] -> 0 | M31: =IFERROR(comp[[#This Row],[F - E]]/comp[[#This Row],[Saldo (Extratos)]], "") | N31: =comp[[#This Row],[Saldo (Informakon)]]-comp[[#This Row],[Saldo (Extratos)]] -> 45490.55 | O31: =IFERROR(comp[[#This Row],[I - E]]/comp[[#This Row],[Saldo (Extratos)]], "")
B32: SAU | C32: 46204 | D32: -280690.27 | E32: 272650.1 | F32: 493903.79 | G32: -221253.69 | H32: =SUMIFS(tb_rec_uni[2026-07-01], tb_rec_uni[empresa], comp[[#This Row],[Empresa]]) -> 0 | I32: =SUMIFS(tb_desp[valor], tb_desp[empresa], comp[[#This Row],[Empresa]], tb_desp[data.pagamento], ">="&C32, tb_desp[data.pagamento], "<"&EOMONTH(C32,0)+1) -> 0 | J32: =comp[[#This Row],[Entradas (Fechamento_E)]]-comp[[#This Row],[Saídas (Fechamento_E)]] -> 0 | K32: -148872.84 | L32: =comp[[#This Row],[Saldo (Fechamento_E)]]-comp[[#This Row],[Saldo (Extratos)]] -> 280690.27 | M32: =IFERROR(comp[[#This Row],[F - E]]/comp[[#This Row],[Saldo (Extratos)]], "") -> -1 | N32: =comp[[#This Row],[Saldo (Informakon)]]-comp[[#This Row],[Saldo (Extratos)]] -> 59436.58 | O32: =IFERROR(comp[[#This Row],[I - E]]/comp[[#This Row],[Saldo (Extratos)]], "") -> -0.21175148
B33: SBB | C33: 46204 | D33: 107.08 | E33: 15001.28 | F33: 15004.03 | G33: -2.75 | H33: =SUMIFS(tb_rec_uni[2026-07-01], tb_rec_uni[empresa], comp[[#This Row],[Empresa]]) -> 0 | I33: =SUMIFS(tb_desp[valor], tb_desp[empresa], comp[[#This Row],[Empresa]], tb_desp[data.pagamento], ">="&C33, tb_desp[data.pagamento], "<"&EOMONTH(C33,0)+1) -> 0 | J33: =comp[[#This Row],[Entradas (Fechamento_E)]]-comp[[#This Row],[Saídas (Fechamento_E)]] -> 0 | L33: =comp[[#This Row],[Saldo (Fechamento_E)]]-comp[[#This Row],[Saldo (Extratos)]] -> -107.08 | M33: =IFERROR(comp[[#This Row],[F - E]]/comp[[#This Row],[Saldo (Extratos)]], "") -> -1 | N33: =comp[[#This Row],[Saldo (Informakon)]]-comp[[#This Row],[Saldo (Extratos)]] -> -109.83 | O33: =IFERROR(comp[[#This Row],[I - E]]/comp[[#This Row],[Saldo (Extratos)]], "") -> -1.0256817
B34: SN2 | C34: 46204 | D34: 2269810.9 | E34: 5184374.8 | F34: 3369826.1 | G34: 1814548.7 | H34: =SUMIFS(tb_rec_uni[2026-07-01], tb_rec_uni[empresa], comp[[#This Row],[Empresa]]) -> 0 | I34: =SUMIFS(tb_desp[valor], tb_desp[empresa], comp[[#This Row],[Empresa]], tb_desp[data.pagamento], ">="&C34, tb_desp[data.pagamento], "<"&EOMONTH(C34,0)+1) -> 0 | J34: =comp[[#This Row],[Entradas (Fechamento_E)]]-comp[[#This Row],[Saídas (Fechamento_E)]] -> 0 | K34: 2847456.1 | L34: =comp[[#This Row],[Saldo (Fechamento_E)]]-comp[[#This Row],[Saldo (Extratos)]] -> -2269810.9 | M34: =IFERROR(comp[[#This Row],[F - E]]/comp[[#This Row],[Saldo (Extratos)]], "") -> -1 | N34: =comp[[#This Row],[Saldo (Informakon)]]-comp[[#This Row],[Saldo (Extratos)]] -> -455262.1 | O34: =IFERROR(comp[[#This Row],[I - E]]/comp[[#This Row],[Saldo (Extratos)]], "") -> -0.2005727
B35: SN4 | C35: 46204 | D35: 1197944.5 | E35: 7092012.8 | F35: 4971788.5 | G35: 2120224.4 | H35: =SUMIFS(tb_rec_uni[2026-07-01], tb_rec_uni[empresa], comp[[#This Row],[Empresa]]) -> 0 | I35: =SUMIFS(tb_desp[valor], tb_desp[empresa], comp[[#This Row],[Empresa]], tb_desp[data.pagamento], ">="&C35, tb_desp[data.pagamento], "<"&EOMONTH(C35,0)+1) -> 0 | J35: =comp[[#This Row],[Entradas (Fechamento_E)]]-comp[[#This Row],[Saídas (Fechamento_E)]] -> 0 | K35: 3696844 | L35: =comp[[#This Row],[Saldo (Fechamento_E)]]-comp[[#This Row],[Saldo (Extratos)]] -> -1197944.5 | M35: =IFERROR(comp[[#This Row],[F - E]]/comp[[#This Row],[Saldo (Extratos)]], "") -> -1 | N35: =comp[[#This Row],[Saldo (Informakon)]]-comp[[#This Row],[Saldo (Extratos)]] -> 922279.89 | O35: =IFERROR(comp[[#This Row],[I - E]]/comp[[#This Row],[Saldo (Extratos)]], "") -> 0.76988533
B36: SOC | C36: 46204 | D36: -1626.96 | E36: 0.32 | F36: 1630.29 | G36: -1629.97 | H36: =SUMIFS(tb_rec_uni[2026-07-01], tb_rec_uni[empresa], comp[[#This Row],[Empresa]]) -> 0 | I36: =SUMIFS(tb_desp[valor], tb_desp[empresa], comp[[#This Row],[Empresa]], tb_desp[data.pagamento], ">="&C36, tb_desp[data.pagamento], "<"&EOMONTH(C36,0)+1) -> 0 | J36: =comp[[#This Row],[Entradas (Fechamento_E)]]-comp[[#This Row],[Saídas (Fechamento_E)]] -> 0 | L36: =comp[[#This Row],[Saldo (Fechamento_E)]]-comp[[#This Row],[Saldo (Extratos)]] -> 1626.96 | M36: =IFERROR(comp[[#This Row],[F - E]]/comp[[#This Row],[Saldo (Extratos)]], "") -> -1 | N36: =comp[[#This Row],[Saldo (Informakon)]]-comp[[#This Row],[Saldo (Extratos)]] -> -3.01 | O36: =IFERROR(comp[[#This Row],[I - E]]/comp[[#This Row],[Saldo (Extratos)]], "") -> 0.0018500762
B37: VII | C37: 46204 | D37: 24977.84 | E37: 0 | F37: 277.37 | G37: -277.37 | H37: =SUMIFS(tb_rec_uni[2026-07-01], tb_rec_uni[empresa], comp[[#This Row],[Empresa]]) -> 0 | I37: =SUMIFS(tb_desp[valor], tb_desp[empresa], comp[[#This Row],[Empresa]], tb_desp[data.pagamento], ">="&C37, tb_desp[data.pagamento], "<"&EOMONTH(C37,0)+1) -> 0 | J37: =comp[[#This Row],[Entradas (Fechamento_E)]]-comp[[#This Row],[Saídas (Fechamento_E)]] -> 0 | L37: =comp[[#This Row],[Saldo (Fechamento_E)]]-comp[[#This Row],[Saldo (Extratos)]] -> -24977.84 | M37: =IFERROR(comp[[#This Row],[F - E]]/comp[[#This Row],[Saldo (Extratos)]], "") -> -1 | N37: =comp[[#This Row],[Saldo (Informakon)]]-comp[[#This Row],[Saldo (Extratos)]] -> -25255.21 | O37: =IFERROR(comp[[#This Row],[I - E]]/comp[[#This Row],[Saldo (Extratos)]], "") -> -1.0111046
B38: VRG | C38: 46204 | D38: 0 | E38: 24694.1 | F38: 463.39 | G38: 24230.71 | H38: =SUMIFS(tb_rec_uni[2026-07-01], tb_rec_uni[empresa], comp[[#This Row],[Empresa]]) -> 0 | I38: =SUMIFS(tb_desp[valor], tb_desp[empresa], comp[[#This Row],[Empresa]], tb_desp[data.pagamento], ">="&C38, tb_desp[data.pagamento], "<"&EOMONTH(C38,0)+1) -> 0 | J38: =comp[[#This Row],[Entradas (Fechamento_E)]]-comp[[#This Row],[Saídas (Fechamento_E)]] -> 0 | L38: =comp[[#This Row],[Saldo (Fechamento_E)]]-comp[[#This Row],[Saldo (Extratos)]] -> 0 | M38: =IFERROR(comp[[#This Row],[F - E]]/comp[[#This Row],[Saldo (Extratos)]], "") | N38: =comp[[#This Row],[Saldo (Informakon)]]-comp[[#This Row],[Saldo (Extratos)]] -> 24230.71 | O38: =IFERROR(comp[[#This Row],[I - E]]/comp[[#This Row],[Saldo (Extratos)]], "")
B39: VRT | C39: 46204 | D39: -785.2 | H39: =SUMIFS(tb_rec_uni[2026-07-01], tb_rec_uni[empresa], comp[[#This Row],[Empresa]]) -> 0 | I39: =SUMIFS(tb_desp[valor], tb_desp[empresa], comp[[#This Row],[Empresa]], tb_desp[data.pagamento], ">="&C39, tb_desp[data.pagamento], "<"&EOMONTH(C39,0)+1) -> 0 | J39: =comp[[#This Row],[Entradas (Fechamento_E)]]-comp[[#This Row],[Saídas (Fechamento_E)]] -> 0 | L39: =comp[[#This Row],[Saldo (Fechamento_E)]]-comp[[#This Row],[Saldo (Extratos)]] -> 785.2 | M39: =IFERROR(comp[[#This Row],[F - E]]/comp[[#This Row],[Saldo (Extratos)]], "") -> -1 | N39: =comp[[#This Row],[Saldo (Informakon)]]-comp[[#This Row],[Saldo (Extratos)]] -> 785.2 | O39: =IFERROR(comp[[#This Row],[I - E]]/comp[[#This Row],[Saldo (Extratos)]], "") -> -1

Sheet cmf
A1: Nº Mov | B1: Data | C1: C | D1: Origem | E1: Histórico | F1: AgenteFinanceiro | G1: Conta Nº | H1: Valor | I1: D/C | J1: V | K1: Cancelado | L1: Nat | M1: Natureza do Movimento | N1: Emp-Filial | O1: Núcleo | P1: Conciliação | Q1: Cliente | R1: Link Natureza | S1: Saldo Caução Cliente | U1: Entradas | V1: =SUMIFS(cmf[Valor], cmf[D/C],"C" ) -> 35692706
A2: 67892 | B2: 46204 | C2: N | D2: IMOBT | E2: RECEITA DO IMOBILIÁRIO | F2: Banco Bradesco | G2: 3635-8 | H2: 28164.28 | I2: C | J2: =IF(cmf[[#This Row],[D/C]]="C",cmf[[#This Row],[Valor]],-1*cmf[[#This Row],[Valor]]) -> 28164.28 | L2: RI | M2: Recebimento imobiliário | N2: VRG.01 | O2: 54 | S2: 0 | U2: Saídas | V2: =SUMIFS(cmf[Valor], cmf[D/C],"D" ) -> 31257794
A3: 67932 | B3: 46204 | C3: C | D3: IMOBT | E3: RECEITA DO IMOBILIÁRIO | F3: Caixa Econômica Federal | G3: 579133363-0 | H3: 539.26 | I3: C | J3: =IF(cmf[[#This Row],[D/C]]="C",cmf[[#This Row],[Valor]],-1*cmf[[#This Row],[Valor]]) -> 539.26 | L3: RI | M3: Recebimento imobiliário | N3: GRA.01 | O3: 25 | P3: 46204 | S3: 0 | U3: Variação | V3: =V1-V2 -> 4434912.2
A4: 67933 | B4: 46204 | C4: C | D4: IMOBT | E4: CUSTO DE COBRANÇA | F4: Caixa Econômica Federal | G4: 579133363-0 | H4: 6.3 | I4: D | J4: =IF(cmf[[#This Row],[D/C]]="C",cmf[[#This Row],[Valor]],-1*cmf[[#This Row],[Valor]]) -> -6.3 | L4: CC | M4: Custo de cobrança | N4: GRA.01 | O4: 25 | P4: 46204 | S4: 0 | U4: Número de entradas | V4: =COUNTIFS(cmf[D/C],"C") -> 893
A5: 68106 | B5: 46204 | C5: C | D5: IMOBT | E5: RECEITA DO IMOBILIÁRIO | F5: ABC do Brasil | G5: 22924479 | H5: 866.18 | I5: C | J5: =IF(cmf[[#This Row],[D/C]]="C",cmf[[#This Row],[Valor]],-1*cmf[[#This Row],[Valor]]) -> 866.18 | L5: RI | M5: Recebimento imobiliário | N5: POM.01 | O5: 24 | P5: 46204 | S5: 0 | U5: Número de saídas | V5: =COUNTIFS(cmf[D/C],"D") -> 1951
A6: 68108 | B6: 46204 | C6: N | D6: IMOBT | E6: RECEITA DO IMOBILIÁRIO | F6: Banco Itaú | G6: 99804-0 | H6: 2415.97 | I6: C | J6: =IF(cmf[[#This Row],[D/C]]="C",cmf[[#This Row],[Valor]],-1*cmf[[#This Row],[Valor]]) -> 2415.97 | L6: RI | M6: Recebimento imobiliário | N6: PRO.01 | O6: 25 | S6: 0 | U6: Número de lançamentos | V6: =SUM(V4:V5) -> 2844
A7: 68109 | B7: 46204 | C7: N | D7: IMOBT | E7: CUSTO DE COBRANÇA | F7: Banco Itaú | G7: 99804-0 | H7: 2.3 | I7: D | J7: =IF(cmf[[#This Row],[D/C]]="C",cmf[[#This Row],[Valor]],-1*cmf[[#This Row],[Valor]]) -> -2.3 | L7: CC | M7: Custo de cobrança | N7: PRO.01 | O7: 25 | S7: 0
A8: 68143 | B8: 46204 | C8: C | D8: SIPAG | E8: ESP.01 001087 - IT RR PARAFUSOS , FERRAGENS E FERRAMENTAS L | F8: Banco Itaú | G8: 99725-0 | H8: 1505.37 | I8: D | J8: =IF(cmf[[#This Row],[D/C]]="C",cmf[[#This Row],[Valor]],-1*cmf[[#This Row],[Valor]]) -> -1505.37 | L8: LP | M8: Lançamentos SIPAG | N8: GRA.01 | O8: 25 | P8: 46204 | S8: 0
A9: 68144 | B9: 46204 | C9: C | D9: SIPAG | E9: ESP.01 001088 - IT LEONARDO DE PAULA SANTOS 32445757819 | F9: Banco Itaú | G9: 99725-0 | H9: 0.03 | I9: D | J9: =IF(cmf[[#This Row],[D/C]]="C",cmf[[#This Row],[Valor]],-1*cmf[[#This Row],[Valor]]) -> -0.03 | L9: LP | M9: Lançamentos SIPAG | N9: GRA.01 | O9: 25 | P9: 46204 | S9: 0
A10: 68145 | B10: 46204 | C10: C | D10: SIPAG | E10: ESP.01 000963 - IT 6 OFICIAL DE REGISTRO DE IMOVEIS DA COMA | F10: Banco Itaú | G10: 99715-1 | H10: 2338.85 | I10: D | J10: =IF(cmf[[#This Row],[D/C]]="C",cmf[[#This Row],[Valor]],-1*cmf[[#This Row],[Valor]]) -> -2338.85 | L10: LP | M10: Lançamentos SIPAG | N10: LUC.01 | O10: 23 | P10: 46204 | S10: 0
A11: 68146 | B11: 46204 | C11: C | D11: SIPAG | E11: ESP.01 000964 - IT 6 OFICIAL DE REGISTRO DE IMOVEIS DA COMA | F11: Banco Itaú | G11: 99715-1 | H11: 2234.49 | I11: D | J11: =IF(cmf[[#This Row],[D/C]]="C",cmf[[#This Row],[Valor]],-1*cmf[[#This Row],[Valor]]) -> -2234.49 | L11: LP | M11: Lançamentos SIPAG | N11: LUC.01 | O11: 23 | P11: 46204 | S11: 0
A12: 68147 | B12: 46204 | C12: C | D12: SIPAG | E12: ESP.01 000965 - IT 6 OFICIAL DE REGISTRO DE IMOVEIS DA COMA | F12: Banco Itaú | G12: 99715-1 | H12: 2234.49 | I12: D | J12: =IF(cmf[[#This Row],[D/C]]="C",cmf[[#This Row],[Valor]],-1*cmf[[#This Row],[Valor]]) -> -2234.49 | L12: LP | M12: Lançamentos SIPAG | N12: LUC.01 | O12: 23 | P12: 46204 | S12: 0
A13: 68148 | B13: 46204 | C13: C | D13: SIPAG | E13: ESP.01 000966 - IT 6 OFICIAL DE REGISTRO DE IMOVEIS DA COMA | F13: Banco Itaú | G13: 99715-1 | H13: 2234.49 | I13: D | J13: =IF(cmf[[#This Row],[D/C]]="C",cmf[[#This Row],[Valor]],-1*cmf[[#This Row],[Valor]]) -> -2234.49 | L13: LP | M13: Lançamentos SIPAG | N13: LUC.01 | O13: 23 | P13: 46204 | S13: 0
A14: 68149 | B14: 46204 | C14: C | D14: SIPAG | E14: ESP.01 000967 - IT 6 OFICIAL DE REGISTRO DE IMOVEIS DA COMA | F14: Banco Itaú | G14: 99715-1 | H14: 1922.79 | I14: D | J14: =IF(cmf[[#This Row],[D/C]]="C",cmf[[#This Row],[Valor]],-1*cmf[[#This Row],[Valor]]) -> -1922.79 | L14: LP | M14: Lançamentos SIPAG | N14: LUC.01 | O14: 23 | P14: 46204 | S14: 0
A15: 68150 | B15: 46204 | C15: C | D15: SIPAG | E15: ESP.01 000968 - IT 6 OFICIAL DE REGISTRO DE IMOVEIS DA COMA | F15: Banco Itaú | G15: 99715-1 | H15: 1922.79 | I15: D | J15: =IF(cmf[[#This Row],[D/C]]="C",cmf[[#This Row],[Valor]],-1*cmf[[#This Row],[Valor]]) -> -1922.79 | L15: LP | M15: Lançamentos SIPAG | N15: LUC.01 | O15: 23 | P15: 46204 | S15: 0
A16: 68151 | B16: 46204 | C16: C | D16: SIPAG | E16: ESP.01 000322 - IT ELETROPAULO METROPOLITANA ELETRICIDADE D | F16: Banco Itaú | G16: 99660-9 | H16: 31.37 | I16: D | J16: =IF(cmf[[#This Row],[D/C]]="C",cmf[[#This Row],[Valor]],-1*cmf[[#This Row],[Valor]]) -> -31.37 | L16: LP | M16: Lançamentos SIPAG | N16: SAU.01 | O16: 31 | P16: 46204 | S16: 0
A17: 68214 | B17: 46204 | C17: N | D17: SIPAG | E17: ESP.01 000030 - IT Ronaldo Evangelista Rocha | F17: Banco Itaú | G17: 99267-3 | H17: 1250 | I17: D | J17: =IF(cmf[[#This Row],[D/C]]="C",cmf[[#This Row],[Valor]],-1*cmf[[#This Row],[Valor]]) -> -1250 | L17: LP | M17: Lançamentos SIPAG | N17: USL.01 | O17: 34 | S17: 0
A18: 68233 | B18: 46204 | C18: N | D18: COEMP | E18: Encontro de Contas - Envio Destino: CPE | F18: Caixa Econômica Federal | G18: 586376394-5 | H18: 4000 | I18: D | J18: =IF(cmf[[#This Row],[D/C]]="C",cmf[[#This Row],[Valor]],-1*cmf[[#This Row],[Valor]]) -> -4000 | L18: CE | M18: Coligadas | N18: DPF.01 | O18: 32 | S18: 0
A19: 68234 | B19: 46204 | C19: N | D19: COEMP | E19: Encontro de Contas - Recebe Origem: DPF | F19: Caixa Econômica Federal | G19: 577565836-8 | H19: 4000 | I19: C | J19: =IF(cmf[[#This Row],[D/C]]="C",cmf[[#This Row],[Valor]],-1*cmf[[#This Row],[Valor]]) -> 4000 | L19: CE | M19: Coligadas | N19: CPE.01 | O19: 37 | S19: 0
A20: 68235 | B20: 46204 | C20: C | D20: COEMP | E20: Encontro de Contas - Envio Destino: AMP | F20: Caixa Econômica Federal | G20: 579133332-0 | H20: 174000 | I20: D | J20: =IF(cmf[[#This Row],[D/C]]="C",cmf[[#This Row],[Valor]],-1*cmf[[#This Row],[Valor]]) -> -174000 | L20: CE | M20: Coligadas | N20: AMP.01 | O20: 07 | P20: 46204 | S20: 0
A21: 68236 | B21: 46204 | C21: C | D21: COEMP | E21: Encontro de Contas - Recebe Origem: AMP | F21: Banco Itaú | G21: 06340-0 | H21: 174000 | I21: C | J21: =IF(cmf[[#This Row],[D/C]]="C",cmf[[#This Row],[Valor]],-1*cmf[[#This Row],[Valor]]) -> 174000 | L21: CE | M21: Coligadas | N21: AMP.01 | O21: 20 | P21: 46204 | S21: 0
A22: 68237 | B22: 46204 | C22: N | D22: IMOBT | E22: CUSTO DE COBRANÇA | F22: Banco Bradesco | G22: 3635-8 | H22: 463.39 | I22: D | J22: =IF(cmf[[#This Row],[D/C]]="C",cmf[[#This Row],[Valor]],-1*cmf[[#This Row],[Valor]]) -> -463.39 | L22: CC | M22: Custo de cobrança | N22: VRG.01 | O22: 54 | S22: 0
A23: 68260 | B23: 46204 | C23: N | D23: IMOBT | E23: CUSTO DE COBRANÇA | F23: QI Tech | G23: 1601332-7 | H23: 332 | I23: D | J23: =IF(cmf[[#This Row],[D/C]]="C",cmf[[#This Row],[Valor]],-1*cmf[[#This Row],[Valor]]) -> -332 | L23: CC | M23: Custo de cobrança | N23: SN2.01 | O23: 26 | S23: 0
A24: 68262 | B24: 46204 | C24: C | D24: SIPAG | E24: ESP.01 000726 - IT IR ARTE E COR PINTURAS RESIDENCIAL E PRE | F24: ABC do Brasil | G24: 22924479 | H24: 40850 | I24: D | J24: =IF(cmf[[#This Row],[D/C]]="C",cmf[[#This Row],[Valor]],-1*cmf[[#This Row],[Valor]]) -> -40850 | L24: LP | M24: Lançamentos SIPAG | N24: POM.01 | O24: 24 | P24: 46204 | S24: 0
A25: 68263 | B25: 46204 | C25: C | D25: SIPAG | E25: ESP.01 000350 - IT ELETROPAULO METROPOLITANA ELETRICIDADE D | F25: Banco Itaú | G25: 99664-1 | H25: 292.36 | I25: D | J25: =IF(cmf[[#This Row],[D/C]]="C",cmf[[#This Row],[Valor]],-1*cmf[[#This Row],[Valor]]) -> -292.36 | L25: LP | M25: Lançamentos SIPAG | N25: SN4.01 | O25: 39 | P25: 46204 | S25: 0
A26: 68264 | B26: 46204 | C26: C | D26: SIPAG | E26: ESP.01 000351 - IT ELETROPAULO METROPOLITANA ELETRICIDADE D | F26: Banco Itaú | G26: 99664-1 | H26: 24.36 | I26: D | J26: =IF(cmf[[#This Row],[D/C]]="C",cmf[[#This Row],[Valor]],-1*cmf[[#This Row],[Valor]]) -> -24.36 | L26: LP | M26: Lançamentos SIPAG | N26: SN4.01 | O26: 39 | P26: 46204 | S26: 0
A27: 68399 | B27: 46204 | C27: N | D27: IMORC | E27: RECIBO No. 627 Comissão/vendas 0347-0 | F27: Tesouraria - UP Vila Sonia 4 | G27: 000001 | H27: 4800 | I27: C | J27: =IF(cmf[[#This Row],[D/C]]="C",cmf[[#This Row],[Valor]],-1*cmf[[#This Row],[Valor]]) -> 4800 | L27: CI | M27: Caixa do imobiliário | N27: SN4.01 | O27: 39 | S27: 0
A28: 68400 | B28: 46204 | C28: N | D28: IMORC | E28: RECIBO No. 628 Comissão/vendas 0348-0 | F28: Tesouraria - UP Vila Sonia 4 | G28: 000001 | H28: 600.05 | I28: C | J28: =IF(cmf[[#This Row],[D/C]]="C",cmf[[#This Row],[Valor]],-1*cmf[[#This Row],[Valor]]) -> 600.05 | L28: CI | M28: Caixa do imobiliário | N28: SN4.01 | O28: 39 | S28: 0
A29: 68518 | B29: 46204 | C29: N | D29: COEMP | E29: Encontro de Contas - Envio Destino: VRG | F29: Tesouraria - UP Vila Sonia 4 | G29: 000001 | H29: 4800 | I29: D | J29: =IF(cmf[[#This Row],[D/C]]="C",cmf[[#This Row],[Valor]],-1*cmf[[#This Row],[Valor]]) -> -4800 | L29: CE | M29: Coligadas | N29: SN4.01 | O29: 39 | S29: 0
A30: 68519 | B30: 46204 | C30: N | D30: COEMP | E30: Encontro de Contas - Recebe Origem: SN4 | F30: Banco Bradesco | G30: 3635-8 | H30: 4800 | I30: C | J30: =IF(cmf[[#This Row],[D/C]]="C",cmf[[#This Row],[Valor]],-1*cmf[[#This Row],[Valor]]) -> 4800 | L30: CE | M30: Coligadas | N30: VRG.01 | O30: 54 | S30: 0
A31: 68520 | B31: 46204 | C31: N | D31: COEMP | E31: Encontro de Contas - Envio Destino: VRG | F31: Tesouraria - UP Vila Sonia 4 | G31: 000001 | H31: 600.05 | I31: D | J31: =IF(cmf[[#This Row],[D/C]]="C",cmf[[#This Row],[Valor]],-1*cmf[[#This Row],[Valor]]) -> -600.05 | L31: CE | M31: Coligadas | N31: SN4.01 | O31: 39 | S31: 0
A32: 68521 | B32: 46204 | C32: N | D32: COEMP | E32: Encontro de Contas - Recebe Origem: SN4 | F32: Banco Bradesco | G32: 3635-8 | H32: 600.05 | I32: C | J32: =IF(cmf[[#This Row],[D/C]]="C",cmf[[#This Row],[Valor]],-1*cmf[[#This Row],[Valor]]) -> 600.05 | L32: CE | M32: Coligadas | N32: VRG.01 | O32: 54 | S32: 0
A33: 68558 | B33: 46204 | C33: C | D33: IMOBT | E33: RECEITA DO IMOBILIÁRIO | F33: Caixa Econômica Federal | G33: 579133324-9 | H33: 1364946.6 | I33: C | J33: =IF(cmf[[#This Row],[D/C]]="C",cmf[[#This Row],[Valor]],-1*cmf[[#This Row],[Valor]]) -> 1364946.6 | L33: RI | M33: Recebimento imobiliário | N33: SN2.01 | O33: 26 | P33: 46204 | S33: 0
A34: 68713 | B34: 46204 | C34: C | D34: FINAN | E34: Financiamento - Agente BC 104 Contrato:8.7877.2540078-5 Tarifa Acompanhamento da Operação | F34: Caixa Econômica Federal | G34: 577180827-6 | H34: 1440 | I34: D | J34: =IF(cmf[[#This Row],[D/C]]="C",cmf[[#This Row],[Valor]],-1*cmf[[#This Row],[Valor]]) -> -1440 | L34: FI | M34: Financiamentos | N34: LUC.01 | O34: 23 | P34: 46204 | S34: 0
A35: 69217 | B35: 46204 | C35: C | D35: SIBAN | E35: JUROS LIMITE DA CONTA | F35: Banco Itaú | G35: 99756-5 | H35: 375.68 | I35: D | J35: =IF(cmf[[#This Row],[D/C]]="C",cmf[[#This Row],[Valor]],-1*cmf[[#This Row],[Valor]]) -> -375.68 | L35: TB | M35: Tarifas bancárias | N35: SN2.01 | O35: 26 | P35: 46204 | S35: 0
A36: 69282 | B36: 46204 | C36: C | D36: APLFI | E36: Aplicacao - Agente BC 341 Resgate | F36: Banco Itaú | G36: 99725-0 | H36: 1505.39 | I36: C | J36: =IF(cmf[[#This Row],[D/C]]="C",cmf[[#This Row],[Valor]],-1*cmf[[#This Row],[Valor]]) -> 1505.39 | L36: AF | M36: Aplicação financeira | N36: GRA.01 | O36: 25 | P36: 46204 | S36: 0
A37: 69295 | B37: 46204 | C37: C | D37: APLFI | E37: Aplicacao - Agente BC 341 Resgate | F37: Banco Itaú | G37: 99725-0 | H37: 0.01 | I37: C | J37: =IF(cmf[[#This Row],[D/C]]="C",cmf[[#This Row],[Valor]],-1*cmf[[#This Row],[Valor]]) -> 0.01 | L37: AF | M37: Aplicação financeira | N37: GRA.01 | O37: 25 | P37: 46204 | S37: 0
A38: 69341 | B38: 46204 | C38: C | D38: APLFI | E38: Aplicacao - Agente BC 341 Resgate | F38: Banco Itaú | G38: 99715-1 | H38: 12887.88 | I38: C | J38: =IF(cmf[[#This Row],[D/C]]="C",cmf[[#This Row],[Valor]],-1*cmf[[#This Row],[Valor]]) -> 12887.88 | L38: AF | M38: Aplicação financeira | N38: LUC.01 | O38: 23 | P38: 46204 | S38: 0
A39: 69342 | B39: 46204 | C39: C | D39: APLFI | E39: Aplicacao - Agente BC 341 Resgate | F39: Banco Itaú | G39: 99715-1 | H39: 0.02 | I39: C | J39: =IF(cmf[[#This Row],[D/C]]="C",cmf[[#This Row],[Valor]],-1*cmf[[#This Row],[Valor]]) -> 0.02 | L39: AF | M39: Aplicação financeira | N39: LUC.01 | O39: 23 | P39: 46204 | S39: 0
A40: 69396 | B40: 46204 | C40: C | D40: IMORC | E40: RECIBO No. 362 Comissão/vendas 0006-0 | F40: Caixa Econômica Federal | G40: 569680108-7 | H40: 11277.54 | I40: C | J40: =IF(cmf[[#This Row],[D/C]]="C",cmf[[#This Row],[Valor]],-1*cmf[[#This Row],[Valor]]) -> 11277.54 | L40: CI | M40: Caixa do imobiliário | N40: LUC.01 | O40: 23 | P40: 46204 | S40: 0
A41: 69474 | B41: 46204 | C41: C | D41: APLFI | E41: Aplicacao - Agente BC 341 Resgate | F41: Banco Itaú | G41: 99660-9 | H41: 31.37 | I41: C | J41: =IF(cmf[[#This Row],[D/C]]="C",cmf[[#This Row],[Valor]],-1*cmf[[#This Row],[Valor]]) -> 31.37 | L41: AF | M41: Aplicação financeira | N41: SAU.01 | O41: 31 | P41: 46204 | S41: 0
A42: 69475 | B42: 46204 | C42: N | D42: SIPAG | E42: ESP.01 000114 - IT Ministério da Fazenda | F42: Caixa Econômica Federal | G42: 579133369-9 | H42: 2671.19 | I42: D | J42: =IF(cmf[[#This Row],[D/C]]="C",cmf[[#This Row],[Valor]],-1*cmf[[#This Row],[Valor]]) -> -2671.19 | L42: LP | M42: Lançamentos SIPAG | N42: BUT.01 | O42: 38 | S42: 0
A43: 69863 | B43: 46204 | C43: C | D43: APLFI | E43: Aplicacao - Agente BC 341 Resgate | F43: Banco Itaú | G43: 99756-5 | H43: 375.68 | I43: C | J43: =IF(cmf[[#This Row],[D/C]]="C",cmf[[#This Row],[Valor]],-1*cmf[[#This Row],[Valor]]) -> 375.68 | L43: AF | M43: Aplicação financeira | N43: SN2.01 | O43: 26 | P43: 46204 | S43: 0
A44: 70203 | B44: 46204 | C44: C | D44: APLFI | E44: Aplicacao - Agente BC 341 Resgate | F44: Banco Itaú | G44: 99664-1 | H44: 316.72 | I44: C | J44: =IF(cmf[[#This Row],[D/C]]="C",cmf[[#This Row],[Valor]],-1*cmf[[#This Row],[Valor]]) -> 316.72 | L44: AF | M44: Aplicação financeira | N44: SN4.01 | O44: 39 | P44: 46204 | S44: 0
A45: 70540 | B45: 46204 | C45: C | D45: SIBAN | E45: TARIFA PAGTO. PIX | F45: ABC do Brasil | G45: 22924479 | H45: 5 | I45: D | J45: =IF(cmf[[#This Row],[D/C]]="C",cmf[[#This Row],[Valor]],-1*cmf[[#This Row],[Valor]]) -> -5 | L45: TB | M45: Tarifas bancárias | N45: POM.01 | O45: 24 | P45: 46204 | S45: 0
A46: 70604 | B46: 46204 | C46: C | D46: SIBAN | E46: TARIFA ACTMAN | F46: Caixa Econômica Federal | G46: 577180827-6 | H46: 2500 | I46: D | J46: =IF(cmf[[#This Row],[D/C]]="C",cmf[[#This Row],[Valor]],-1*cmf[[#This Row],[Valor]]) -> -2500 | L46: TB | M46: Tarifas bancárias | N46: LUC.01 | O46: 23 | P46: 46204 | S46: 0
A47: 70605 | B47: 46204 | C47: C | D47: SIBAN | E47: TARIFA EXT EL | F47: Caixa Econômica Federal | G47: 577180827-6 | H47: 2.2 | I47: D | J47: =IF(cmf[[#This Row],[D/C]]="C",cmf[[#This Row],[Valor]],-1*cmf[[#This Row],[Valor]]) -> -2.2 | L47: TB | M47: Tarifas bancárias | N47: LUC.01 | O47: 23 | P47: 46204 | S47: 0
A48: 70625 | B48: 46204 | C48: C | D48: APLFI | E48: Aplicacao - Agente BC 246 Resgate | F48: ABC do Brasil | G48: 22924479 | H48: 39988.82 | I48: C | J48: =IF(cmf[[#This Row],[D/C]]="C",cmf[[#This Row],[Valor]],-1*cmf[[#This Row],[Valor]]) -> 39988.82 | L48: AF | M48: Aplicação financeira | N48: POM.01 | O48: 24 | P48: 46204 | S48: 0
A49: 70674 | B49: 46204 | C49: C | D49: SIBAN | E49: TAR EXT EL | F49: Caixa Econômica Federal | G49: 577294854-3 | H49: 0.2 | I49: D | J49: =IF(cmf[[#This Row],[D/C]]="C",cmf[[#This Row],[Valor]],-1*cmf[[#This Row],[Valor]]) -> -0.2 | L49: TB | M49: Tarifas bancárias | N49: AVS.01 | O49: 10 | P49: 46204 | S49: 0
A50: 70748 | B50: 46204 | C50: C | D50: SIBAN | E50: TARIFA COBRANÇA | F50: Caixa Econômica Federal | G50: 569680108-7 | H50: 6.3 | I50: D | J50: =IF(cmf[[#This Row],[D/C]]="C",cmf[[#This Row],[Valor]],-1*cmf[[#This Row],[Valor]]) -> -6.3 | L50: TB | M50: Tarifas bancárias | N50: LUC.01 | O50: 23 | P50: 46204 | S50: 0
A51: 70749 | B51: 46204 | C51: C | D51: SIBAN | E51: TARIFA COBRANÇA | F51: Caixa Econômica Federal | G51: 569680108-7 | H51: 1.2 | I51: D | J51: =IF(cmf[[#This Row],[D/C]]="C",cmf[[#This Row],[Valor]],-1*cmf[[#This Row],[Valor]]) -> -1.2 | L51: TB | M51: Tarifas bancárias | N51: LUC.01 | O51: 23 | P51: 46204 | S51: 0
A52: 70750 | B52: 46204 | C52: C | D52: SIBAN | E52: TARIFA COBRANÇA | F52: Caixa Econômica Federal | G52: 569680108-7 | H52: 4.5 | I52: D | J52: =IF(cmf[[#This Row],[D/C]]="C",cmf[[#This Row],[Valor]],-1*cmf[[#This Row],[Valor]]) -> -4.5 | L52: TB | M52: Tarifas bancárias | N52: LUC.01 | O52: 23 | P52: 46204 | S52: 0
A53: 70961 | B53: 46204 | C53: C | D53: SIBAN | E53: TARIFA EXT EL | F53: Caixa Econômica Federal | G53: 579133363-0 | H53: 0.4 | I53: D | J53: =IF(cmf[[#This Row],[D/C]]="C",cmf[[#This Row],[Valor]],-1*cmf[[#This Row],[Valor]]) -> -0.4 | L53: TB | M53: Tarifas bancárias | N53: GRA.01 | O53: 25 | P53: 46204 | S53: 0
A54: 70981 | B54: 46204 | C54: C | D54: SIBAN | E54: TARIFA EXT EL | F54: Caixa Econômica Federal | G54: 576425863-0 | H54: 0.2 | I54: D | J54: =IF(cmf[[#This Row],[D/C]]="C",cmf[[#This Row],[Valor]],-1*cmf[[#This Row],[Valor]]) -> -0.2 | L54: TB | M54: Tarifas bancárias | N54: GRA.01 | O54: 25 | P54: 46204 | S54: 0
... A67: 72516 | B67: 46204 | C67: C | D67: SIBAN | E67: JUROS | F67: SAFRA | G67: 00585896-1 | H67: 1505.53 | I67: D | J67: =IF(cmf[[#This Row],[D/C]]="C",cmf[[#This Row],[Valor]],-1*cmf[[#This Row],[Valor]]) -> -1505.53 | L67: TB | M67: Tarifas bancárias | N67: AMP.01 | O67: 20 | P67: 46204 | S67: 0
A68: 68107 | B68: 46205 | C68: N | D68: IMOBT | E68: RECEITA DO IMOBILIÁRIO | F68: Banco Bradesco | G68: 3635-8 | H68: 140.96 | I68: C | J68: =IF(cmf[[#This Row],[D/C]]="C",cmf[[#This Row],[Valor]],-1*cmf[[#This Row],[Valor]]) -> 140.96 | L68: RI | M68: Recebimento imobiliário | N68: VRG.01 | O68: 54 | S68: 0
A69: 68110 | B69: 46205 | C69: C | D69: IMOBT | E69: RECEITA DO IMOBILIÁRIO | F69: Caixa Econômica Federal | G69: 579133363-0 | H69: 949.63 | I69: C | J69: =IF(cmf[[#This Row],[D/C]]="C",cmf[[#This Row],[Valor]],-1*cmf[[#This Row],[Valor]]) -> 949.63 | L69: RI | M69: Recebimento imobiliário | N69: GRA.01 | O69: 25 | P69: 46205 | S69: 0
A70: 68111 | B70: 46205 | C70: C | D70: IMOBT | E70: CUSTO DE COBRANÇA | F70: Caixa Econômica Federal | G70: 579133363-0 | H70: 6.3 | I70: D | J70: =IF(cmf[[#This Row],[D/C]]="C",cmf[[#This Row],[Valor]],-1*cmf[[#This Row],[Valor]]) -> -6.3 | L70: CC | M70: Custo de cobrança | N70: GRA.01 | O70: 25 | P70: 46205 | S70: 0
A71: 68239 | B71: 46205 | C71: C | D71: IMOBT | E71: RECEITA DO IMOBILIÁRIO | F71: ABC do Brasil | G71: 22924479 | H71: 9725.14 | I71: C | J71: =IF(cmf[[#This Row],[D/C]]="C",cmf[[#This Row],[Valor]],-1*cmf[[#This Row],[Valor]]) -> 9725.14 | L71: RI | M71: Recebimento imobiliário | N71: POM.01 | O71: 24 | P71: 46205 | S71: 0
A72: 68244 | B72: 46205 | C72: N | D72: IMOBT | E72: RECEITA DO IMOBILIÁRIO | F72: Banco Itaú | G72: 099843-8 | H72: 3795.1 | I72: C | J72: =IF(cmf[[#This Row],[D/C]]="C",cmf[[#This Row],[Valor]],-1*cmf[[#This Row],[Valor]]) -> 3795.1 | L72: RI | M72: Recebimento imobiliário | N72: PRO.01 | O72: 31 | S72: 0
A73: 68245 | B73: 46205 | C73: N | D73: IMOBT | E73: CUSTO DE COBRANÇA | F73: Banco Itaú | G73: 099843-8 | H73: 6.9 | I73: D | J73: =IF(cmf[[#This Row],[D/C]]="C",cmf[[#This Row],[Valor]],-1*cmf[[#This Row],[Valor]]) -> -6.9 | L73: CC | M73: Custo de cobrança | N73: PRO.01 | O73: 31 | S73: 0
A74: 68248 | B74: 46205 | C74: C | D74: IMOBT | E74: RECEITA DO IMOBILIÁRIO | F74: Caixa Econômica Federal | G74: 579133302-8 | H74: 645.82 | I74: C | J74: =IF(cmf[[#This Row],[D/C]]="C",cmf[[#This Row],[Valor]],-1*cmf[[#This Row],[Valor]]) -> 645.82 | L74: RI | M74: Recebimento imobiliário | N74: AMP.01 | O74: 20 | P74: 46205 | S74: 0
A75: 68249 | B75: 46205 | C75: C | D75: IMOBT | E75: CUSTO DE COBRANÇA | F75: Caixa Econômica Federal | G75: 579133302-8 | H75: 18.9 | I75: D | J75: =IF(cmf[[#This Row],[D/C]]="C",cmf[[#This Row],[Valor]],-1*cmf[[#This Row],[Valor]]) -> -18.9 | L75: CC | M75: Custo de cobrança | N75: AMP.01 | O75: 20 | P75: 46205 | S75: 0
A76: 68254 | B76: 46205 | C76: N | D76: IMOBT | E76: RECEITA DO IMOBILIÁRIO | F76: Banco Itaú | G76: 99804-0 | H76: 6455.43 | I76: C | J76: =IF(cmf[[#This Row],[D/C]]="C",cmf[[#This Row],[Valor]],-1*cmf[[#This Row],[Valor]]) -> 6455.43 | L76: RI | M76: Recebimento imobiliário | N76: PRO.01 | O76: 25 | S76: 0
A77: 68255 | B77: 46205 | C77: N | D77: IMOBT | E77: CUSTO DE COBRANÇA | F77: Banco Itaú | G77: 99804-0 | H77: 9.2 | I77: D | J77: =IF(cmf[[#This Row],[D/C]]="C",cmf[[#This Row],[Valor]],-1*cmf[[#This Row],[Valor]]) -> -9.2 | L77: CC | M77: Custo de cobrança | N77: PRO.01 | O77: 25 | S77: 0
A78: 68256 | B78: 46205 | C78: C | D78: IMOBT | E78: RECEITA DO IMOBILIÁRIO | F78: Caixa Econômica Federal | G78: 577294854-3 | H78: 1035.16 | I78: C | J78: =IF(cmf[[#This Row],[D/C]]="C",cmf[[#This Row],[Valor]],-1*cmf[[#This Row],[Valor]]) -> 1035.16 | L78: RI | M78: Recebimento imobiliário | N78: AVS.01 | O78: 10 | P78: 46205 | S78: 0
A79: 68257 | B79: 46205 | C79: C | D79: IMOBT | E79: CUSTO DE COBRANÇA | F79: Caixa Econômica Federal | G79: 577294854-3 | H79: 6.3 | I79: D | J79: =IF(cmf[[#This Row],[D/C]]="C",cmf[[#This Row],[Valor]],-1*cmf[[#This Row],[Valor]]) -> -6.3 | L79: CC | M79: Custo de cobrança | N79: AVS.01 | O79: 10 | P79: 46205 | S79: 0
A80: 68261 | B80: 46205 | C80: N | D80: IMOBT | E80: RECEITA DO IMOBILIÁRIO | F80: QI Tech | G80: 1601332-7 | H80: 9520.6 | I80: C | J80: =IF(cmf[[#This Row],[D/C]]="C",cmf[[#This Row],[Valor]],-1*cmf[[#This Row],[Valor]]) -> 9520.6 | L80: RI | M80: Recebimento imobiliário | N80: SN2.01 | O80: 26 | S80: 0
A81: 68289 | B81: 46205 | C81: C | D81: SIPAG | E81: ESP.01 000969 - IT COMPANHIA DE ENGENHARIA DE TRAFEGO | F81: Banco Itaú | G81: 99715-1 | H81: 3888.21 | I81: D | J81: =IF(cmf[[#This Row],[D/C]]="C",cmf[[#This Row],[Valor]],-1*cmf[[#This Row],[Valor]]) -> -3888.21 | L81: LP | M81: Lançamentos SIPAG | N81: LUC.01 | O81: 23 | P81: 46205 | S81: 0
A82: 68324 | B82: 46205 | C82: C | D82: IMORC | E82: RECIBO No. 235 Comissão/vendas 0139-1 | F82: Banco Itaú | G82: 99715-1 | H82: 220.19 | I82: C | J82: =IF(cmf[[#This Row],[D/C]]="C",cmf[[#This Row],[Valor]],-1*cmf[[#This Row],[Valor]]) -> 220.19 | L82: CI | M82: Caixa do imobiliário | N82: LUC.01 | O82: 23 | P82: 46205 | S82: 0
A83: 68337 | B83: 46205 | C83: C | D83: SIPAG | E83: ESP.01 001594 - IT ANGELO PAIOTTI COMERCIO VAREJISTA DE MAT | F83: Banco Itaú | G83: 06340-0 | H83: 1648 | I83: D | J83: =IF(cmf[[#This Row],[D/C]]="C",cmf[[#This Row],[Valor]],-1*cmf[[#This Row],[Valor]]) -> -1648 | L83: LP | M83: Lançamentos SIPAG | N83: AMP.01 | O83: 20 | P83: 46205 | S83: 0
A84: 68338 | B84: 46205 | C84: C | D84: SIPAG | E84: ESP.01 001595 - IT SEM PARAR INSTITUICAO DE PAGAMENTO LTDA | F84: Banco Itaú | G84: 06340-0 | H84: 73.58 | I84: D | J84: =IF(cmf[[#This Row],[D/C]]="C",cmf[[#This Row],[Valor]],-1*cmf[[#This Row],[Valor]]) -> -73.58 | L84: LP | M84: Lançamentos SIPAG | N84: AMP.01 | O84: 20 | P84: 46205 | S84: 0
A85: 68339 | B85: 46205 | C85: C | D85: SIPAG | E85: DSP.01 000046 - DC BC 341; 06340-0; carpe diem | F85: Banco Itaú | G85: 06340-0 | H85: 1170 | I85: D | J85: =IF(cmf[[#This Row],[D/C]]="C",cmf[[#This Row],[Valor]],-1*cmf[[#This Row],[Valor]]) -> -1170 | L85: LP | M85: Lançamentos SIPAG | N85: AMP.01 | O85: 20 | P85: 46205 | S85: 0
A86: 68372 | B86: 46205 | C86: C | D86: COEMP | E86: Encontro de Contas - Envio Destino: AMP | F86: Caixa Econômica Federal | G86: 579133324-9 | H86: 400000 | I86: D | J86: =IF(cmf[[#This Row],[D/C]]="C",cmf[[#This Row],[Valor]],-1*cmf[[#This Row],[Valor]]) -> -400000 | L86: CE | M86: Coligadas | N86: SN2.01 | O86: 26 | P86: 46205 | S86: 0
A87: 68373 | B87: 46205 | C87: C | D87: COEMP | E87: Encontro de Contas - Recebe Origem: SN2 | F87: Banco Itaú | G87: 06340-0 | H87: 400000 | I87: C | J87: =IF(cmf[[#This Row],[D/C]]="C",cmf[[#This Row],[Valor]],-1*cmf[[#This Row],[Valor]]) -> 400000 | L87: CE | M87: Coligadas | N87: AMP.01 | O87: 20 | P87: 46205 | S87: 0
A88: 68377 | B88: 46205 | C88: N | D88: IMOBT | E88: CUSTO DE COBRANÇA | F88: Banco Bradesco | G88: 3635-8 | H88: 5.96 | I88: D | J88: =IF(cmf[[#This Row],[D/C]]="C",cmf[[#This Row],[Valor]],-1*cmf[[#This Row],[Valor]]) -> -5.96 | L88: CC | M88: Custo de cobrança | N88: VRG.01 | O88: 54 | S88: 0
A89: 68379 | B89: 46205 | C89: C | D89: IMOBT | E89: RECEITA DO IMOBILIÁRIO | F89: Banco Itaú | G89: 99651-8 | H89: 200924.91 | I89: C | J89: =IF(cmf[[#This Row],[D/C]]="C",cmf[[#This Row],[Valor]],-1*cmf[[#This Row],[Valor]]) -> 200924.91 | L89: RI | M89: Recebimento imobiliário | N89: CBL.01 | O89: 43 | P89: 46205 | S89: 0
A90: 68380 | B90: 46205 | C90: C | D90: IMOBT | E90: CUSTO DE COBRANÇA | F90: Banco Itaú | G90: 99651-8 | H90: 6.57 | I90: D | J90: =IF(cmf[[#This Row],[D/C]]="C",cmf[[#This Row],[Valor]],-1*cmf[[#This Row],[Valor]]) -> -6.57 | L90: CC | M90: Custo de cobrança | N90: CBL.01 | O90: 43 | P90: 46205 | S90: 0
A91: 68391 | B91: 46205 | C91: N | D91: IMOBT | E91: CUSTO DE COBRANÇA | F91: QI Tech | G91: 1601332-7 | H91: 2 | I91: D | J91: =IF(cmf[[#This Row],[D/C]]="C",cmf[[#This Row],[Valor]],-1*cmf[[#This Row],[Valor]]) -> -2 | L91: CC | M91: Custo de cobrança | N91: SN2.01 | O91: 26 | S91: 0
A92: 68401 | B92: 46205 | C92: C | D92: SIPAG | E92: ESP.01 000733 - IT MERCADO PAGO INSTITUICAO DE PAGAMENTO LT | F92: ABC do Brasil | G92: 22924479 | H92: 196.91 | I92: D | J92: =IF(cmf[[#This Row],[D/C]]="C",cmf[[#This Row],[Valor]],-1*cmf[[#This Row],[Valor]]) -> -196.91 | L92: LP | M92: Lançamentos SIPAG | N92: POM.01 | O92: 24 | P92: 46205 | S92: 0
A93: 68402 | B93: 46205 | C93: C | D93: SIPAG | E93: ESP.01 000734 - IT COMPANHIA DE ENGENHARIA DE TRAFEGO | F93: ABC do Brasil | G93: 22924479 | H93: 448.63 | I93: D | J93: =IF(cmf[[#This Row],[D/C]]="C",cmf[[#This Row],[Valor]],-1*cmf[[#This Row],[Valor]]) -> -448.63 | L93: LP | M93: Lançamentos SIPAG | N93: POM.01 | O93: 24 | P93: 46205 | S93: 0
A94: 68404 | B94: 46205 | C94: C | D94: SIPAG | E94: ESP.01 001596 - IT GRAFFIT LIMEIRA PAPELARIA LTDA | F94: Banco Itaú | G94: 06340-0 | H94: 365 | I94: D | J94: =IF(cmf[[#This Row],[D/C]]="C",cmf[[#This Row],[Valor]],-1*cmf[[#This Row],[Valor]]) -> -365 | L94: LP | M94: Lançamentos SIPAG | N94: AMP.01 | O94: 20 | P94: 46205 | S94: 0
A95: 68424 | B95: 46205 | C95: N | D95: IMORC | E95: RECIBO No. 630 Comissão/vendas 0239-0 | F95: Tesouraria - UP Vila Sonia 4 | G95: 000001 | H95: 368.13 | I95: C | J95: =IF(cmf[[#This Row],[D/C]]="C",cmf[[#This Row],[Valor]],-1*cmf[[#This Row],[Valor]]) -> 368.13 | L95: CI | M95: Caixa do imobiliário | N95: SN4.01 | O95: 39 | S95: 0
A96: 68425 | B96: 46205 | C96: N | D96: IMORC | E96: RECIBO No. 631 Comissão/vendas 0240-0 | F96: Tesouraria - UP Vila Sonia 4 | G96: 000001 | H96: 2057.33 | I96: C | J96: =IF(cmf[[#This Row],[D/C]]="C",cmf[[#This Row],[Valor]],-1*cmf[[#This Row],[Valor]]) -> 2057.33 | L96: CI | M96: Caixa do imobiliário | N96: SN4.01 | O96: 39 | S96: 0
A97: 68514 | B97: 46205 | C97: N | D97: COEMP | E97: Encontro de Contas - Envio Destino: VRG | F97: Tesouraria - UP Vila Sonia 4 | G97: 000001 | H97: 2057.33 | I97: D | J97: =IF(cmf[[#This Row],[D/C]]="C",cmf[[#This Row],[Valor]],-1*cmf[[#This Row],[Valor]]) -> -2057.33 | L97: CE | M97: Coligadas | N97: SN4.01 | O97: 39 | S97: 0
A98: 68515 | B98: 46205 | C98: N | D98: COEMP | E98: Encontro de Contas - Recebe Origem: SN4 | F98: Banco Bradesco | G98: 3635-8 | H98: 2057.33 | I98: C | J98: =IF(cmf[[#This Row],[D/C]]="C",cmf[[#This Row],[Valor]],-1*cmf[[#This Row],[Valor]]) -> 2057.33 | L98: CE | M98: Coligadas | N98: VRG.01 | O98: 54 | S98: 0
A99: 68516 | B99: 46205 | C99: N | D99: COEMP | E99: Encontro de Contas - Envio Destino: VRG | F99: Tesouraria - UP Vila Sonia 4 | G99: 000001 | H99: 368.13 | I99: D | J99: =IF(cmf[[#This Row],[D/C]]="C",cmf[[#This Row],[Valor]],-1*cmf[[#This Row],[Valor]]) -> -368.13 | L99: CE | M99: Coligadas | N99: SN4.01 | O99: 39 | S99: 0
A100: 68517 | B100: 46205 | C100: N | D100: COEMP | E100: Encontro de Contas - Recebe Origem: SN4 | F100: Banco Bradesco | G100: 3635-8 | H100: 368.13 | I100: C | J100: =IF(cmf[[#This Row],[D/C]]="C",cmf[[#This Row],[Valor]],-1*cmf[[#This Row],[Valor]]) -> 368.13 | L100: CE | M100: Coligadas | N100: VRG.01 | O100: 54 | S100: 0
A101: 68587 | B101: 46205 | C101: C | D101: FINAN | E101: Financiamento - Agente BC 104 Contrato:8.7877.2137629-4 Crédito em conta corrente | F101: Caixa Econômica Federal | G101: 579133324-9 | H101: 374752.57 | I101: C | J101: =IF(cmf[[#This Row],[D/C]]="C",cmf[[#This Row],[Valor]],-1*cmf[[#This Row],[Valor]]) -> 374752.57 | L101: FI | M101: Financiamentos | N101: SN2.01 | O101: 26 | P101: 46205 | S101: 0
A102: 68744 | B102: 46205 | C102: C | D102: SIPAG | E102: ESP.01 000130 - IT SOUTO LOPES SOLUCOES LTDA | F102: Banco Itaú | G102: 99681-5 | H102: 8000 | I102: D | J102: =IF(cmf[[#This Row],[D/C]]="C",cmf[[#This Row],[Valor]],-1*cmf[[#This Row],[Valor]]) -> -8000 | L102: LP | M102: Lançamentos SIPAG | N102: JRP.01 | O102: 45 | P102: 46205 | S102: 0
A103: 69052 | B103: 46205 | C103: C | D103: FINAN | E103: Financiamento - Agente BC 246 Contrato:15502024 Juros de contrato | F103: ABC do Brasil | G103: 22924479 | H103: 5485.89 | I103: D | J103: =IF(cmf[[#This Row],[D/C]]="C",cmf[[#This Row],[Valor]],-1*cmf[[#This Row],[Valor]]) -> -5485.89 | L103: FI | M103: Financiamentos | N103: POM.01 | O103: 24 | P103: 46205 | S103: 0
A104: 69053 | B104: 46205 | C104: C | D104: FINAN | E104: Financiamento - Agente BC 246 Contrato:15502024 Juros de contrato | F104: ABC do Brasil | G104: 22924479 | H104: 79853.19 | I104: D | J104: =IF(cmf[[#This Row],[D/C]]="C",cmf[[#This Row],[Valor]],-1*cmf[[#This Row],[Valor]]) -> -79853.19 | L104: FI | M104: Financiamentos | N104: POM.01 | O104: 24 | P104: 46205 | S104: 0
A105: 69054 | B105: 46205 | C105: C | D105: FINAN | E105: Financiamento - Agente BC 246 Contrato:15502024 Juros de contrato | F105: ABC do Brasil | G105: 22924479 | H105: 4578.26 | I105: D | J105: =IF(cmf[[#This Row],[D/C]]="C",cmf[[#This Row],[Valor]],-1*cmf[[#This Row],[Valor]]) -> -4578.26 | L105: FI | M105: Financiamentos | N105: POM.01 | O105: 24 | P105: 46205 | S105: 0
A106: 69055 | B106: 46205 | C106: C | D106: FINAN | E106: Financiamento - Agente BC 246 Contrato:15502024 Juros de contrato | F106: ABC do Brasil | G106: 22924479 | H106: 8769.42 | I106: D | J106: =IF(cmf[[#This Row],[D/C]]="C",cmf[[#This Row],[Valor]],-1*cmf[[#This Row],[Valor]]) -> -8769.42 | L106: FI | M106: Financiamentos | N106: POM.01 | O106: 24 | P106: 46205 | S106: 0
A107: 69056 | B107: 46205 | C107: C | D107: FINAN | E107: Financiamento - Agente BC 246 Contrato:15502024 Juros de contrato | F107: ABC do Brasil | G107: 22924479 | H107: 5339.07 | I107: D | J107: =IF(cmf[[#This Row],[D/C]]="C",cmf[[#This Row],[Valor]],-1*cmf[[#This Row],[Valor]]) -> -5339.07 | L107: FI | M107: Financiamentos | N107: POM.01 | O107: 24 | P107: 46205 | S107: 0
A108: 69057 | B108: 46205 | C108: C | D108: FINAN | E108: Financiamento - Agente BC 246 Contrato:15502024 Juros de contrato | F108: ABC do Brasil | G108: 22924479 | H108: 9023.03 | I108: D | J108: =IF(cmf[[#This Row],[D/C]]="C",cmf[[#This Row],[Valor]],-1*cmf[[#This Row],[Valor]]) -> -9023.03 | L108: FI | M108: Financiamentos | N108: POM.01 | O108: 24 | P108: 46205 | S108: 0
A109: 69059 | B109: 46205 | C109: C | D109: FINAN | E109: Financiamento - Agente BC 246 Contrato:15502024 Juros de contrato | F109: ABC do Brasil | G109: 22924479 | H109: 13481.15 | I109: D | J109: =IF(cmf[[#This Row],[D/C]]="C",cmf[[#This Row],[Valor]],-1*cmf[[#This Row],[Valor]]) -> -13481.15 | L109: FI | M109: Financiamentos | N109: POM.01 | O109: 24 | P109: 46205 | S109: 0
A110: 69218 | B110: 46205 | C110: C | D110: SIBAN | E110: IOF | F110: Banco Itaú | G110: 99756-5 | H110: 113.39 | I110: D | J110: =IF(cmf[[#This Row],[D/C]]="C",cmf[[#This Row],[Valor]],-1*cmf[[#This Row],[Valor]]) -> -113.39 | L110: TB | M110: Tarifas bancárias | N110: SN2.01 | O110: 26 | P110: 46205 | S110: 0
A111: 69219 | B111: 46205 | C111: C | D111: SIBAN | E111: TAR PLANO ADAPT 06/26 | F111: Banco Itaú | G111: 99756-5 | H111: 169 | I111: D | J111: =IF(cmf[[#This Row],[D/C]]="C",cmf[[#This Row],[Valor]],-1*cmf[[#This Row],[Valor]]) -> -169 | L111: TB | M111: Tarifas bancárias | N111: SN2.01 | O111: 26 | P111: 46205 | S111: 0
A112: 69220 | B112: 46205 | C112: C | D112: SIBAN | E112: TAR PIX PGTO TRANSF | F112: Banco Itaú | G112: 99756-5 | H112: 88.15 | I112: D | J112: =IF(cmf[[#This Row],[D/C]]="C",cmf[[#This Row],[Valor]],-1*cmf[[#This Row],[Valor]]) -> -88.15 | L112: TB | M112: Tarifas bancárias | N112: SN2.01 | O112: 26 | P112: 46205 | S112: 0
...

Sheet RxP
D1: =SUBTOTAL(9,fech[Despesas]) -> 0 | H1: =SUM(H3:H33) -> 0 | I1: =SUM(I3:I33) -> 0 | J1: =SUM(J3:J33) -> 0 | K1: =SUM(K3:K33) -> 0 | L1: =SUM(L3:L33) -> 0 | M1: =SUM(M3:M33) -> 0
A2: Núcleo | B2: Empresa (resultado) | C2: Destacado | D2: Despesas | H2: Entradas | I2: Despesas_Resultado | J2: R_Resultado | K2: Despesas_Pagadora | L2: R_Pagadora | M2: Ajuste
A3: AMPLA INCORP. | B3: AMP | C3: TRUE | D3: =SUMIFS( tb_desp[valor], tb_desp[nucleo],fech[[#This Row],[Núcleo]], tb_desp[data.pagamento],">="&DATE(YEAR(inputs!$A$1),MONTH(inputs!$A$1),1), tb_desp[data.pagamento],"<"&EOMONTH(inputs!$A$1,0)+1 ) -> 0 | G3: {=_xlfn._xlws.SORT(_xlfn.UNIQUE(tb_desp[empresa]))} -> 0 | H3: =SUMIFS(tb_rec_uni[2026-07-01], tb_rec_uni[empresa], $G3, tb_rec_uni[natureza], "parcela.cef.assinar") +SUMIFS(tb_rec_uni[2026-07-01], tb_rec_uni[empresa], $G3, tb_rec_uni[natureza], "parcela.fin.total.ik") +SUMIFS(tb_rec_uni[2026-07-01], tb_rec_uni[empresa], $G3, tb_rec_uni[natureza], "pro.soluto") +SUMIFS(tb_rec_uni[2026-07-01], tb_rec_uni[empresa], $G3, tb_rec_uni[natureza], "repasse.cef.obra") +SUMIFS(tb_rec_uni[2026-07-01], tb_rec_uni[empresa], $G3, tb_rec_uni[natureza], "repasse.cef.terreno") +SUMIFS(tb_rec_uni[2026-07-01], tb_rec_uni[empresa], $G3, tb_rec_uni[natureza], "taxa.extra") -> 0 | I3: =-SUMIFS(fech[Despesas],fech[Empresa (resultado)],$G3) -> 0 | J3: =H3+I3 -> 0 | K3: =-SUMIFS(tb_desp[valor], tb_desp[empresa],$G3, tb_desp[data.pagamento],">="&DATE(YEAR(inputs!$A$1),MONTH(inputs!$A$1),1), tb_desp[data.pagamento],"<"&EOMONTH(inputs!$A$1,0)+1 ) -> 0 | L3: =H3+K3 -> 0 | M3: =L3-J3 -> 0
A4: AP - JOSÉ ROBERTO | B4: AMP | C4: FALSE | D4: =SUMIFS( tb_desp[valor], tb_desp[nucleo],fech[[#This Row],[Núcleo]], tb_desp[data.pagamento],">="&DATE(YEAR(inputs!$A$1),MONTH(inputs!$A$1),1), tb_desp[data.pagamento],"<"&EOMONTH(inputs!$A$1,0)+1 ) -> 0 | H4: =SUMIFS(tb_rec_uni[2026-07-01], tb_rec_uni[empresa], $G4, tb_rec_uni[natureza], "parcela.cef.assinar") +SUMIFS(tb_rec_uni[2026-07-01], tb_rec_uni[empresa], $G4, tb_rec_uni[natureza], "parcela.fin.total.ik") +SUMIFS(tb_rec_uni[2026-07-01], tb_rec_uni[empresa], $G4, tb_rec_uni[natureza], "pro.soluto") +SUMIFS(tb_rec_uni[2026-07-01], tb_rec_uni[empresa], $G4, tb_rec_uni[natureza], "repasse.cef.obra") +SUMIFS(tb_rec_uni[2026-07-01], tb_rec_uni[empresa], $G4, tb_rec_uni[natureza], "repasse.cef.terreno") +SUMIFS(tb_rec_uni[2026-07-01], tb_rec_uni[empresa], $G4, tb_rec_uni[natureza], "taxa.extra") -> 0 | I4: =-SUMIFS(fech[Despesas],fech[Empresa (resultado)],$G4) -> 0 | J4: =H4+I4 -> 0 | K4: =-SUMIFS(tb_desp[valor], tb_desp[empresa],$G4, tb_desp[data.pagamento],">="&DATE(YEAR(inputs!$A$1),MONTH(inputs!$A$1),1), tb_desp[data.pagamento],"<"&EOMONTH(inputs!$A$1,0)+1 ) -> 0 | L4: =H4+K4 -> 0 | M4: =L4-J4 -> 0
A5: APTO DAVI | B5: AMP | C5: FALSE | D5: =SUMIFS( tb_desp[valor], tb_desp[nucleo],fech[[#This Row],[Núcleo]], tb_desp[data.pagamento],">="&DATE(YEAR(inputs!$A$1),MONTH(inputs!$A$1),1), tb_desp[data.pagamento],"<"&EOMONTH(inputs!$A$1,0)+1 ) -> 0 | H5: =SUMIFS(tb_rec_uni[2026-07-01], tb_rec_uni[empresa], $G5, tb_rec_uni[natureza], "parcela.cef.assinar") +SUMIFS(tb_rec_uni[2026-07-01], tb_rec_uni[empresa], $G5, tb_rec_uni[natureza], "parcela.fin.total.ik") +SUMIFS(tb_rec_uni[2026-07-01], tb_rec_uni[empresa], $G5, tb_rec_uni[natureza], "pro.soluto") +SUMIFS(tb_rec_uni[2026-07-01], tb_rec_uni[empresa], $G5, tb_rec_uni[natureza], "repasse.cef.obra") +SUMIFS(tb_rec_uni[2026-07-01], tb_rec_uni[empresa], $G5, tb_rec_uni[natureza], "repasse.cef.terreno") +SUMIFS(tb_rec_uni[2026-07-01], tb_rec_uni[empresa], $G5, tb_rec_uni[natureza], "taxa.extra") -> 0 | I5: =-SUMIFS(fech[Despesas],fech[Empresa (resultado)],$G5) -> 0 | J5: =H5+I5 -> 0 | K5: =-SUMIFS(tb_desp[valor], tb_desp[empresa],$G5, tb_desp[data.pagamento],">="&DATE(YEAR(inputs!$A$1),MONTH(inputs!$A$1),1), tb_desp[data.pagamento],"<"&EOMONTH(inputs!$A$1,0)+1 ) -> 0 | L5: =H5+K5 -> 0 | M5: =L5-J5 -> 0
A6: BIG VILA SONIA - VLS7 | B6: AMP | C6: FALSE | D6: =SUMIFS( tb_desp[valor], tb_desp[nucleo],fech[[#This Row],[Núcleo]], tb_desp[data.pagamento],">="&DATE(YEAR(inputs!$A$1),MONTH(inputs!$A$1),1), tb_desp[data.pagamento],"<"&EOMONTH(inputs!$A$1,0)+1 ) -> 0 | H6: =SUMIFS(tb_rec_uni[2026-07-01], tb_rec_uni[empresa], $G6, tb_rec_uni[natureza], "parcela.cef.assinar") +SUMIFS(tb_rec_uni[2026-07-01], tb_rec_uni[empresa], $G6, tb_rec_uni[natureza], "parcela.fin.total.ik") +SUMIFS(tb_rec_uni[2026-07-01], tb_rec_uni[empresa], $G6, tb_rec_uni[natureza], "pro.soluto") +SUMIFS(tb_rec_uni[2026-07-01], tb_rec_uni[empresa], $G6, tb_rec_uni[natureza], "repasse.cef.obra") +SUMIFS(tb_rec_uni[2026-07-01], tb_rec_uni[empresa], $G6, tb_rec_uni[natureza], "repasse.cef.terreno") +SUMIFS(tb_rec_uni[2026-07-01], tb_rec_uni[empresa], $G6, tb_rec_uni[natureza], "taxa.extra") -> 0 | I6: =-SUMIFS(fech[Despesas],fech[Empresa (resultado)],$G6) -> 0 | J6: =H6+I6 -> 0 | K6: =-SUMIFS(tb_desp[valor], tb_desp[empresa],$G6, tb_desp[data.pagamento],">="&DATE(YEAR(inputs!$A$1),MONTH(inputs!$A$1),1), tb_desp[data.pagamento],"<"&EOMONTH(inputs!$A$1,0)+1 ) -> 0 | L6: =H6+K6 -> 0 | M6: =L6-J6 -> 0
A7: BUTIA | B7: BUT | C7: FALSE | D7: =SUMIFS( tb_desp[valor], tb_desp[nucleo],fech[[#This Row],[Núcleo]], tb_desp[data.pagamento],">="&DATE(YEAR(inputs!$A$1),MONTH(inputs!$A$1),1), tb_desp[data.pagamento],"<"&EOMONTH(inputs!$A$1,0)+1 ) -> 0 | H7: =SUMIFS(tb_rec_uni[2026-07-01], tb_rec_uni[empresa], $G7, tb_rec_uni[natureza], "parcela.cef.assinar") +SUMIFS(tb_rec_uni[2026-07-01], tb_rec_uni[empresa], $G7, tb_rec_uni[natureza], "parcela.fin.total.ik") +SUMIFS(tb_rec_uni[2026-07-01], tb_rec_uni[empresa], $G7, tb_rec_uni[natureza], "pro.soluto") +SUMIFS(tb_rec_uni[2026-07-01], tb_rec_uni[empresa], $G7, tb_rec_uni[natureza], "repasse.cef.obra") +SUMIFS(tb_rec_uni[2026-07-01], tb_rec_uni[empresa], $G7, tb_rec_uni[natureza], "repasse.cef.terreno") +SUMIFS(tb_rec_uni[2026-07-01], tb_rec_uni[empresa], $G7, tb_rec_uni[natureza], "taxa.extra") -> 0 | I7: =-SUMIFS(fech[Despesas],fech[Empresa (resultado)],$G7) -> 0 | J7: =H7+I7 -> 0 | K7: =-SUMIFS(tb_desp[valor], tb_desp[empresa],$G7, tb_desp[data.pagamento],">="&DATE(YEAR(inputs!$A$1),MONTH(inputs!$A$1),1), tb_desp[data.pagamento],"<"&EOMONTH(inputs!$A$1,0)+1 ) -> 0 | L7: =H7+K7 -> 0 | M7: =L7-J7 -> 0
A8: CAMPOLARGO | B8: CPE | C8: FALSE | D8: =SUMIFS( tb_desp[valor], tb_desp[nucleo],fech[[#This Row],[Núcleo]], tb_desp[data.pagamento],">="&DATE(YEAR(inputs!$A$1),MONTH(inputs!$A$1),1), tb_desp[data.pagamento],"<"&EOMONTH(inputs!$A$1,0)+1 ) -> 0 | H8: =SUMIFS(tb_rec_uni[2026-07-01], tb_rec_uni[empresa], $G8, tb_rec_uni[natureza], "parcela.cef.assinar") +SUMIFS(tb_rec_uni[2026-07-01], tb_rec_uni[empresa], $G8, tb_rec_uni[natureza], "parcela.fin.total.ik") +SUMIFS(tb_rec_uni[2026-07-01], tb_rec_uni[empresa], $G8, tb_rec_uni[natureza], "pro.soluto") +SUMIFS(tb_rec_uni[2026-07-01], tb_rec_uni[empresa], $G8, tb_rec_uni[natureza], "repasse.cef.obra") +SUMIFS(tb_rec_uni[2026-07-01], tb_rec_uni[empresa], $G8, tb_rec_uni[natureza], "repasse.cef.terreno") +SUMIFS(tb_rec_uni[2026-07-01], tb_rec_uni[empresa], $G8, tb_rec_uni[natureza], "taxa.extra") -> 0 | I8: =-SUMIFS(fech[Despesas],fech[Empresa (resultado)],$G8) -> 0 | J8: =H8+I8 -> 0 | K8: =-SUMIFS(tb_desp[valor], tb_desp[empresa],$G8, tb_desp[data.pagamento],">="&DATE(YEAR(inputs!$A$1),MONTH(inputs!$A$1),1), tb_desp[data.pagamento],"<"&EOMONTH(inputs!$A$1,0)+1 ) -> 0 | L8: =H8+K8 -> 0 | M8: =L8-J8 -> 0
A9: CAXINGUI | B9: CXG | C9: FALSE | D9: =SUMIFS( tb_desp[valor], tb_desp[nucleo],fech[[#This Row],[Núcleo]], tb_desp[data.pagamento],">="&DATE(YEAR(inputs!$A$1),MONTH(inputs!$A$1),1), tb_desp[data.pagamento],"<"&EOMONTH(inputs!$A$1,0)+1 ) -> 0 | H9: =SUMIFS(tb_rec_uni[2026-07-01], tb_rec_uni[empresa], $G9, tb_rec_uni[natureza], "parcela.cef.assinar") +SUMIFS(tb_rec_uni[2026-07-01], tb_rec_uni[empresa], $G9, tb_rec_uni[natureza], "parcela.fin.total.ik") +SUMIFS(tb_rec_uni[2026-07-01], tb_rec_uni[empresa], $G9, tb_rec_uni[natureza], "pro.soluto") +SUMIFS(tb_rec_uni[2026-07-01], tb_rec_uni[empresa], $G9, tb_rec_uni[natureza], "repasse.cef.obra") +SUMIFS(tb_rec_uni[2026-07-01], tb_rec_uni[empresa], $G9, tb_rec_uni[natureza], "repasse.cef.terreno") +SUMIFS(tb_rec_uni[2026-07-01], tb_rec_uni[empresa], $G9, tb_rec_uni[natureza], "taxa.extra") -> 0 | I9: =-SUMIFS(fech[Despesas],fech[Empresa (resultado)],$G9) -> 0 | J9: =H9+I9 -> 0 | K9: =-SUMIFS(tb_desp[valor], tb_desp[empresa],$G9, tb_desp[data.pagamento],">="&DATE(YEAR(inputs!$A$1),MONTH(inputs!$A$1),1), tb_desp[data.pagamento],"<"&EOMONTH(inputs!$A$1,0)+1 ) -> 0 | L9: =H9+K9 -> 0 | M9: =L9-J9 -> 0
A10: DAVI PF | B10: DPF | C10: FALSE | D10: =SUMIFS( tb_desp[valor], tb_desp[nucleo],fech[[#This Row],[Núcleo]], tb_desp[data.pagamento],">="&DATE(YEAR(inputs!$A$1),MONTH(inputs!$A$1),1), tb_desp[data.pagamento],"<"&EOMONTH(inputs!$A$1,0)+1 ) -> 0 | H10: =SUMIFS(tb_rec_uni[2026-07-01], tb_rec_uni[empresa], $G10, tb_rec_uni[natureza], "parcela.cef.assinar") +SUMIFS(tb_rec_uni[2026-07-01], tb_rec_uni[empresa], $G10, tb_rec_uni[natureza], "parcela.fin.total.ik") +SUMIFS(tb_rec_uni[2026-07-01], tb_rec_uni[empresa], $G10, tb_rec_uni[natureza], "pro.soluto") +SUMIFS(tb_rec_uni[2026-07-01], tb_rec_uni[empresa], $G10, tb_rec_uni[natureza], "repasse.cef.obra") +SUMIFS(tb_rec_uni[2026-07-01], tb_rec_uni[empresa], $G10, tb_rec_uni[natureza], "repasse.cef.terreno") +SUMIFS(tb_rec_uni[2026-07-01], tb_rec_uni[empresa], $G10, tb_rec_uni[natureza], "taxa.extra") -> 0 | I10: =-SUMIFS(fech[Despesas],fech[Empresa (resultado)],$G10) -> 0 | J10: =H10+I10 -> 0 | K10: =-SUMIFS(tb_desp[valor], tb_desp[empresa],$G10, tb_desp[data.pagamento],">="&DATE(YEAR(inputs!$A$1),MONTH(inputs!$A$1),1), tb_desp[data.pagamento],"<"&EOMONTH(inputs!$A$1,0)+1 ) -> 0 | L10: =H10+K10 -> 0 | M10: =L10-J10 -> 0
A11: ÉDEN - FERREIRA ANDRADE | B11: AMP | C11: FALSE | D11: =SUMIFS( tb_desp[valor], tb_desp[nucleo],fech[[#This Row],[Núcleo]], tb_desp[data.pagamento],">="&DATE(YEAR(inputs!$A$1),MONTH(inputs!$A$1),1), tb_desp[data.pagamento],"<"&EOMONTH(inputs!$A$1,0)+1 ) -> 0 | H11: =SUMIFS(tb_rec_uni[2026-07-01], tb_rec_uni[empresa], $G11, tb_rec_uni[natureza], "parcela.cef.assinar") +SUMIFS(tb_rec_uni[2026-07-01], tb_rec_uni[empresa], $G11, tb_rec_uni[natureza], "parcela.fin.total.ik") +SUMIFS(tb_rec_uni[2026-07-01], tb_rec_uni[empresa], $G11, tb_rec_uni[natureza], "pro.soluto") +SUMIFS(tb_rec_uni[2026-07-01], tb_rec_uni[empresa], $G11, tb_rec_uni[natureza], "repasse.cef.obra") +SUMIFS(tb_rec_uni[2026-07-01], tb_rec_uni[empresa], $G11, tb_rec_uni[natureza], "repasse.cef.terreno") +SUMIFS(tb_rec_uni[2026-07-01], tb_rec_uni[empresa], $G11, tb_rec_uni[natureza], "taxa.extra") -> 0 | I11: =-SUMIFS(fech[Despesas],fech[Empresa (resultado)],$G11) -> 0 | J11: =H11+I11 -> 0 | K11: =-SUMIFS(tb_desp[valor], tb_desp[empresa],$G11, tb_desp[data.pagamento],">="&DATE(YEAR(inputs!$A$1),MONTH(inputs!$A$1),1), tb_desp[data.pagamento],"<"&EOMONTH(inputs!$A$1,0)+1 ) -> 0 | L11: =H11+K11 -> 0 | M11: =L11-J11 -> 0
A12: EDEN 446 | B12: AMP | C12: FALSE | D12: =SUMIFS( tb_desp[valor], tb_desp[nucleo],fech[[#This Row],[Núcleo]], tb_desp[data.pagamento],">="&DATE(YEAR(inputs!$A$1),MONTH(inputs!$A$1),1), tb_desp[data.pagamento],"<"&EOMONTH(inputs!$A$1,0)+1 ) -> 0 | H12: =SUMIFS(tb_rec_uni[2026-07-01], tb_rec_uni[empresa], $G12, tb_rec_uni[natureza], "parcela.cef.assinar") +SUMIFS(tb_rec_uni[2026-07-01], tb_rec_uni[empresa], $G12, tb_rec_uni[natureza], "parcela.fin.total.ik") +SUMIFS(tb_rec_uni[2026-07-01], tb_rec_uni[empresa], $G12, tb_rec_uni[natureza], "pro.soluto") +SUMIFS(tb_rec_uni[2026-07-01], tb_rec_uni[empresa], $G12, tb_rec_uni[natureza], "repasse.cef.obra") +SUMIFS(tb_rec_uni[2026-07-01], tb_rec_uni[empresa], $G12, tb_rec_uni[natureza], "repasse.cef.terreno") +SUMIFS(tb_rec_uni[2026-07-01], tb_rec_uni[empresa], $G12, tb_rec_uni[natureza], "taxa.extra") -> 0 | I12: =-SUMIFS(fech[Despesas],fech[Empresa (resultado)],$G12) -> 0 | J12: =H12+I12 -> 0 | K12: =-SUMIFS(tb_desp[valor], tb_desp[empresa],$G12, tb_desp[data.pagamento],">="&DATE(YEAR(inputs!$A$1),MONTH(inputs!$A$1),1), tb_desp[data.pagamento],"<"&EOMONTH(inputs!$A$1,0)+1 ) -> 0 | L12: =H12+K12 -> 0 | M12: =L12-J12 -> 0
A13: GERAL | B13: AMP | C13: FALSE | D13: =SUMIFS( tb_desp[valor], tb_desp[nucleo],fech[[#This Row],[Núcleo]], tb_desp[data.pagamento],">="&DATE(YEAR(inputs!$A$1),MONTH(inputs!$A$1),1), tb_desp[data.pagamento],"<"&EOMONTH(inputs!$A$1,0)+1 ) -> 0 | H13: =SUMIFS(tb_rec_uni[2026-07-01], tb_rec_uni[empresa], $G13, tb_rec_uni[natureza], "parcela.cef.assinar") +SUMIFS(tb_rec_uni[2026-07-01], tb_rec_uni[empresa], $G13, tb_rec_uni[natureza], "parcela.fin.total.ik") +SUMIFS(tb_rec_uni[2026-07-01], tb_rec_uni[empresa], $G13, tb_rec_uni[natureza], "pro.soluto") +SUMIFS(tb_rec_uni[2026-07-01], tb_rec_uni[empresa], $G13, tb_rec_uni[natureza], "repasse.cef.obra") +SUMIFS(tb_rec_uni[2026-07-01], tb_rec_uni[empresa], $G13, tb_rec_uni[natureza], "repasse.cef.terreno") +SUMIFS(tb_rec_uni[2026-07-01], tb_rec_uni[empresa], $G13, tb_rec_uni[natureza], "taxa.extra") -> 0 | I13: =-SUMIFS(fech[Despesas],fech[Empresa (resultado)],$G13) -> 0 | J13: =H13+I13 -> 0 | K13: =-SUMIFS(tb_desp[valor], tb_desp[empresa],$G13, tb_desp[data.pagamento],">="&DATE(YEAR(inputs!$A$1),MONTH(inputs!$A$1),1), tb_desp[data.pagamento],"<"&EOMONTH(inputs!$A$1,0)+1 ) -> 0 | L13: =H13+K13 -> 0 | M13: =L13-J13 -> 0
A14: IBIRAPUERA | B14: AVR | C14: FALSE | D14: =SUMIFS( tb_desp[valor], tb_desp[nucleo],fech[[#This Row],[Núcleo]], tb_desp[data.pagamento],">="&DATE(YEAR(inputs!$A$1),MONTH(inputs!$A$1),1), tb_desp[data.pagamento],"<"&EOMONTH(inputs!$A$1,0)+1 ) -> 0 | H14: =SUMIFS(tb_rec_uni[2026-07-01], tb_rec_uni[empresa], $G14, tb_rec_uni[natureza], "parcela.cef.assinar") +SUMIFS(tb_rec_uni[2026-07-01], tb_rec_uni[empresa], $G14, tb_rec_uni[natureza], "parcela.fin.total.ik") +SUMIFS(tb_rec_uni[2026-07-01], tb_rec_uni[empresa], $G14, tb_rec_uni[natureza], "pro.soluto") +SUMIFS(tb_rec_uni[2026-07-01], tb_rec_uni[empresa], $G14, tb_rec_uni[natureza], "repasse.cef.obra") +SUMIFS(tb_rec_uni[2026-07-01], tb_rec_uni[empresa], $G14, tb_rec_uni[natureza], "repasse.cef.terreno") +SUMIFS(tb_rec_uni[2026-07-01], tb_rec_uni[empresa], $G14, tb_rec_uni[natureza], "taxa.extra") -> 0 | I14: =-SUMIFS(fech[Despesas],fech[Empresa (resultado)],$G14) -> 0 | J14: =H14+I14 -> 0 | K14: =-SUMIFS(tb_desp[valor], tb_desp[empresa],$G14, tb_desp[data.pagamento],">="&DATE(YEAR(inputs!$A$1),MONTH(inputs!$A$1),1), tb_desp[data.pagamento],"<"&EOMONTH(inputs!$A$1,0)+1 ) -> 0 | L14: =H14+K14 -> 0 | M14: =L14-J14 -> 0
A15: INCORFLORA | B15: INC | C15: FALSE | D15: =SUMIFS( tb_desp[valor], tb_desp[nucleo],fech[[#This Row],[Núcleo]], tb_desp[data.pagamento],">="&DATE(YEAR(inputs!$A$1),MONTH(inputs!$A$1),1), tb_desp[data.pagamento],"<"&EOMONTH(inputs!$A$1,0)+1 ) -> 0 | H15: =SUMIFS(tb_rec_uni[2026-07-01], tb_rec_uni[empresa], $G15, tb_rec_uni[natureza], "parcela.cef.assinar") +SUMIFS(tb_rec_uni[2026-07-01], tb_rec_uni[empresa], $G15, tb_rec_uni[natureza], "parcela.fin.total.ik") +SUMIFS(tb_rec_uni[2026-07-01], tb_rec_uni[empresa], $G15, tb_rec_uni[natureza], "pro.soluto") +SUMIFS(tb_rec_uni[2026-07-01], tb_rec_uni[empresa], $G15, tb_rec_uni[natureza], "repasse.cef.obra") +SUMIFS(tb_rec_uni[2026-07-01], tb_rec_uni[empresa], $G15, tb_rec_uni[natureza], "repasse.cef.terreno") +SUMIFS(tb_rec_uni[2026-07-01], tb_rec_uni[empresa], $G15, tb_rec_uni[natureza], "taxa.extra") -> 0 | I15: =-SUMIFS(fech[Despesas],fech[Empresa (resultado)],$G15) -> 0 | J15: =H15+I15 -> 0 | K15: =-SUMIFS(tb_desp[valor], tb_desp[empresa],$G15, tb_desp[data.pagamento],">="&DATE(YEAR(inputs!$A$1),MONTH(inputs!$A$1),1), tb_desp[data.pagamento],"<"&EOMONTH(inputs!$A$1,0)+1 ) -> 0 | L15: =H15+K15 -> 0 | M15: =L15-J15 -> 0
... A33: UP MOVE VILA SONIA | B33: SN4 | C33: TRUE | D33: =SUMIFS( tb_desp[valor], tb_desp[nucleo],fech[[#This Row],[Núcleo]], tb_desp[data.pagamento],">="&DATE(YEAR(inputs!$A$1),MONTH(inputs!$A$1),1), tb_desp[data.pagamento],"<"&EOMONTH(inputs!$A$1,0)+1 ) -> 0 | H33: =SUMIFS(tb_rec_uni[2026-07-01], tb_rec_uni[empresa], $G33, tb_rec_uni[natureza], "parcela.cef.assinar") +SUMIFS(tb_rec_uni[2026-07-01], tb_rec_uni[empresa], $G33, tb_rec_uni[natureza], "parcela.fin.total.ik") +SUMIFS(tb_rec_uni[2026-07-01], tb_rec_uni[empresa], $G33, tb_rec_uni[natureza], "pro.soluto") +SUMIFS(tb_rec_uni[2026-07-01], tb_rec_uni[empresa], $G33, tb_rec_uni[natureza], "repasse.cef.obra") +SUMIFS(tb_rec_uni[2026-07-01], tb_rec_uni[empresa], $G33, tb_rec_uni[natureza], "repasse.cef.terreno") +SUMIFS(tb_rec_uni[2026-07-01], tb_rec_uni[empresa], $G33, tb_rec_uni[natureza], "taxa.extra") -> 0 | I33: =-SUMIFS(fech[Despesas],fech[Empresa (resultado)],$G33) -> 0 | J33: =H33+I33 -> 0 | K33: =-SUMIFS(tb_desp[valor], tb_desp[empresa],$G33, tb_desp[data.pagamento],">="&DATE(YEAR(inputs!$A$1),MONTH(inputs!$A$1),1), tb_desp[data.pagamento],"<"&EOMONTH(inputs!$A$1,0)+1 ) -> 0 | L33: =H33+K33 -> 0 | M33: =L33-J33 -> 0
A34: UP PARADA INGLESA | B34: AMP | C34: FALSE | D34: =SUMIFS( tb_desp[valor], tb_desp[nucleo],fech[[#This Row],[Núcleo]], tb_desp[data.pagamento],">="&DATE(YEAR(inputs!$A$1),MONTH(inputs!$A$1),1), tb_desp[data.pagamento],"<"&EOMONTH(inputs!$A$1,0)+1 ) -> 0
A35: UP POMPEIA | B35: POM | C35: TRUE | D35: =SUMIFS( tb_desp[valor], tb_desp[nucleo],fech[[#This Row],[Núcleo]], tb_desp[data.pagamento],">="&DATE(YEAR(inputs!$A$1),MONTH(inputs!$A$1),1), tb_desp[data.pagamento],"<"&EOMONTH(inputs!$A$1,0)+1 ) -> 0
A36: UP SALE | B36: USL | C36: FALSE | D36: =SUMIFS( tb_desp[valor], tb_desp[nucleo],fech[[#This Row],[Núcleo]], tb_desp[data.pagamento],">="&DATE(YEAR(inputs!$A$1),MONTH(inputs!$A$1),1), tb_desp[data.pagamento],"<"&EOMONTH(inputs!$A$1,0)+1 ) -> 0
A37: UP SAUDE | B37: SAU | C37: TRUE | D37: =SUMIFS( tb_desp[valor], tb_desp[nucleo],fech[[#This Row],[Núcleo]], tb_desp[data.pagamento],">="&DATE(YEAR(inputs!$A$1),MONTH(inputs!$A$1),1), tb_desp[data.pagamento],"<"&EOMONTH(inputs!$A$1,0)+1 ) -> 0
A38: UP SELECT VILA SONIA | B38: GRA | C38: TRUE | D38: =SUMIFS( tb_desp[valor], tb_desp[nucleo],fech[[#This Row],[Núcleo]], tb_desp[data.pagamento],">="&DATE(YEAR(inputs!$A$1),MONTH(inputs!$A$1),1), tb_desp[data.pagamento],"<"&EOMONTH(inputs!$A$1,0)+1 ) -> 0
A39: UP SOCORRO | B39: SOC | C39: FALSE | D39: =SUMIFS( tb_desp[valor], tb_desp[nucleo],fech[[#This Row],[Núcleo]], tb_desp[data.pagamento],">="&DATE(YEAR(inputs!$A$1),MONTH(inputs!$A$1),1), tb_desp[data.pagamento],"<"&EOMONTH(inputs!$A$1,0)+1 ) -> 0
A40: UP SPORT HOME - JURUPITÉ | B40: JRP | C40: FALSE | D40: =SUMIFS( tb_desp[valor], tb_desp[nucleo],fech[[#This Row],[Núcleo]], tb_desp[data.pagamento],">="&DATE(YEAR(inputs!$A$1),MONTH(inputs!$A$1),1), tb_desp[data.pagamento],"<"&EOMONTH(inputs!$A$1,0)+1 ) -> 0
A41: Up Stay Congonhas | B41: CBL | C41: TRUE | D41: =SUMIFS( tb_desp[valor], tb_desp[nucleo],fech[[#This Row],[Núcleo]], tb_desp[data.pagamento],">="&DATE(YEAR(inputs!$A$1),MONTH(inputs!$A$1),1), tb_desp[data.pagamento],"<"&EOMONTH(inputs!$A$1,0)+1 ) -> 0
A42: UP VILA SONIA | B42: AVS | C42: TRUE | D42: =SUMIFS( tb_desp[valor], tb_desp[nucleo],fech[[#This Row],[Núcleo]], tb_desp[data.pagamento],">="&DATE(YEAR(inputs!$A$1),MONTH(inputs!$A$1),1), tb_desp[data.pagamento],"<"&EOMONTH(inputs!$A$1,0)+1 ) -> 0
A43: VILLA SICILIA | B43: AMP | C43: FALSE | D43: =SUMIFS( tb_desp[valor], tb_desp[nucleo],fech[[#This Row],[Núcleo]], tb_desp[data.pagamento],">="&DATE(YEAR(inputs!$A$1),MONTH(inputs!$A$1),1), tb_desp[data.pagamento],"<"&EOMONTH(inputs!$A$1,0)+1 ) -> 0
A44: VILLA VENETO | B44: AMP | C44: FALSE | D44: =SUMIFS( tb_desp[valor], tb_desp[nucleo],fech[[#This Row],[Núcleo]], tb_desp[data.pagamento],">="&DATE(YEAR(inputs!$A$1),MONTH(inputs!$A$1),1), tb_desp[data.pagamento],"<"&EOMONTH(inputs!$A$1,0)+1 ) -> 0
A45: VIRGO | B45: VRG | C45: FALSE | D45: =SUMIFS( tb_desp[valor], tb_desp[nucleo],fech[[#This Row],[Núcleo]], tb_desp[data.pagamento],">="&DATE(YEAR(inputs!$A$1),MONTH(inputs!$A$1),1), tb_desp[data.pagamento],"<"&EOMONTH(inputs!$A$1,0)+1 ) -> 0

Sheet f.grupo
A1: Código | B1: Descrição | C1: Origem | D1: 45658 | E1: 45689 | F1: 45717 | G1: 45748 | H1: 45778 | I1: 45809 | J1: 45839 | K1: 45870 | L1: 45901 | M1: 45931 | N1: 45962 | O1: 45992 | P1: 46023 | Q1: 46054 | R1: 46082 | S1: 46113 | T1: 46143 | U1: 46174 | V1: 46204 | W1: 46235 | X1: 46266 | Y1: 46296 | Z1: 46327 | AA1: 46357 | AC1: Incorrido | AE1: Total | AG1: Duvidoso
A2: 1. | B2: Caixa líq. das atividades operacionais | D2: =D$3+D$33 -> 66315.2 | E2: =E$3+E$33 -> 102314.88 | F2: =F$3+F$33 -> 247260.96 | G2: =G$3+G$33 -> 361891.52 | H2: =H$3+H$33 -> 806203.36 | I2: =I$3+I$33 -> 770203.68 | J2: =J$3+J$33 -> 1031675 | K2: =K$3+K$33 -> 400733.28 | ... AA2: =AA$3+AA$33 -> 0 | AC2: =SUM($D2:INDEX($D2:$AA2,1,MATCH(DATE(YEAR(inputs!$A$1),MONTH(inputs!$A$1),1),$D$1:$AA$1,0))) -> 8746974.9 | AE2: =SUM(D2:AA2) -> 8746974.9 | AG2: Não identificável
A3: 1.1. | B3: Entradas de atividades operacionais | D3: =SUM(D$4,D$11,D$25,D$23) -> 66315.2 | E3: =SUM(E$4,E$11,E$25,E$23) -> 102314.88 | F3: =SUM(F$4,F$11,F$25,F$23) -> 247260.96 | G3: =SUM(G$4,G$11,G$25,G$23) -> 361891.52 | H3: =SUM(H$4,H$11,H$25,H$23) -> 806203.36 | I3: =SUM(I$4,I$11,I$25,I$23) -> 770203.68 | J3: =SUM(J$4,J$11,J$25,J$23) -> 1031675 | K3: =SUM(K$4,K$11,K$25,K$23) -> 400733.28 | ... AA3: =SUM(AA$4,AA$11,AA$25,AA$23) -> 0 | AC3: =SUM($D3:INDEX($D3:$AA3,1,MATCH(DATE(YEAR(inputs!$A$1),MONTH(inputs!$A$1),1),$D$1:$AA$1,0))) -> 8746974.9 | AE3: =SUM(D3:AA3) -> 8746974.9
A4: 1.1.1. | B4: Repasse CEF | C4: CEF | D4: =SUM(D$5:D$10) -> 0 | E4: =SUM(E$5:E$10) -> 0 | F4: =SUM(F$5:F$10) -> 0 | G4: =SUM(G$5:G$10) -> 0 | H4: =SUM(H$5:H$10) -> 0 | I4: =SUM(I$5:I$10) -> 0 | J4: =SUM(J$5:J$10) -> 0 | K4: =SUM(K$5:K$10) -> 0 | ... AA4: =SUM(AA$5:AA$10) -> 0 | AC4: =SUM($D4:INDEX($D4:$AA4,1,MATCH(DATE(YEAR(inputs!$A$1),MONTH(inputs!$A$1),1),$D$1:$AA$1,0))) -> 0 | AE4: =SUM(D4:AA4) -> 0
A5: 1.1.1.SN2. | B5: SN2 | C5: CEF | D5: =SUMIFS(tb_rec_uni[2025-01-01], INDIRECT("tb_rec_uni[natureza]"),"repasse.cef.obra", INDIRECT("tb_rec_uni[empresa]"),$B5)+ SUMIFS(tb_rec_uni[2025-01-01], INDIRECT("tb_rec_uni[natureza]"),"repasse.cef.terreno", INDIRECT("tb_rec_uni[empresa]"),$B5) -> 0 | E5: =SUMIFS(tb_rec_uni[2025-02-01], INDIRECT("tb_rec_uni[natureza]"),"repasse.cef.obra", INDIRECT("tb_rec_uni[empresa]"),$B5)+ SUMIFS(tb_rec_uni[2025-02-01], INDIRECT("tb_rec_uni[natureza]"),"repasse.cef.terreno", INDIRECT("tb_rec_uni[empresa]"),$B5) -> 0 | F5: =SUMIFS(tb_rec_uni[2025-03-01], INDIRECT("tb_rec_uni[natureza]"),"repasse.cef.obra", INDIRECT("tb_rec_uni[empresa]"),$B5)+ SUMIFS(tb_rec_uni[2025-03-01], INDIRECT("tb_rec_uni[natureza]"),"repasse.cef.terreno", INDIRECT("tb_rec_uni[empresa]"),$B5) -> 0 | G5: =SUMIFS(tb_rec_uni[2025-04-01], INDIRECT("tb_rec_uni[natureza]"),"repasse.cef.obra", INDIRECT("tb_rec_uni[empresa]"),$B5)+ SUMIFS(tb_rec_uni[2025-04-01], INDIRECT("tb_rec_uni[natureza]"),"repasse.cef.terreno", INDIRECT("tb_rec_uni[empresa]"),$B5) -> 0 | H5: =SUMIFS(tb_rec_uni[2025-05-01], INDIRECT("tb_rec_uni[natureza]"),"repasse.cef.obra", INDIRECT("tb_rec_uni[empresa]"),$B5)+ SUMIFS(tb_rec_uni[2025-05-01], INDIRECT("tb_rec_uni[natureza]"),"repasse.cef.terreno", INDIRECT("tb_rec_uni[empresa]"),$B5) -> 0 | I5: =SUMIFS(tb_rec_uni[2025-06-01], INDIRECT("tb_rec_uni[natureza]"),"repasse.cef.obra", INDIRECT("tb_rec_uni[empresa]"),$B5)+ SUMIFS(tb_rec_uni[2025-06-01], INDIRECT("tb_rec_uni[natureza]"),"repasse.cef.terreno", INDIRECT("tb_rec_uni[empresa]"),$B5) -> 0 | J5: =SUMIFS(tb_rec_uni[2025-07-01], INDIRECT("tb_rec_uni[natureza]"),"repasse.cef.obra", INDIRECT("tb_rec_uni[empresa]"),$B5)+ SUMIFS(tb_rec_uni[2025-07-01], INDIRECT("tb_rec_uni[natureza]"),"repasse.cef.terreno", INDIRECT("tb_rec_uni[empresa]"),$B5) -> 0 | K5: =SUMIFS(tb_rec_uni[2025-08-01], INDIRECT("tb_rec_uni[natureza]"),"repasse.cef.obra", INDIRECT("tb_rec_uni[empresa]"),$B5)+ SUMIFS(tb_rec_uni[2025-08-01], INDIRECT("tb_rec_uni[natureza]"),"repasse.cef.terreno", INDIRECT("tb_rec_uni[empresa]"),$B5) -> 0 | L5: =SUMIFS(tb_rec_uni[2025-09-01], INDIRECT("tb_rec_uni[natureza]"),"repasse.cef.obra", INDIRECT("tb_rec_uni[empresa]"),$B5)+ SUMIFS(tb_rec_uni[2025-09-01], INDIRECT("tb_rec_uni[natureza]"),"repasse.cef.terreno", INDIRECT("tb_rec_uni[empresa]"),$B5) -> 0 | M5: =SUMIFS(tb_rec_uni[2025-10-01], INDIRECT("tb_rec_uni[natureza]"),"repasse.cef.obra", INDIRECT("tb_rec_uni[empresa]"),$B5)+ SUMIFS(tb_rec_uni[2025-10-01], INDIRECT("tb_rec_uni[natureza]"),"repasse.cef.terreno", INDIRECT("tb_rec_uni[empresa]"),$B5) -> 0 | N5: =SUMIFS(tb_rec_uni[2025-11-01], INDIRECT("tb_rec_uni[natureza]"),"repasse.cef.obra", INDIRECT("tb_rec_uni[empresa]"),$B5)+ SUMIFS(tb_rec_uni[2025-11-01], INDIRECT("tb_rec_uni[natureza]"),"repasse.cef.terreno", INDIRECT("tb_rec_uni[empresa]"),$B5) -> 0 | O5: =SUMIFS(tb_rec_uni[2025-12-01], INDIRECT("tb_rec_uni[natureza]"),"repasse.cef.obra", INDIRECT("tb_rec_uni[empresa]"),$B5)+ SUMIFS(tb_rec_uni[2025-12-01], INDIRECT("tb_rec_uni[natureza]"),"repasse.cef.terreno", INDIRECT("tb_rec_uni[empresa]"),$B5) -> 0 | P5: =SUMIFS(tb_rec_uni[2026-01-01], INDIRECT("tb_rec_uni[natureza]"),"repasse.cef.obra", INDIRECT("tb_rec_uni[empresa]"),$B5)+ SUMIFS(tb_rec_uni[2026-01-01], INDIRECT("tb_rec_uni[natureza]"),"repasse.cef.terreno", INDIRECT("tb_rec_uni[empresa]"),$B5) -> 0 | Q5: =SUMIFS(tb_rec_uni[2026-02-01], INDIRECT("tb_rec_uni[natureza]"),"repasse.cef.obra", INDIRECT("tb_rec_uni[empresa]"),$B5)+ SUMIFS(tb_rec_uni[2026-02-01], INDIRECT("tb_rec_uni[natureza]"),"repasse.cef.terreno", INDIRECT("tb_rec_uni[empresa]"),$B5) -> 0 | R5: =SUMIFS(tb_rec_uni[2026-03-01], INDIRECT("tb_rec_uni[natureza]"),"repasse.cef.obra", INDIRECT("tb_rec_uni[empresa]"),$B5)+ SUMIFS(tb_rec_uni[2026-03-01], INDIRECT("tb_rec_uni[natureza]"),"repasse.cef.terreno", INDIRECT("tb_rec_uni[empresa]"),$B5) -> 0 | S5: =SUMIFS(tb_rec_uni[2026-04-01], INDIRECT("tb_rec_uni[natureza]"),"repasse.cef.obra", INDIRECT("tb_rec_uni[empresa]"),$B5)+ SUMIFS(tb_rec_uni[2026-04-01], INDIRECT("tb_rec_uni[natureza]"),"repasse.cef.terreno", INDIRECT("tb_rec_uni[empresa]"),$B5) -> 0 | T5: =SUMIFS(tb_rec_uni[2026-05-01], INDIRECT("tb_rec_uni[natureza]"),"repasse.cef.obra", INDIRECT("tb_rec_uni[empresa]"),$B5)+ SUMIFS(tb_rec_uni[2026-05-01], INDIRECT("tb_rec_uni[natureza]"),"repasse.cef.terreno", INDIRECT("tb_rec_uni[empresa]"),$B5) -> 0 | U5: =SUMIFS(tb_rec_uni[2026-06-01], INDIRECT("tb_rec_uni[natureza]"),"repasse.cef.obra", INDIRECT("tb_rec_uni[empresa]"),$B5)+ SUMIFS(tb_rec_uni[2026-06-01], INDIRECT("tb_rec_uni[natureza]"),"repasse.cef.terreno", INDIRECT("tb_rec_uni[empresa]"),$B5) -> 0 | V5: =SUMIFS(tb_rec_uni[2026-07-01], INDIRECT("tb_rec_uni[natureza]"),"repasse.cef.obra", INDIRECT("tb_rec_uni[empresa]"),$B5)+ SUMIFS(tb_rec_uni[2026-07-01], INDIRECT("tb_rec_uni[natureza]"),"repasse.cef.terreno", INDIRECT("tb_rec_uni[empresa]"),$B5) -> 0 | W5: =SUMIFS(tb_rec_uni[2026-08-01], INDIRECT("tb_rec_uni[natureza]"),"repasse.cef.obra", INDIRECT("tb_rec_uni[empresa]"),$B5)+ SUMIFS(tb_rec_uni[2026-08-01], INDIRECT("tb_rec_uni[natureza]"),"repasse.cef.terreno", INDIRECT("tb_rec_uni[empresa]"),$B5) -> 0 | X5: =SUMIFS(tb_rec_uni[2026-09-01], INDIRECT("tb_rec_uni[natureza]"),"repasse.cef.obra", INDIRECT("tb_rec_uni[empresa]"),$B5)+ SUMIFS(tb_rec_uni[2026-09-01], INDIRECT("tb_rec_uni[natureza]"),"repasse.cef.terreno", INDIRECT("tb_rec_uni[empresa]"),$B5) -> 0 | Y5: =SUMIFS(tb_rec_uni[2026-10-01], INDIRECT("tb_rec_uni[natureza]"),"repasse.cef.obra", INDIRECT("tb_rec_uni[empresa]"),$B5)+ SUMIFS(tb_rec_uni[2026-10-01], INDIRECT("tb_rec_uni[natureza]"),"repasse.cef.terreno", INDIRECT("tb_rec_uni[empresa]"),$B5) -> 0 | Z5: =SUMIFS(tb_rec_uni[2026-11-01], INDIRECT("tb_rec_uni[natureza]"),"repasse.cef.obra", INDIRECT("tb_rec_uni[empresa]"),$B5)+ SUMIFS(tb_rec_uni[2026-11-01], INDIRECT("tb_rec_uni[natureza]"),"repasse.cef.terreno", INDIRECT("tb_rec_uni[empresa]"),$B5) -> 0 | AA5: =SUMIFS(tb_rec_uni[2026-12-01], INDIRECT("tb_rec_uni[natureza]"),"repasse.cef.obra", INDIRECT("tb_rec_uni[empresa]"),$B5)+ SUMIFS(tb_rec_uni[2026-12-01], INDIRECT("tb_rec_uni[natureza]"),"repasse.cef.terreno", INDIRECT("tb_rec_uni[empresa]"),$B5) -> 0 | AC5: =SUM($D5:INDEX($D5:$AA5,1,MATCH(DATE(YEAR(inputs!$A$1),MONTH(inputs!$A$1),1),$D$1:$AA$1,0))) -> 0 | AE5: =SUM(D5:AA5) -> 0
A6: 1.1.1.GRA. | B6: GRA | C6: CEF | D6: =SUMIFS(tb_rec_uni[2025-01-01], INDIRECT("tb_rec_uni[natureza]"),"repasse.cef.obra", INDIRECT("tb_rec_uni[empresa]"),$B6)+ SUMIFS(tb_rec_uni[2025-01-01], INDIRECT("tb_rec_uni[natureza]"),"repasse.cef.terreno", INDIRECT("tb_rec_uni[empresa]"),$B6) -> 0 | E6: =SUMIFS(tb_rec_uni[2025-02-01], INDIRECT("tb_rec_uni[natureza]"),"repasse.cef.obra", INDIRECT("tb_rec_uni[empresa]"),$B6)+ SUMIFS(tb_rec_uni[2025-02-01], INDIRECT("tb_rec_uni[natureza]"),"repasse.cef.terreno", INDIRECT("tb_rec_uni[empresa]"),$B6) -> 0 | F6: =SUMIFS(tb_rec_uni[2025-03-01], INDIRECT("tb_rec_uni[natureza]"),"repasse.cef.obra", INDIRECT("tb_rec_uni[empresa]"),$B6)+ SUMIFS(tb_rec_uni[2025-03-01], INDIRECT("tb_rec_uni[natureza]"),"repasse.cef.terreno", INDIRECT("tb_rec_uni[empresa]"),$B6) -> 0 | G6: =SUMIFS(tb_rec_uni[2025-04-01], INDIRECT("tb_rec_uni[natureza]"),"repasse.cef.obra", INDIRECT("tb_rec_uni[empresa]"),$B6)+ SUMIFS(tb_rec_uni[2025-04-01], INDIRECT("tb_rec_uni[natureza]"),"repasse.cef.terreno", INDIRECT("tb_rec_uni[empresa]"),$B6) -> 0 | H6: =SUMIFS(tb_rec_uni[2025-05-01], INDIRECT("tb_rec_uni[natureza]"),"repasse.cef.obra", INDIRECT("tb_rec_uni[empresa]"),$B6)+ SUMIFS(tb_rec_uni[2025-05-01], INDIRECT("tb_rec_uni[natureza]"),"repasse.cef.terreno", INDIRECT("tb_rec_uni[empresa]"),$B6) -> 0 | I6: =SUMIFS(tb_rec_uni[2025-06-01], INDIRECT("tb_rec_uni[natureza]"),"repasse.cef.obra", INDIRECT("tb_rec_uni[empresa]"),$B6)+ SUMIFS(tb_rec_uni[2025-06-01], INDIRECT("tb_rec_uni[natureza]"),"repasse.cef.terreno", INDIRECT("tb_rec_uni[empresa]"),$B6) -> 0 | J6: =SUMIFS(tb_rec_uni[2025-07-01], INDIRECT("tb_rec_uni[natureza]"),"repasse.cef.obra", INDIRECT("tb_rec_uni[empresa]"),$B6)+ SUMIFS(tb_rec_uni[2025-07-01], INDIRECT("tb_rec_uni[natureza]"),"repasse.cef.terreno", INDIRECT("tb_rec_uni[empresa]"),$B6) -> 0 | K6: =SUMIFS(tb_rec_uni[2025-08-01], INDIRECT("tb_rec_uni[natureza]"),"repasse.cef.obra", INDIRECT("tb_rec_uni[empresa]"),$B6)+ SUMIFS(tb_rec_uni[2025-08-01], INDIRECT("tb_rec_uni[natureza]"),"repasse.cef.terreno", INDIRECT("tb_rec_uni[empresa]"),$B6) -> 0 | L6: =SUMIFS(tb_rec_uni[2025-09-01], INDIRECT("tb_rec_uni[natureza]"),"repasse.cef.obra", INDIRECT("tb_rec_uni[empresa]"),$B6)+ SUMIFS(tb_rec_uni[2025-09-01], INDIRECT("tb_rec_uni[natureza]"),"repasse.cef.terreno", INDIRECT("tb_rec_uni[empresa]"),$B6) -> 0 | M6: =SUMIFS(tb_rec_uni[2025-10-01], INDIRECT("tb_rec_uni[natureza]"),"repasse.cef.obra", INDIRECT("tb_rec_uni[empresa]"),$B6)+ SUMIFS(tb_rec_uni[2025-10-01], INDIRECT("tb_rec_uni[natureza]"),"repasse.cef.terreno", INDIRECT("tb_rec_uni[empresa]"),$B6) -> 0 | N6: =SUMIFS(tb_rec_uni[2025-11-01], INDIRECT("tb_rec_uni[natureza]"),"repasse.cef.obra", INDIRECT("tb_rec_uni[empresa]"),$B6)+ SUMIFS(tb_rec_uni[2025-11-01], INDIRECT("tb_rec_uni[natureza]"),"repasse.cef.terreno", INDIRECT("tb_rec_uni[empresa]"),$B6) -> 0 | O6: =SUMIFS(tb_rec_uni[2025-12-01], INDIRECT("tb_rec_uni[natureza]"),"repasse.cef.obra", INDIRECT("tb_rec_uni[empresa]"),$B6)+ SUMIFS(tb_rec_uni[2025-12-01], INDIRECT("tb_rec_uni[natureza]"),"repasse.cef.terreno", INDIRECT("tb_rec_uni[empresa]"),$B6) -> 0 | P6: =SUMIFS(tb_rec_uni[2026-01-01], INDIRECT("tb_rec_uni[natureza]"),"repasse.cef.obra", INDIRECT("tb_rec_uni[empresa]"),$B6)+ SUMIFS(tb_rec_uni[2026-01-01], INDIRECT("tb_rec_uni[natureza]"),"repasse.cef.terreno", INDIRECT("tb_rec_uni[empresa]"),$B6) -> 0 | Q6: =SUMIFS(tb_rec_uni[2026-02-01], INDIRECT("tb_rec_uni[natureza]"),"repasse.cef.obra", INDIRECT("tb_rec_uni[empresa]"),$B6)+ SUMIFS(tb_rec_uni[2026-02-01], INDIRECT("tb_rec_uni[natureza]"),"repasse.cef.terreno", INDIRECT("tb_rec_uni[empresa]"),$B6) -> 0 | R6: =SUMIFS(tb_rec_uni[2026-03-01], INDIRECT("tb_rec_uni[natureza]"),"repasse.cef.obra", INDIRECT("tb_rec_uni[empresa]"),$B6)+ SUMIFS(tb_rec_uni[2026-03-01], INDIRECT("tb_rec_uni[natureza]"),"repasse.cef.terreno", INDIRECT("tb_rec_uni[empresa]"),$B6) -> 0 | S6: =SUMIFS(tb_rec_uni[2026-04-01], INDIRECT("tb_rec_uni[natureza]"),"repasse.cef.obra", INDIRECT("tb_rec_uni[empresa]"),$B6)+ SUMIFS(tb_rec_uni[2026-04-01], INDIRECT("tb_rec_uni[natureza]"),"repasse.cef.terreno", INDIRECT("tb_rec_uni[empresa]"),$B6) -> 0 | T6: =SUMIFS(tb_rec_uni[2026-05-01], INDIRECT("tb_rec_uni[natureza]"),"repasse.cef.obra", INDIRECT("tb_rec_uni[empresa]"),$B6)+ SUMIFS(tb_rec_uni[2026-05-01], INDIRECT("tb_rec_uni[natureza]"),"repasse.cef.terreno", INDIRECT("tb_rec_uni[empresa]"),$B6) -> 0 | U6: =SUMIFS(tb_rec_uni[2026-06-01], INDIRECT("tb_rec_uni[natureza]"),"repasse.cef.obra", INDIRECT("tb_rec_uni[empresa]"),$B6)+ SUMIFS(tb_rec_uni[2026-06-01], INDIRECT("tb_rec_uni[natureza]"),"repasse.cef.terreno", INDIRECT("tb_rec_uni[empresa]"),$B6) -> 0 | V6: =SUMIFS(tb_rec_uni[2026-07-01], INDIRECT("tb_rec_uni[natureza]"),"repasse.cef.obra", INDIRECT("tb_rec_uni[empresa]"),$B6)+ SUMIFS(tb_rec_uni[2026-07-01], INDIRECT("tb_rec_uni[natureza]"),"repasse.cef.terreno", INDIRECT("tb_rec_uni[empresa]"),$B6) -> 0 | W6: =SUMIFS(tb_rec_uni[2026-08-01], INDIRECT("tb_rec_uni[natureza]"),"repasse.cef.obra", INDIRECT("tb_rec_uni[empresa]"),$B6)+ SUMIFS(tb_rec_uni[2026-08-01], INDIRECT("tb_rec_uni[natureza]"),"repasse.cef.terreno", INDIRECT("tb_rec_uni[empresa]"),$B6) -> 0 | X6: =SUMIFS(tb_rec_uni[2026-09-01], INDIRECT("tb_rec_uni[natureza]"),"repasse.cef.obra", INDIRECT("tb_rec_uni[empresa]"),$B6)+ SUMIFS(tb_rec_uni[2026-09-01], INDIRECT("tb_rec_uni[natureza]"),"repasse.cef.terreno", INDIRECT("tb_rec_uni[empresa]"),$B6) -> 0 | Y6: =SUMIFS(tb_rec_uni[2026-10-01], INDIRECT("tb_rec_uni[natureza]"),"repasse.cef.obra", INDIRECT("tb_rec_uni[empresa]"),$B6)+ SUMIFS(tb_rec_uni[2026-10-01], INDIRECT("tb_rec_uni[natureza]"),"repasse.cef.terreno", INDIRECT("tb_rec_uni[empresa]"),$B6) -> 0 | Z6: =SUMIFS(tb_rec_uni[2026-11-01], INDIRECT("tb_rec_uni[natureza]"),"repasse.cef.obra", INDIRECT("tb_rec_uni[empresa]"),$B6)+ SUMIFS(tb_rec_uni[2026-11-01], INDIRECT("tb_rec_uni[natureza]"),"repasse.cef.terreno", INDIRECT("tb_rec_uni[empresa]"),$B6) -> 0 | AA6: =SUMIFS(tb_rec_uni[2026-12-01], INDIRECT("tb_rec_uni[natureza]"),"repasse.cef.obra", INDIRECT("tb_rec_uni[empresa]"),$B6)+ SUMIFS(tb_rec_uni[2026-12-01], INDIRECT("tb_rec_uni[natureza]"),"repasse.cef.terreno", INDIRECT("tb_rec_uni[empresa]"),$B6) -> 0 | AC6: =SUM($D6:INDEX($D6:$AA6,1,MATCH(DATE(YEAR(inputs!$A$1),MONTH(inputs!$A$1),1),$D$1:$AA$1,0))) -> 0 | AE6: =SUM(D6:AA6) -> 0
A7: 1.1.1.AMP. | B7: AMP | C7: CEF | D7: =SUMIFS(tb_rec_uni[2025-01-01], INDIRECT("tb_rec_uni[natureza]"),"repasse.cef.obra", INDIRECT("tb_rec_uni[empresa]"),$B7)+ SUMIFS(tb_rec_uni[2025-01-01], INDIRECT("tb_rec_uni[natureza]"),"repasse.cef.terreno", INDIRECT("tb_rec_uni[empresa]"),$B7) -> 0 | E7: =SUMIFS(tb_rec_uni[2025-02-01], INDIRECT("tb_rec_uni[natureza]"),"repasse.cef.obra", INDIRECT("tb_rec_uni[empresa]"),$B7)+ SUMIFS(tb_rec_uni[2025-02-01], INDIRECT("tb_rec_uni[natureza]"),"repasse.cef.terreno", INDIRECT("tb_rec_uni[empresa]"),$B7) -> 0 | F7: =SUMIFS(tb_rec_uni[2025-03-01], INDIRECT("tb_rec_uni[natureza]"),"repasse.cef.obra", INDIRECT("tb_rec_uni[empresa]"),$B7)+ SUMIFS(tb_rec_uni[2025-03-01], INDIRECT("tb_rec_uni[natureza]"),"repasse.cef.terreno", INDIRECT("tb_rec_uni[empresa]"),$B7) -> 0 | G7: =SUMIFS(tb_rec_uni[2025-04-01], INDIRECT("tb_rec_uni[natureza]"),"repasse.cef.obra", INDIRECT("tb_rec_uni[empresa]"),$B7)+ SUMIFS(tb_rec_uni[2025-04-01], INDIRECT("tb_rec_uni[natureza]"),"repasse.cef.terreno", INDIRECT("tb_rec_uni[empresa]"),$B7) -> 0 | H7: =SUMIFS(tb_rec_uni[2025-05-01], INDIRECT("tb_rec_uni[natureza]"),"repasse.cef.obra", INDIRECT("tb_rec_uni[empresa]"),$B7)+ SUMIFS(tb_rec_uni[2025-05-01], INDIRECT("tb_rec_uni[natureza]"),"repasse.cef.terreno", INDIRECT("tb_rec_uni[empresa]"),$B7) -> 0 | I7: =SUMIFS(tb_rec_uni[2025-06-01], INDIRECT("tb_rec_uni[natureza]"),"repasse.cef.obra", INDIRECT("tb_rec_uni[empresa]"),$B7)+ SUMIFS(tb_rec_uni[2025-06-01], INDIRECT("tb_rec_uni[natureza]"),"repasse.cef.terreno", INDIRECT("tb_rec_uni[empresa]"),$B7) -> 0 | J7: =SUMIFS(tb_rec_uni[2025-07-01], INDIRECT("tb_rec_uni[natureza]"),"repasse.cef.obra", INDIRECT("tb_rec_uni[empresa]"),$B7)+ SUMIFS(tb_rec_uni[2025-07-01], INDIRECT("tb_rec_uni[natureza]"),"repasse.cef.terreno", INDIRECT("tb_rec_uni[empresa]"),$B7) -> 0 | K7: =SUMIFS(tb_rec_uni[2025-08-01], INDIRECT("tb_rec_uni[natureza]"),"repasse.cef.obra", INDIRECT("tb_rec_uni[empresa]"),$B7)+ SUMIFS(tb_rec_uni[2025-08-01], INDIRECT("tb_rec_uni[natureza]"),"repasse.cef.terreno", INDIRECT("tb_rec_uni[empresa]"),$B7) -> 0 | L7: =SUMIFS(tb_rec_uni[2025-09-01], INDIRECT("tb_rec_uni[natureza]"),"repasse.cef.obra", INDIRECT("tb_rec_uni[empresa]"),$B7)+ SUMIFS(tb_rec_uni[2025-09-01], INDIRECT("tb_rec_uni[natureza]"),"repasse.cef.terreno", INDIRECT("tb_rec_uni[empresa]"),$B7) -> 0 | M7: =SUMIFS(tb_rec_uni[2025-10-01], INDIRECT("tb_rec_uni[natureza]"),"repasse.cef.obra", INDIRECT("tb_rec_uni[empresa]"),$B7)+ SUMIFS(tb_rec_uni[2025-10-01], INDIRECT("tb_rec_uni[natureza]"),"repasse.cef.terreno", INDIRECT("tb_rec_uni[empresa]"),$B7) -> 0 | N7: =SUMIFS(tb_rec_uni[2025-11-01], INDIRECT("tb_rec_uni[natureza]"),"repasse.cef.obra", INDIRECT("tb_rec_uni[empresa]"),$B7)+ SUMIFS(tb_rec_uni[2025-11-01], INDIRECT("tb_rec_uni[natureza]"),"repasse.cef.terreno", INDIRECT("tb_rec_uni[empresa]"),$B7) -> 0 | O7: =SUMIFS(tb_rec_uni[2025-12-01], INDIRECT("tb_rec_uni[natureza]"),"repasse.cef.obra", INDIRECT("tb_rec_uni[empresa]"),$B7)+ SUMIFS(tb_rec_uni[2025-12-01], INDIRECT("tb_rec_uni[natureza]"),"repasse.cef.terreno", INDIRECT("tb_rec_uni[empresa]"),$B7) -> 0 | P7: =SUMIFS(tb_rec_uni[2026-01-01], INDIRECT("tb_rec_uni[natureza]"),"repasse.cef.obra", INDIRECT("tb_rec_uni[empresa]"),$B7)+ SUMIFS(tb_rec_uni[2026-01-01], INDIRECT("tb_rec_uni[natureza]"),"repasse.cef.terreno", INDIRECT("tb_rec_uni[empresa]"),$B7) -> 0 | Q7: =SUMIFS(tb_rec_uni[2026-02-01], INDIRECT("tb_rec_uni[natureza]"),"repasse.cef.obra", INDIRECT("tb_rec_uni[empresa]"),$B7)+ SUMIFS(tb_rec_uni[2026-02-01], INDIRECT("tb_rec_uni[natureza]"),"repasse.cef.terreno", INDIRECT("tb_rec_uni[empresa]"),$B7) -> 0 | R7: =SUMIFS(tb_rec_uni[2026-03-01], INDIRECT("tb_rec_uni[natureza]"),"repasse.cef.obra", INDIRECT("tb_rec_uni[empresa]"),$B7)+ SUMIFS(tb_rec_uni[2026-03-01], INDIRECT("tb_rec_uni[natureza]"),"repasse.cef.terreno", INDIRECT("tb_rec_uni[empresa]"),$B7) -> 0 | S7: =SUMIFS(tb_rec_uni[2026-04-01], INDIRECT("tb_rec_uni[natureza]"),"repasse.cef.obra", INDIRECT("tb_rec_uni[empresa]"),$B7)+ SUMIFS(tb_rec_uni[2026-04-01], INDIRECT("tb_rec_uni[natureza]"),"repasse.cef.terreno", INDIRECT("tb_rec_uni[empresa]"),$B7) -> 0 | T7: =SUMIFS(tb_rec_uni[2026-05-01], INDIRECT("tb_rec_uni[natureza]"),"repasse.cef.obra", INDIRECT("tb_rec_uni[empresa]"),$B7)+ SUMIFS(tb_rec_uni[2026-05-01], INDIRECT("tb_rec_uni[natureza]"),"repasse.cef.terreno", INDIRECT("tb_rec_uni[empresa]"),$B7) -> 0 | U7: =SUMIFS(tb_rec_uni[2026-06-01], INDIRECT("tb_rec_uni[natureza]"),"repasse.cef.obra", INDIRECT("tb_rec_uni[empresa]"),$B7)+ SUMIFS(tb_rec_uni[2026-06-01], INDIRECT("tb_rec_uni[natureza]"),"repasse.cef.terreno", INDIRECT("tb_rec_uni[empresa]"),$B7) -> 0 | V7: =SUMIFS(tb_rec_uni[2026-07-01], INDIRECT("tb_rec_uni[natureza]"),"repasse.cef.obra", INDIRECT("tb_rec_uni[empresa]"),$B7)+ SUMIFS(tb_rec_uni[2026-07-01], INDIRECT("tb_rec_uni[natureza]"),"repasse.cef.terreno", INDIRECT("tb_rec_uni[empresa]"),$B7) -> 0 | W7: =SUMIFS(tb_rec_uni[2026-08-01], INDIRECT("tb_rec_uni[natureza]"),"repasse.cef.obra", INDIRECT("tb_rec_uni[empresa]"),$B7)+ SUMIFS(tb_rec_uni[2026-08-01], INDIRECT("tb_rec_uni[natureza]"),"repasse.cef.terreno", INDIRECT("tb_rec_uni[empresa]"),$B7) -> 0 | X7: =SUMIFS(tb_rec_uni[2026-09-01], INDIRECT("tb_rec_uni[natureza]"),"repasse.cef.obra", INDIRECT("tb_rec_uni[empresa]"),$B7)+ SUMIFS(tb_rec_uni[2026-09-01], INDIRECT("tb_rec_uni[natureza]"),"repasse.cef.terreno", INDIRECT("tb_rec_uni[empresa]"),$B7) -> 0 | Y7: =SUMIFS(tb_rec_uni[2026-10-01], INDIRECT("tb_rec_uni[natureza]"),"repasse.cef.obra", INDIRECT("tb_rec_uni[empresa]"),$B7)+ SUMIFS(tb_rec_uni[2026-10-01], INDIRECT("tb_rec_uni[natureza]"),"repasse.cef.terreno", INDIRECT("tb_rec_uni[empresa]"),$B7) -> 0 | Z7: =SUMIFS(tb_rec_uni[2026-11-01], INDIRECT("tb_rec_uni[natureza]"),"repasse.cef.obra", INDIRECT("tb_rec_uni[empresa]"),$B7)+ SUMIFS(tb_rec_uni[2026-11-01], INDIRECT("tb_rec_uni[natureza]"),"repasse.cef.terreno", INDIRECT("tb_rec_uni[empresa]"),$B7) -> 0 | AA7: =SUMIFS(tb_rec_uni[2026-12-01], INDIRECT("tb_rec_uni[natureza]"),"repasse.cef.obra", INDIRECT("tb_rec_uni[empresa]"),$B7)+ SUMIFS(tb_rec_uni[2026-12-01], INDIRECT("tb_rec_uni[natureza]"),"repasse.cef.terreno", INDIRECT("tb_rec_uni[empresa]"),$B7) -> 0 | AC7: =SUM($D7:INDEX($D7:$AA7,1,MATCH(DATE(YEAR(inputs!$A$1),MONTH(inputs!$A$1),1),$D$1:$AA$1,0))) -> 0 | AE7: =SUM(D7:AA7) -> 0
A8: 1.1.1.LUC. | B8: LUC | C8: CEF | D8: =SUMIFS(tb_rec_uni[2025-01-01], INDIRECT("tb_rec_uni[natureza]"),"repasse.cef.obra", INDIRECT("tb_rec_uni[empresa]"),$B8)+ SUMIFS(tb_rec_uni[2025-01-01], INDIRECT("tb_rec_uni[natureza]"),"repasse.cef.terreno", INDIRECT("tb_rec_uni[empresa]"),$B8) -> 0 | E8: =SUMIFS(tb_rec_uni[2025-02-01], INDIRECT("tb_rec_uni[natureza]"),"repasse.cef.obra", INDIRECT("tb_rec_uni[empresa]"),$B8)+ SUMIFS(tb_rec_uni[2025-02-01], INDIRECT("tb_rec_uni[natureza]"),"repasse.cef.terreno", INDIRECT("tb_rec_uni[empresa]"),$B8) -> 0 | F8: =SUMIFS(tb_rec_uni[2025-03-01], INDIRECT("tb_rec_uni[natureza]"),"repasse.cef.obra", INDIRECT("tb_rec_uni[empresa]"),$B8)+ SUMIFS(tb_rec_uni[2025-03-01], INDIRECT("tb_rec_uni[natureza]"),"repasse.cef.terreno", INDIRECT("tb_rec_uni[empresa]"),$B8) -> 0 | G8: =SUMIFS(tb_rec_uni[2025-04-01], INDIRECT("tb_rec_uni[natureza]"),"repasse.cef.obra", INDIRECT("tb_rec_uni[empresa]"),$B8)+ SUMIFS(tb_rec_uni[2025-04-01], INDIRECT("tb_rec_uni[natureza]"),"repasse.cef.terreno", INDIRECT("tb_rec_uni[empresa]"),$B8) -> 0 | H8: =SUMIFS(tb_rec_uni[2025-05-01], INDIRECT("tb_rec_uni[natureza]"),"repasse.cef.obra", INDIRECT("tb_rec_uni[empresa]"),$B8)+ SUMIFS(tb_rec_uni[2025-05-01], INDIRECT("tb_rec_uni[natureza]"),"repasse.cef.terreno", INDIRECT("tb_rec_uni[empresa]"),$B8) -> 0 | I8: =SUMIFS(tb_rec_uni[2025-06-01], INDIRECT("tb_rec_uni[natureza]"),"repasse.cef.obra", INDIRECT("tb_rec_uni[empresa]"),$B8)+ SUMIFS(tb_rec_uni[2025-06-01], INDIRECT("tb_rec_uni[natureza]"),"repasse.cef.terreno", INDIRECT("tb_rec_uni[empresa]"),$B8) -> 0 | J8: =SUMIFS(tb_rec_uni[2025-07-01], INDIRECT("tb_rec_uni[natureza]"),"repasse.cef.obra", INDIRECT("tb_rec_uni[empresa]"),$B8)+ SUMIFS(tb_rec_uni[2025-07-01], INDIRECT("tb_rec_uni[natureza]"),"repasse.cef.terreno", INDIRECT("tb_rec_uni[empresa]"),$B8) -> 0 | K8: =SUMIFS(tb_rec_uni[2025-08-01], INDIRECT("tb_rec_uni[natureza]"),"repasse.cef.obra", INDIRECT("tb_rec_uni[empresa]"),$B8)+ SUMIFS(tb_rec_uni[2025-08-01], INDIRECT("tb_rec_uni[natureza]"),"repasse.cef.terreno", INDIRECT("tb_rec_uni[empresa]"),$B8) -> 0 | L8: =SUMIFS(tb_rec_uni[2025-09-01], INDIRECT("tb_rec_uni[natureza]"),"repasse.cef.obra", INDIRECT("tb_rec_uni[empresa]"),$B8)+ SUMIFS(tb_rec_uni[2025-09-01], INDIRECT("tb_rec_uni[natureza]"),"repasse.cef.terreno", INDIRECT("tb_rec_uni[empresa]"),$B8) -> 0 | M8: =SUMIFS(tb_rec_uni[2025-10-01], INDIRECT("tb_rec_uni[natureza]"),"repasse.cef.obra", INDIRECT("tb_rec_uni[empresa]"),$B8)+ SUMIFS(tb_rec_uni[2025-10-01], INDIRECT("tb_rec_uni[natureza]"),"repasse.cef.terreno", INDIRECT("tb_rec_uni[empresa]"),$B8) -> 0 | N8: =SUMIFS(tb_rec_uni[2025-11-01], INDIRECT("tb_rec_uni[natureza]"),"repasse.cef.obra", INDIRECT("tb_rec_uni[empresa]"),$B8)+ SUMIFS(tb_rec_uni[2025-11-01], INDIRECT("tb_rec_uni[natureza]"),"repasse.cef.terreno", INDIRECT("tb_rec_uni[empresa]"),$B8) -> 0 | O8: =SUMIFS(tb_rec_uni[2025-12-01], INDIRECT("tb_rec_uni[natureza]"),"repasse.cef.obra", INDIRECT("tb_rec_uni[empresa]"),$B8)+ SUMIFS(tb_rec_uni[2025-12-01], INDIRECT("tb_rec_uni[natureza]"),"repasse.cef.terreno", INDIRECT("tb_rec_uni[empresa]"),$B8) -> 0 | P8: =SUMIFS(tb_rec_uni[2026-01-01], INDIRECT("tb_rec_uni[natureza]"),"repasse.cef.obra", INDIRECT("tb_rec_uni[empresa]"),$B8)+ SUMIFS(tb_rec_uni[2026-01-01], INDIRECT("tb_rec_uni[natureza]"),"repasse.cef.terreno", INDIRECT("tb_rec_uni[empresa]"),$B8) -> 0 | Q8: =SUMIFS(tb_rec_uni[2026-02-01], INDIRECT("tb_rec_uni[natureza]"),"repasse.cef.obra", INDIRECT("tb_rec_uni[empresa]"),$B8)+ SUMIFS(tb_rec_uni[2026-02-01], INDIRECT("tb_rec_uni[natureza]"),"repasse.cef.terreno", INDIRECT("tb_rec_uni[empresa]"),$B8) -> 0 | R8: =SUMIFS(tb_rec_uni[2026-03-01], INDIRECT("tb_rec_uni[natureza]"),"repasse.cef.obra", INDIRECT("tb_rec_uni[empresa]"),$B8)+ SUMIFS(tb_rec_uni[2026-03-01], INDIRECT("tb_rec_uni[natureza]"),"repasse.cef.terreno", INDIRECT("tb_rec_uni[empresa]"),$B8) -> 0 | S8: =SUMIFS(tb_rec_uni[2026-04-01], INDIRECT("tb_rec_uni[natureza]"),"repasse.cef.obra", INDIRECT("tb_rec_uni[empresa]"),$B8)+ SUMIFS(tb_rec_uni[2026-04-01], INDIRECT("tb_rec_uni[natureza]"),"repasse.cef.terreno", INDIRECT("tb_rec_uni[empresa]"),$B8) -> 0 | T8: =SUMIFS(tb_rec_uni[2026-05-01], INDIRECT("tb_rec_uni[natureza]"),"repasse.cef.obra", INDIRECT("tb_rec_uni[empresa]"),$B8)+ SUMIFS(tb_rec_uni[2026-05-01], INDIRECT("tb_rec_uni[natureza]"),"repasse.cef.terreno", INDIRECT("tb_rec_uni[empresa]"),$B8) -> 0 | U8: =SUMIFS(tb_rec_uni[2026-06-01], INDIRECT("tb_rec_uni[natureza]"),"repasse.cef.obra", INDIRECT("tb_rec_uni[empresa]"),$B8)+ SUMIFS(tb_rec_uni[2026-06-01], INDIRECT("tb_rec_uni[natureza]"),"repasse.cef.terreno", INDIRECT("tb_rec_uni[empresa]"),$B8) -> 0 | V8: =SUMIFS(tb_rec_uni[2026-07-01], INDIRECT("tb_rec_uni[natureza]"),"repasse.cef.obra", INDIRECT("tb_rec_uni[empresa]"),$B8)+ SUMIFS(tb_rec_uni[2026-07-01], INDIRECT("tb_rec_uni[natureza]"),"repasse.cef.terreno", INDIRECT("tb_rec_uni[empresa]"),$B8) -> 0 | W8: =SUMIFS(tb_rec_uni[2026-08-01], INDIRECT("tb_rec_uni[natureza]"),"repasse.cef.obra", INDIRECT("tb_rec_uni[empresa]"),$B8)+ SUMIFS(tb_rec_uni[2026-08-01], INDIRECT("tb_rec_uni[natureza]"),"repasse.cef.terreno", INDIRECT("tb_rec_uni[empresa]"),$B8) -> 0 | X8: =SUMIFS(tb_rec_uni[2026-09-01], INDIRECT("tb_rec_uni[natureza]"),"repasse.cef.obra", INDIRECT("tb_rec_uni[empresa]"),$B8)+ SUMIFS(tb_rec_uni[2026-09-01], INDIRECT("tb_rec_uni[natureza]"),"repasse.cef.terreno", INDIRECT("tb_rec_uni[empresa]"),$B8) -> 0 | Y8: =SUMIFS(tb_rec_uni[2026-10-01], INDIRECT("tb_rec_uni[natureza]"),"repasse.cef.obra", INDIRECT("tb_rec_uni[empresa]"),$B8)+ SUMIFS(tb_rec_uni[2026-10-01], INDIRECT("tb_rec_uni[natureza]"),"repasse.cef.terreno", INDIRECT("tb_rec_uni[empresa]"),$B8) -> 0 | Z8: =SUMIFS(tb_rec_uni[2026-11-01], INDIRECT("tb_rec_uni[natureza]"),"repasse.cef.obra", INDIRECT("tb_rec_uni[empresa]"),$B8)+ SUMIFS(tb_rec_uni[2026-11-01], INDIRECT("tb_rec_uni[natureza]"),"repasse.cef.terreno", INDIRECT("tb_rec_uni[empresa]"),$B8) -> 0 | AA8: =SUMIFS(tb_rec_uni[2026-12-01], INDIRECT("tb_rec_uni[natureza]"),"repasse.cef.obra", INDIRECT("tb_rec_uni[empresa]"),$B8)+ SUMIFS(tb_rec_uni[2026-12-01], INDIRECT("tb_rec_uni[natureza]"),"repasse.cef.terreno", INDIRECT("tb_rec_uni[empresa]"),$B8) -> 0 | AC8: =SUM($D8:INDEX($D8:$AA8,1,MATCH(DATE(YEAR(inputs!$A$1),MONTH(inputs!$A$1),1),$D$1:$AA$1,0))) -> 0 | AE8: =SUM(D8:AA8) -> 0
A9: 1.1.1.AVS. | B9: AVS | C9: CEF | D9: =SUMIFS(tb_rec_uni[2025-01-01], INDIRECT("tb_rec_uni[natureza]"),"repasse.cef.obra", INDIRECT("tb_rec_uni[empresa]"),$B9)+ SUMIFS(tb_rec_uni[2025-01-01], INDIRECT("tb_rec_uni[natureza]"),"repasse.cef.terreno", INDIRECT("tb_rec_uni[empresa]"),$B9) -> 0 | E9: =SUMIFS(tb_rec_uni[2025-02-01], INDIRECT("tb_rec_uni[natureza]"),"repasse.cef.obra", INDIRECT("tb_rec_uni[empresa]"),$B9)+ SUMIFS(tb_rec_uni[2025-02-01], INDIRECT("tb_rec_uni[natureza]"),"repasse.cef.terreno", INDIRECT("tb_rec_uni[empresa]"),$B9) -> 0 | F9: =SUMIFS(tb_rec_uni[2025-03-01], INDIRECT("tb_rec_uni[natureza]"),"repasse.cef.obra", INDIRECT("tb_rec_uni[empresa]"),$B9)+ SUMIFS(tb_rec_uni[2025-03-01], INDIRECT("tb_rec_uni[natureza]"),"repasse.cef.terreno", INDIRECT("tb_rec_uni[empresa]"),$B9) -> 0 | G9: =SUMIFS(tb_rec_uni[2025-04-01], INDIRECT("tb_rec_uni[natureza]"),"repasse.cef.obra", INDIRECT("tb_rec_uni[empresa]"),$B9)+ SUMIFS(tb_rec_uni[2025-04-01], INDIRECT("tb_rec_uni[natureza]"),"repasse.cef.terreno", INDIRECT("tb_rec_uni[empresa]"),$B9) -> 0 | H9: =SUMIFS(tb_rec_uni[2025-05-01], INDIRECT("tb_rec_uni[natureza]"),"repasse.cef.obra", INDIRECT("tb_rec_uni[empresa]"),$B9)+ SUMIFS(tb_rec_uni[2025-05-01], INDIRECT("tb_rec_uni[natureza]"),"repasse.cef.terreno", INDIRECT("tb_rec_uni[empresa]"),$B9) -> 0 | I9: =SUMIFS(tb_rec_uni[2025-06-01], INDIRECT("tb_rec_uni[natureza]"),"repasse.cef.obra", INDIRECT("tb_rec_uni[empresa]"),$B9)+ SUMIFS(tb_rec_uni[2025-06-01], INDIRECT("tb_rec_uni[natureza]"),"repasse.cef.terreno", INDIRECT("tb_rec_uni[empresa]"),$B9) -> 0 | J9: =SUMIFS(tb_rec_uni[2025-07-01], INDIRECT("tb_rec_uni[natureza]"),"repasse.cef.obra", INDIRECT("tb_rec_uni[empresa]"),$B9)+ SUMIFS(tb_rec_uni[2025-07-01], INDIRECT("tb_rec_uni[natureza]"),"repasse.cef.terreno", INDIRECT("tb_rec_uni[empresa]"),$B9) -> 0 | K9: =SUMIFS(tb_rec_uni[2025-08-01], INDIRECT("tb_rec_uni[natureza]"),"repasse.cef.obra", INDIRECT("tb_rec_uni[empresa]"),$B9)+ SUMIFS(tb_rec_uni[2025-08-01], INDIRECT("tb_rec_uni[natureza]"),"repasse.cef.terreno", INDIRECT("tb_rec_uni[empresa]"),$B9) -> 0 | L9: =SUMIFS(tb_rec_uni[2025-09-01], INDIRECT("tb_rec_uni[natureza]"),"repasse.cef.obra", INDIRECT("tb_rec_uni[empresa]"),$B9)+ SUMIFS(tb_rec_uni[2025-09-01], INDIRECT("tb_rec_uni[natureza]"),"repasse.cef.terreno", INDIRECT("tb_rec_uni[empresa]"),$B9) -> 0 | M9: =SUMIFS(tb_rec_uni[2025-10-01], INDIRECT("tb_rec_uni[natureza]"),"repasse.cef.obra", INDIRECT("tb_rec_uni[empresa]"),$B9)+ SUMIFS(tb_rec_uni[2025-10-01], INDIRECT("tb_rec_uni[natureza]"),"repasse.cef.terreno", INDIRECT("tb_rec_uni[empresa]"),$B9) -> 0 | N9: =SUMIFS(tb_rec_uni[2025-11-01], INDIRECT("tb_rec_uni[natureza]"),"repasse.cef.obra", INDIRECT("tb_rec_uni[empresa]"),$B9)+ SUMIFS(tb_rec_uni[2025-11-01], INDIRECT("tb_rec_uni[natureza]"),"repasse.cef.terreno", INDIRECT("tb_rec_uni[empresa]"),$B9) -> 0 | O9: =SUMIFS(tb_rec_uni[2025-12-01], INDIRECT("tb_rec_uni[natureza]"),"repasse.cef.obra", INDIRECT("tb_rec_uni[empresa]"),$B9)+ SUMIFS(tb_rec_uni[2025-12-01], INDIRECT("tb_rec_uni[natureza]"),"repasse.cef.terreno", INDIRECT("tb_rec_uni[empresa]"),$B9) -> 0 | P9: =SUMIFS(tb_rec_uni[2026-01-01], INDIRECT("tb_rec_uni[natureza]"),"repasse.cef.obra", INDIRECT("tb_rec_uni[empresa]"),$B9)+ SUMIFS(tb_rec_uni[2026-01-01], INDIRECT("tb_rec_uni[natureza]"),"repasse.cef.terreno", INDIRECT("tb_rec_uni[empresa]"),$B9) -> 0 | Q9: =SUMIFS(tb_rec_uni[2026-02-01], INDIRECT("tb_rec_uni[natureza]"),"repasse.cef.obra", INDIRECT("tb_rec_uni[empresa]"),$B9)+ SUMIFS(tb_rec_uni[2026-02-01], INDIRECT("tb_rec_uni[natureza]"),"repasse.cef.terreno", INDIRECT("tb_rec_uni[empresa]"),$B9) -> 0 | R9: =SUMIFS(tb_rec_uni[2026-03-01], INDIRECT("tb_rec_uni[natureza]"),"repasse.cef.obra", INDIRECT("tb_rec_uni[empresa]"),$B9)+ SUMIFS(tb_rec_uni[2026-03-01], INDIRECT("tb_rec_uni[natureza]"),"repasse.cef.terreno", INDIRECT("tb_rec_uni[empresa]"),$B9) -> 0 | S9: =SUMIFS(tb_rec_uni[2026-04-01], INDIRECT("tb_rec_uni[natureza]"),"repasse.cef.obra", INDIRECT("tb_rec_uni[empresa]"),$B9)+ SUMIFS(tb_rec_uni[2026-04-01], INDIRECT("tb_rec_uni[natureza]"),"repasse.cef.terreno", INDIRECT("tb_rec_uni[empresa]"),$B9) -> 0 | T9: =SUMIFS(tb_rec_uni[2026-05-01], INDIRECT("tb_rec_uni[natureza]"),"repasse.cef.obra", INDIRECT("tb_rec_uni[empresa]"),$B9)+ SUMIFS(tb_rec_uni[2026-05-01], INDIRECT("tb_rec_uni[natureza]"),"repasse.cef.terreno", INDIRECT("tb_rec_uni[empresa]"),$B9) -> 0 | U9: =SUMIFS(tb_rec_uni[2026-06-01], INDIRECT("tb_rec_uni[natureza]"),"repasse.cef.obra", INDIRECT("tb_rec_uni[empresa]"),$B9)+ SUMIFS(tb_rec_uni[2026-06-01], INDIRECT("tb_rec_uni[natureza]"),"repasse.cef.terreno", INDIRECT("tb_rec_uni[empresa]"),$B9) -> 0 | V9: =SUMIFS(tb_rec_uni[2026-07-01], INDIRECT("tb_rec_uni[natureza]"),"repasse.cef.obra", INDIRECT("tb_rec_uni[empresa]"),$B9)+ SUMIFS(tb_rec_uni[2026-07-01], INDIRECT("tb_rec_uni[natureza]"),"repasse.cef.terreno", INDIRECT("tb_rec_uni[empresa]"),$B9) -> 0 | W9: =SUMIFS(tb_rec_uni[2026-08-01], INDIRECT("tb_rec_uni[natureza]"),"repasse.cef.obra", INDIRECT("tb_rec_uni[empresa]"),$B9)+ SUMIFS(tb_rec_uni[2026-08-01], INDIRECT("tb_rec_uni[natureza]"),"repasse.cef.terreno", INDIRECT("tb_rec_uni[empresa]"),$B9) -> 0 | X9: =SUMIFS(tb_rec_uni[2026-09-01], INDIRECT("tb_rec_uni[natureza]"),"repasse.cef.obra", INDIRECT("tb_rec_uni[empresa]"),$B9)+ SUMIFS(tb_rec_uni[2026-09-01], INDIRECT("tb_rec_uni[natureza]"),"repasse.cef.terreno", INDIRECT("tb_rec_uni[empresa]"),$B9) -> 0 | Y9: =SUMIFS(tb_rec_uni[2026-10-01], INDIRECT("tb_rec_uni[natureza]"),"repasse.cef.obra", INDIRECT("tb_rec_uni[empresa]"),$B9)+ SUMIFS(tb_rec_uni[2026-10-01], INDIRECT("tb_rec_uni[natureza]"),"repasse.cef.terreno", INDIRECT("tb_rec_uni[empresa]"),$B9) -> 0 | Z9: =SUMIFS(tb_rec_uni[2026-11-01], INDIRECT("tb_rec_uni[natureza]"),"repasse.cef.obra", INDIRECT("tb_rec_uni[empresa]"),$B9)+ SUMIFS(tb_rec_uni[2026-11-01], INDIRECT("tb_rec_uni[natureza]"),"repasse.cef.terreno", INDIRECT("tb_rec_uni[empresa]"),$B9) -> 0 | AA9: =SUMIFS(tb_rec_uni[2026-12-01], INDIRECT("tb_rec_uni[natureza]"),"repasse.cef.obra", INDIRECT("tb_rec_uni[empresa]"),$B9)+ SUMIFS(tb_rec_uni[2026-12-01], INDIRECT("tb_rec_uni[natureza]"),"repasse.cef.terreno", INDIRECT("tb_rec_uni[empresa]"),$B9) -> 0 | AC9: =SUM($D9:INDEX($D9:$AA9,1,MATCH(DATE(YEAR(inputs!$A$1),MONTH(inputs!$A$1),1),$D$1:$AA$1,0))) -> 0 | AE9: =SUM(D9:AA9) -> 0
A10: 1.1.1.SN4. | B10: SN4 | C10: CEF | D10: =SUMIFS(tb_rec_uni[2025-01-01], INDIRECT("tb_rec_uni[natureza]"),"repasse.cef.obra", INDIRECT("tb_rec_uni[empresa]"),$B10)+ SUMIFS(tb_rec_uni[2025-01-01], INDIRECT("tb_rec_uni[natureza]"),"repasse.cef.terreno", INDIRECT("tb_rec_uni[empresa]"),$B10) -> 0 | E10: =SUMIFS(tb_rec_uni[2025-02-01], INDIRECT("tb_rec_uni[natureza]"),"repasse.cef.obra", INDIRECT("tb_rec_uni[empresa]"),$B10)+ SUMIFS(tb_rec_uni[2025-02-01], INDIRECT("tb_rec_uni[natureza]"),"repasse.cef.terreno", INDIRECT("tb_rec_uni[empresa]"),$B10) -> 0 | F10: =SUMIFS(tb_rec_uni[2025-03-01], INDIRECT("tb_rec_uni[natureza]"),"repasse.cef.obra", INDIRECT("tb_rec_uni[empresa]"),$B10)+ SUMIFS(tb_rec_uni[2025-03-01], INDIRECT("tb_rec_uni[natureza]"),"repasse.cef.terreno", INDIRECT("tb_rec_uni[empresa]"),$B10) -> 0 | G10: =SUMIFS(tb_rec_uni[2025-04-01], INDIRECT("tb_rec_uni[natureza]"),"repasse.cef.obra", INDIRECT("tb_rec_uni[empresa]"),$B10)+ SUMIFS(tb_rec_uni[2025-04-01], INDIRECT("tb_rec_uni[natureza]"),"repasse.cef.terreno", INDIRECT("tb_rec_uni[empresa]"),$B10) -> 0 | H10: =SUMIFS(tb_rec_uni[2025-05-01], INDIRECT("tb_rec_uni[natureza]"),"repasse.cef.obra", INDIRECT("tb_rec_uni[empresa]"),$B10)+ SUMIFS(tb_rec_uni[2025-05-01], INDIRECT("tb_rec_uni[natureza]"),"repasse.cef.terreno", INDIRECT("tb_rec_uni[empresa]"),$B10) -> 0 | I10: =SUMIFS(tb_rec_uni[2025-06-01], INDIRECT("tb_rec_uni[natureza]"),"repasse.cef.obra", INDIRECT("tb_rec_uni[empresa]"),$B10)+ SUMIFS(tb_rec_uni[2025-06-01], INDIRECT("tb_rec_uni[natureza]"),"repasse.cef.terreno", INDIRECT("tb_rec_uni[empresa]"),$B10) -> 0 | J10: =SUMIFS(tb_rec_uni[2025-07-01], INDIRECT("tb_rec_uni[natureza]"),"repasse.cef.obra", INDIRECT("tb_rec_uni[empresa]"),$B10)+ SUMIFS(tb_rec_uni[2025-07-01], INDIRECT("tb_rec_uni[natureza]"),"repasse.cef.terreno", INDIRECT("tb_rec_uni[empresa]"),$B10) -> 0 | K10: =SUMIFS(tb_rec_uni[2025-08-01], INDIRECT("tb_rec_uni[natureza]"),"repasse.cef.obra", INDIRECT("tb_rec_uni[empresa]"),$B10)+ SUMIFS(tb_rec_uni[2025-08-01], INDIRECT("tb_rec_uni[natureza]"),"repasse.cef.terreno", INDIRECT("tb_rec_uni[empresa]"),$B10) -> 0 | L10: =SUMIFS(tb_rec_uni[2025-09-01], INDIRECT("tb_rec_uni[natureza]"),"repasse.cef.obra", INDIRECT("tb_rec_uni[empresa]"),$B10)+ SUMIFS(tb_rec_uni[2025-09-01], INDIRECT("tb_rec_uni[natureza]"),"repasse.cef.terreno", INDIRECT("tb_rec_uni[empresa]"),$B10) -> 0 | M10: =SUMIFS(tb_rec_uni[2025-10-01], INDIRECT("tb_rec_uni[natureza]"),"repasse.cef.obra", INDIRECT("tb_rec_uni[empresa]"),$B10)+ SUMIFS(tb_rec_uni[2025-10-01], INDIRECT("tb_rec_uni[natureza]"),"repasse.cef.terreno", INDIRECT("tb_rec_uni[empresa]"),$B10) -> 0 | N10: =SUMIFS(tb_rec_uni[2025-11-01], INDIRECT("tb_rec_uni[natureza]"),"repasse.cef.obra", INDIRECT("tb_rec_uni[empresa]"),$B10)+ SUMIFS(tb_rec_uni[2025-11-01], INDIRECT("tb_rec_uni[natureza]"),"repasse.cef.terreno", INDIRECT("tb_rec_uni[empresa]"),$B10) -> 0 | O10: =SUMIFS(tb_rec_uni[2025-12-01], INDIRECT("tb_rec_uni[natureza]"),"repasse.cef.obra", INDIRECT("tb_rec_uni[empresa]"),$B10)+ SUMIFS(tb_rec_uni[2025-12-01], INDIRECT("tb_rec_uni[natureza]"),"repasse.cef.terreno", INDIRECT("tb_rec_uni[empresa]"),$B10) -> 0 | P10: =SUMIFS(tb_rec_uni[2026-01-01], INDIRECT("tb_rec_uni[natureza]"),"repasse.cef.obra", INDIRECT("tb_rec_uni[empresa]"),$B10)+ SUMIFS(tb_rec_uni[2026-01-01], INDIRECT("tb_rec_uni[natureza]"),"repasse.cef.terreno", INDIRECT("tb_rec_uni[empresa]"),$B10) -> 0 | Q10: =SUMIFS(tb_rec_uni[2026-02-01], INDIRECT("tb_rec_uni[natureza]"),"repasse.cef.obra", INDIRECT("tb_rec_uni[empresa]"),$B10)+ SUMIFS(tb_rec_uni[2026-02-01], INDIRECT("tb_rec_uni[natureza]"),"repasse.cef.terreno", INDIRECT("tb_rec_uni[empresa]"),$B10) -> 0 | R10: =SUMIFS(tb_rec_uni[2026-03-01], INDIRECT("tb_rec_uni[natureza]"),"repasse.cef.obra", INDIRECT("tb_rec_uni[empresa]"),$B10)+ SUMIFS(tb_rec_uni[2026-03-01], INDIRECT("tb_rec_uni[natureza]"),"repasse.cef.terreno", INDIRECT("tb_rec_uni[empresa]"),$B10) -> 0 | S10: =SUMIFS(tb_rec_uni[2026-04-01], INDIRECT("tb_rec_uni[natureza]"),"repasse.cef.obra", INDIRECT("tb_rec_uni[empresa]"),$B10)+ SUMIFS(tb_rec_uni[2026-04-01], INDIRECT("tb_rec_uni[natureza]"),"repasse.cef.terreno", INDIRECT("tb_rec_uni[empresa]"),$B10) -> 0 | T10: =SUMIFS(tb_rec_uni[2026-05-01], INDIRECT("tb_rec_uni[natureza]"),"repasse.cef.obra", INDIRECT("tb_rec_uni[empresa]"),$B10)+ SUMIFS(tb_rec_uni[2026-05-01], INDIRECT("tb_rec_uni[natureza]"),"repasse.cef.terreno", INDIRECT("tb_rec_uni[empresa]"),$B10) -> 0 | U10: =SUMIFS(tb_rec_uni[2026-06-01], INDIRECT("tb_rec_uni[natureza]"),"repasse.cef.obra", INDIRECT("tb_rec_uni[empresa]"),$B10)+ SUMIFS(tb_rec_uni[2026-06-01], INDIRECT("tb_rec_uni[natureza]"),"repasse.cef.terreno", INDIRECT("tb_rec_uni[empresa]"),$B10) -> 0 | V10: =SUMIFS(tb_rec_uni[2026-07-01], INDIRECT("tb_rec_uni[natureza]"),"repasse.cef.obra", INDIRECT("tb_rec_uni[empresa]"),$B10)+ SUMIFS(tb_rec_uni[2026-07-01], INDIRECT("tb_rec_uni[natureza]"),"repasse.cef.terreno", INDIRECT("tb_rec_uni[empresa]"),$B10) -> 0 | W10: =SUMIFS(tb_rec_uni[2026-08-01], INDIRECT("tb_rec_uni[natureza]"),"repasse.cef.obra", INDIRECT("tb_rec_uni[empresa]"),$B10)+ SUMIFS(tb_rec_uni[2026-08-01], INDIRECT("tb_rec_uni[natureza]"),"repasse.cef.terreno", INDIRECT("tb_rec_uni[empresa]"),$B10) -> 0 | X10: =SUMIFS(tb_rec_uni[2026-09-01], INDIRECT("tb_rec_uni[natureza]"),"repasse.cef.obra", INDIRECT("tb_rec_uni[empresa]"),$B10)+ SUMIFS(tb_rec_uni[2026-09-01], INDIRECT("tb_rec_uni[natureza]"),"repasse.cef.terreno", INDIRECT("tb_rec_uni[empresa]"),$B10) -> 0 | Y10: =SUMIFS(tb_rec_uni[2026-10-01], INDIRECT("tb_rec_uni[natureza]"),"repasse.cef.obra", INDIRECT("tb_rec_uni[empresa]"),$B10)+ SUMIFS(tb_rec_uni[2026-10-01], INDIRECT("tb_rec_uni[natureza]"),"repasse.cef.terreno", INDIRECT("tb_rec_uni[empresa]"),$B10) -> 0 | Z10: =SUMIFS(tb_rec_uni[2026-11-01], INDIRECT("tb_rec_uni[natureza]"),"repasse.cef.obra", INDIRECT("tb_rec_uni[empresa]"),$B10)+ SUMIFS(tb_rec_uni[2026-11-01], INDIRECT("tb_rec_uni[natureza]"),"repasse.cef.terreno", INDIRECT("tb_rec_uni[empresa]"),$B10) -> 0 | AA10: =SUMIFS(tb_rec_uni[2026-12-01], INDIRECT("tb_rec_uni[natureza]"),"repasse.cef.obra", INDIRECT("tb_rec_uni[empresa]"),$B10)+ SUMIFS(tb_rec_uni[2026-12-01], INDIRECT("tb_rec_uni[natureza]"),"repasse.cef.terreno", INDIRECT("tb_rec_uni[empresa]"),$B10) -> 0 | AC10: =SUM($D10:INDEX($D10:$AA10,1,MATCH(DATE(YEAR(inputs!$A$1),MONTH(inputs!$A$1),1),$D$1:$AA$1,0))) -> 0 | AE10: =SUM(D10:AA10) -> 0
A11: 1.1.2. | B11: Pró soluto | C11: IK | D11: =SUM(D$12:D$22) -> 0 | E11: =SUM(E$12:E$22) -> 0 | F11: =SUM(F$12:F$22) -> 0 | G11: =SUM(G$12:G$22) -> 0 | H11: =SUM(H$12:H$22) -> 0 | I11: =SUM(I$12:I$22) -> 0 | J11: =SUM(J$12:J$22) -> 0 | K11: =SUM(K$12:K$22) -> 0 | ... AA11: =SUM(AA$12:AA$22) -> 0 | AC11: =SUM($D11:INDEX($D11:$AA11,1,MATCH(DATE(YEAR(inputs!$A$1),MONTH(inputs!$A$1),1),$D$1:$AA$1,0))) -> 0 | AE11: =SUM(D11:AA11) -> 0
A12: 1.1.2.CBL. | B12: CBL | C12: IK | D12: =SUMIFS(tb_rec_uni[2025-01-01], INDIRECT("tb_rec_uni[natureza]"),"pro.soluto", INDIRECT("tb_rec_uni[empresa]"),$B12) -> 0 | E12: =SUMIFS(tb_rec_uni[2025-02-01], INDIRECT("tb_rec_uni[natureza]"),"pro.soluto", INDIRECT("tb_rec_uni[empresa]"),$B12) -> 0 | F12: =SUMIFS(tb_rec_uni[2025-03-01], INDIRECT("tb_rec_uni[natureza]"),"pro.soluto", INDIRECT("tb_rec_uni[empresa]"),$B12) -> 0 | G12: =SUMIFS(tb_rec_uni[2025-04-01], INDIRECT("tb_rec_uni[natureza]"),"pro.soluto", INDIRECT("tb_rec_uni[empresa]"),$B12) -> 0 | H12: =SUMIFS(tb_rec_uni[2025-05-01], INDIRECT("tb_rec_uni[natureza]"),"pro.soluto", INDIRECT("tb_rec_uni[empresa]"),$B12) -> 0 | I12: =SUMIFS(tb_rec_uni[2025-06-01], INDIRECT("tb_rec_uni[natureza]"),"pro.soluto", INDIRECT("tb_rec_uni[empresa]"),$B12) -> 0 | J12: =SUMIFS(tb_rec_uni[2025-07-01], INDIRECT("tb_rec_uni[natureza]"),"pro.soluto", INDIRECT("tb_rec_uni[empresa]"),$B12) -> 0 | K12: =SUMIFS(tb_rec_uni[2025-08-01], INDIRECT("tb_rec_uni[natureza]"),"pro.soluto", INDIRECT("tb_rec_uni[empresa]"),$B12) -> 0 | L12: =SUMIFS(tb_rec_uni[2025-09-01], INDIRECT("tb_rec_uni[natureza]"),"pro.soluto", INDIRECT("tb_rec_uni[empresa]"),$B12) -> 0 | M12: =SUMIFS(tb_rec_uni[2025-10-01], INDIRECT("tb_rec_uni[natureza]"),"pro.soluto", INDIRECT("tb_rec_uni[empresa]"),$B12) -> 0 | N12: =SUMIFS(tb_rec_uni[2025-11-01], INDIRECT("tb_rec_uni[natureza]"),"pro.soluto", INDIRECT("tb_rec_uni[empresa]"),$B12) -> 0 | O12: =SUMIFS(tb_rec_uni[2025-12-01], INDIRECT("tb_rec_uni[natureza]"),"pro.soluto", INDIRECT("tb_rec_uni[empresa]"),$B12) -> 0 | P12: =SUMIFS(tb_rec_uni[2026-01-01], INDIRECT("tb_rec_uni[natureza]"),"pro.soluto", INDIRECT("tb_rec_uni[empresa]"),$B12) -> 0 | Q12: =SUMIFS(tb_rec_uni[2026-02-01], INDIRECT("tb_rec_uni[natureza]"),"pro.soluto", INDIRECT("tb_rec_uni[empresa]"),$B12) -> 0 | R12: =SUMIFS(tb_rec_uni[2026-03-01], INDIRECT("tb_rec_uni[natureza]"),"pro.soluto", INDIRECT("tb_rec_uni[empresa]"),$B12) -> 0 | S12: =SUMIFS(tb_rec_uni[2026-04-01], INDIRECT("tb_rec_uni[natureza]"),"pro.soluto", INDIRECT("tb_rec_uni[empresa]"),$B12) -> 0 | T12: =SUMIFS(tb_rec_uni[2026-05-01], INDIRECT("tb_rec_uni[natureza]"),"pro.soluto", INDIRECT("tb_rec_uni[empresa]"),$B12) -> 0 | U12: =SUMIFS(tb_rec_uni[2026-06-01], INDIRECT("tb_rec_uni[natureza]"),"pro.soluto", INDIRECT("tb_rec_uni[empresa]"),$B12) -> 0 | V12: =SUMIFS(tb_rec_uni[2026-07-01], INDIRECT("tb_rec_uni[natureza]"),"pro.soluto", INDIRECT("tb_rec_uni[empresa]"),$B12) -> 0 | W12: =SUMIFS(tb_rec_uni[2026-08-01], INDIRECT("tb_rec_uni[natureza]"),"pro.soluto", INDIRECT("tb_rec_uni[empresa]"),$B12) -> 0 | X12: =SUMIFS(tb_rec_uni[2026-09-01], INDIRECT("tb_rec_uni[natureza]"),"pro.soluto", INDIRECT("tb_rec_uni[empresa]"),$B12) -> 0 | Y12: =SUMIFS(tb_rec_uni[2026-10-01], INDIRECT("tb_rec_uni[natureza]"),"pro.soluto", INDIRECT("tb_rec_uni[empresa]"),$B12) -> 0 | Z12: =SUMIFS(tb_rec_uni[2026-11-01], INDIRECT("tb_rec_uni[natureza]"),"pro.soluto", INDIRECT("tb_rec_uni[empresa]"),$B12) -> 0 | AA12: =SUMIFS(tb_rec_uni[2026-12-01], INDIRECT("tb_rec_uni[natureza]"),"pro.soluto", INDIRECT("tb_rec_uni[empresa]"),$B12) -> 0 | AC12: =SUM($D12:INDEX($D12:$AA12,1,MATCH(DATE(YEAR(inputs!$A$1),MONTH(inputs!$A$1),1),$D$1:$AA$1,0))) -> 0 | AE12: =SUM(D12:AA12) -> 0
A13: 1.1.2.SN4. | B13: SN4 | C13: IK | D13: =SUMIFS(tb_rec_uni[2025-01-01], INDIRECT("tb_rec_uni[natureza]"),"pro.soluto", INDIRECT("tb_rec_uni[empresa]"),$B13) -> 0 | E13: =SUMIFS(tb_rec_uni[2025-02-01], INDIRECT("tb_rec_uni[natureza]"),"pro.soluto", INDIRECT("tb_rec_uni[empresa]"),$B13) -> 0 | F13: =SUMIFS(tb_rec_uni[2025-03-01], INDIRECT("tb_rec_uni[natureza]"),"pro.soluto", INDIRECT("tb_rec_uni[empresa]"),$B13) -> 0 | G13: =SUMIFS(tb_rec_uni[2025-04-01], INDIRECT("tb_rec_uni[natureza]"),"pro.soluto", INDIRECT("tb_rec_uni[empresa]"),$B13) -> 0 | H13: =SUMIFS(tb_rec_uni[2025-05-01], INDIRECT("tb_rec_uni[natureza]"),"pro.soluto", INDIRECT("tb_rec_uni[empresa]"),$B13) -> 0 | I13: =SUMIFS(tb_rec_uni[2025-06-01], INDIRECT("tb_rec_uni[natureza]"),"pro.soluto", INDIRECT("tb_rec_uni[empresa]"),$B13) -> 0 | J13: =SUMIFS(tb_rec_uni[2025-07-01], INDIRECT("tb_rec_uni[natureza]"),"pro.soluto", INDIRECT("tb_rec_uni[empresa]"),$B13) -> 0 | K13: =SUMIFS(tb_rec_uni[2025-08-01], INDIRECT("tb_rec_uni[natureza]"),"pro.soluto", INDIRECT("tb_rec_uni[empresa]"),$B13) -> 0 | L13: =SUMIFS(tb_rec_uni[2025-09-01], INDIRECT("tb_rec_uni[natureza]"),"pro.soluto", INDIRECT("tb_rec_uni[empresa]"),$B13) -> 0 | M13: =SUMIFS(tb_rec_uni[2025-10-01], INDIRECT("tb_rec_uni[natureza]"),"pro.soluto", INDIRECT("tb_rec_uni[empresa]"),$B13) -> 0 | N13: =SUMIFS(tb_rec_uni[2025-11-01], INDIRECT("tb_rec_uni[natureza]"),"pro.soluto", INDIRECT("tb_rec_uni[empresa]"),$B13) -> 0 | O13: =SUMIFS(tb_rec_uni[2025-12-01], INDIRECT("tb_rec_uni[natureza]"),"pro.soluto", INDIRECT("tb_rec_uni[empresa]"),$B13) -> 0 | P13: =SUMIFS(tb_rec_uni[2026-01-01], INDIRECT("tb_rec_uni[natureza]"),"pro.soluto", INDIRECT("tb_rec_uni[empresa]"),$B13) -> 0 | Q13: =SUMIFS(tb_rec_uni[2026-02-01], INDIRECT("tb_rec_uni[natureza]"),"pro.soluto", INDIRECT("tb_rec_uni[empresa]"),$B13) -> 0 | R13: =SUMIFS(tb_rec_uni[2026-03-01], INDIRECT("tb_rec_uni[natureza]"),"pro.soluto", INDIRECT("tb_rec_uni[empresa]"),$B13) -> 0 | S13: =SUMIFS(tb_rec_uni[2026-04-01], INDIRECT("tb_rec_uni[natureza]"),"pro.soluto", INDIRECT("tb_rec_uni[empresa]"),$B13) -> 0 | T13: =SUMIFS(tb_rec_uni[2026-05-01], INDIRECT("tb_rec_uni[natureza]"),"pro.soluto", INDIRECT("tb_rec_uni[empresa]"),$B13) -> 0 | U13: =SUMIFS(tb_rec_uni[2026-06-01], INDIRECT("tb_rec_uni[natureza]"),"pro.soluto", INDIRECT("tb_rec_uni[empresa]"),$B13) -> 0 | V13: =SUMIFS(tb_rec_uni[2026-07-01], INDIRECT("tb_rec_uni[natureza]"),"pro.soluto", INDIRECT("tb_rec_uni[empresa]"),$B13) -> 0 | W13: =SUMIFS(tb_rec_uni[2026-08-01], INDIRECT("tb_rec_uni[natureza]"),"pro.soluto", INDIRECT("tb_rec_uni[empresa]"),$B13) -> 0 | X13: =SUMIFS(tb_rec_uni[2026-09-01], INDIRECT("tb_rec_uni[natureza]"),"pro.soluto", INDIRECT("tb_rec_uni[empresa]"),$B13) -> 0 | Y13: =SUMIFS(tb_rec_uni[2026-10-01], INDIRECT("tb_rec_uni[natureza]"),"pro.soluto", INDIRECT("tb_rec_uni[empresa]"),$B13) -> 0 | Z13: =SUMIFS(tb_rec_uni[2026-11-01], INDIRECT("tb_rec_uni[natureza]"),"pro.soluto", INDIRECT("tb_rec_uni[empresa]"),$B13) -> 0 | AA13: =SUMIFS(tb_rec_uni[2026-12-01], INDIRECT("tb_rec_uni[natureza]"),"pro.soluto", INDIRECT("tb_rec_uni[empresa]"),$B13) -> 0 | AC13: =SUM($D13:INDEX($D13:$AA13,1,MATCH(DATE(YEAR(inputs!$A$1),MONTH(inputs!$A$1),1),$D$1:$AA$1,0))) -> 0 | AE13: =SUM(D13:AA13) -> 0
A14: 1.1.2.SN2. | B14: SN2 | C14: IK | D14: =SUMIFS(tb_rec_uni[2025-01-01], INDIRECT("tb_rec_uni[natureza]"),"pro.soluto", INDIRECT("tb_rec_uni[empresa]"),$B14) -> 0 | E14: =SUMIFS(tb_rec_uni[2025-02-01], INDIRECT("tb_rec_uni[natureza]"),"pro.soluto", INDIRECT("tb_rec_uni[empresa]"),$B14) -> 0 | F14: =SUMIFS(tb_rec_uni[2025-03-01], INDIRECT("tb_rec_uni[natureza]"),"pro.soluto", INDIRECT("tb_rec_uni[empresa]"),$B14) -> 0 | G14: =SUMIFS(tb_rec_uni[2025-04-01], INDIRECT("tb_rec_uni[natureza]"),"pro.soluto", INDIRECT("tb_rec_uni[empresa]"),$B14) -> 0 | H14: =SUMIFS(tb_rec_uni[2025-05-01], INDIRECT("tb_rec_uni[natureza]"),"pro.soluto", INDIRECT("tb_rec_uni[empresa]"),$B14) -> 0 | I14: =SUMIFS(tb_rec_uni[2025-06-01], INDIRECT("tb_rec_uni[natureza]"),"pro.soluto", INDIRECT("tb_rec_uni[empresa]"),$B14) -> 0 | J14: =SUMIFS(tb_rec_uni[2025-07-01], INDIRECT("tb_rec_uni[natureza]"),"pro.soluto", INDIRECT("tb_rec_uni[empresa]"),$B14) -> 0 | K14: =SUMIFS(tb_rec_uni[2025-08-01], INDIRECT("tb_rec_uni[natureza]"),"pro.soluto", INDIRECT("tb_rec_uni[empresa]"),$B14) -> 0 | L14: =SUMIFS(tb_rec_uni[2025-09-01], INDIRECT("tb_rec_uni[natureza]"),"pro.soluto", INDIRECT("tb_rec_uni[empresa]"),$B14) -> 0 | M14: =SUMIFS(tb_rec_uni[2025-10-01], INDIRECT("tb_rec_uni[natureza]"),"pro.soluto", INDIRECT("tb_rec_uni[empresa]"),$B14) -> 0 | N14: =SUMIFS(tb_rec_uni[2025-11-01], INDIRECT("tb_rec_uni[natureza]"),"pro.soluto", INDIRECT("tb_rec_uni[empresa]"),$B14) -> 0 | O14: =SUMIFS(tb_rec_uni[2025-12-01], INDIRECT("tb_rec_uni[natureza]"),"pro.soluto", INDIRECT("tb_rec_uni[empresa]"),$B14) -> 0 | P14: =SUMIFS(tb_rec_uni[2026-01-01], INDIRECT("tb_rec_uni[natureza]"),"pro.soluto", INDIRECT("tb_rec_uni[empresa]"),$B14) -> 0 | Q14: =SUMIFS(tb_rec_uni[2026-02-01], INDIRECT("tb_rec_uni[natureza]"),"pro.soluto", INDIRECT("tb_rec_uni[empresa]"),$B14) -> 0 | R14: =SUMIFS(tb_rec_uni[2026-03-01], INDIRECT("tb_rec_uni[natureza]"),"pro.soluto", INDIRECT("tb_rec_uni[empresa]"),$B14) -> 0 | S14: =SUMIFS(tb_rec_uni[2026-04-01], INDIRECT("tb_rec_uni[natureza]"),"pro.soluto", INDIRECT("tb_rec_uni[empresa]"),$B14) -> 0 | T14: =SUMIFS(tb_rec_uni[2026-05-01], INDIRECT("tb_rec_uni[natureza]"),"pro.soluto", INDIRECT("tb_rec_uni[empresa]"),$B14) -> 0 | U14: =SUMIFS(tb_rec_uni[2026-06-01], INDIRECT("tb_rec_uni[natureza]"),"pro.soluto", INDIRECT("tb_rec_uni[empresa]"),$B14) -> 0 | V14: =SUMIFS(tb_rec_uni[2026-07-01], INDIRECT("tb_rec_uni[natureza]"),"pro.soluto", INDIRECT("tb_rec_uni[empresa]"),$B14) -> 0 | W14: =SUMIFS(tb_rec_uni[2026-08-01], INDIRECT("tb_rec_uni[natureza]"),"pro.soluto", INDIRECT("tb_rec_uni[empresa]"),$B14) -> 0 | X14: =SUMIFS(tb_rec_uni[2026-09-01], INDIRECT("tb_rec_uni[natureza]"),"pro.soluto", INDIRECT("tb_rec_uni[empresa]"),$B14) -> 0 | Y14: =SUMIFS(tb_rec_uni[2026-10-01], INDIRECT("tb_rec_uni[natureza]"),"pro.soluto", INDIRECT("tb_rec_uni[empresa]"),$B14) -> 0 | Z14: =SUMIFS(tb_rec_uni[2026-11-01], INDIRECT("tb_rec_uni[natureza]"),"pro.soluto", INDIRECT("tb_rec_uni[empresa]"),$B14) -> 0 | AA14: =SUMIFS(tb_rec_uni[2026-12-01], INDIRECT("tb_rec_uni[natureza]"),"pro.soluto", INDIRECT("tb_rec_uni[empresa]"),$B14) -> 0 | AC14: =SUM($D14:INDEX($D14:$AA14,1,MATCH(DATE(YEAR(inputs!$A$1),MONTH(inputs!$A$1),1),$D$1:$AA$1,0))) -> 0 | AE14: =SUM(D14:AA14) -> 0
A15: 1.1.2.GRA. | B15: GRA | C15: IK | D15: =SUMIFS(tb_rec_uni[2025-01-01], INDIRECT("tb_rec_uni[natureza]"),"pro.soluto", INDIRECT("tb_rec_uni[empresa]"),$B15) -> 0 | E15: =SUMIFS(tb_rec_uni[2025-02-01], INDIRECT("tb_rec_uni[natureza]"),"pro.soluto", INDIRECT("tb_rec_uni[empresa]"),$B15) -> 0 | F15: =SUMIFS(tb_rec_uni[2025-03-01], INDIRECT("tb_rec_uni[natureza]"),"pro.soluto", INDIRECT("tb_rec_uni[empresa]"),$B15) -> 0 | G15: =SUMIFS(tb_rec_uni[2025-04-01], INDIRECT("tb_rec_uni[natureza]"),"pro.soluto", INDIRECT("tb_rec_uni[empresa]"),$B15) -> 0 | H15: =SUMIFS(tb_rec_uni[2025-05-01], INDIRECT("tb_rec_uni[natureza]"),"pro.soluto", INDIRECT("tb_rec_uni[empresa]"),$B15) -> 0 | I15: =SUMIFS(tb_rec_uni[2025-06-01], INDIRECT("tb_rec_uni[natureza]"),"pro.soluto", INDIRECT("tb_rec_uni[empresa]"),$B15) -> 0 | J15: =SUMIFS(tb_rec_uni[2025-07-01], INDIRECT("tb_rec_uni[natureza]"),"pro.soluto", INDIRECT("tb_rec_uni[empresa]"),$B15) -> 0 | K15: =SUMIFS(tb_rec_uni[2025-08-01], INDIRECT("tb_rec_uni[natureza]"),"pro.soluto", INDIRECT("tb_rec_uni[empresa]"),$B15) -> 0 | L15: =SUMIFS(tb_rec_uni[2025-09-01], INDIRECT("tb_rec_uni[natureza]"),"pro.soluto", INDIRECT("tb_rec_uni[empresa]"),$B15) -> 0 | M15: =SUMIFS(tb_rec_uni[2025-10-01], INDIRECT("tb_rec_uni[natureza]"),"pro.soluto", INDIRECT("tb_rec_uni[empresa]"),$B15) -> 0 | N15: =SUMIFS(tb_rec_uni[2025-11-01], INDIRECT("tb_rec_uni[natureza]"),"pro.soluto", INDIRECT("tb_rec_uni[empresa]"),$B15) -> 0 | O15: =SUMIFS(tb_rec_uni[2025-12-01], INDIRECT("tb_rec_uni[natureza]"),"pro.soluto", INDIRECT("tb_rec_uni[empresa]"),$B15) -> 0 | P15: =SUMIFS(tb_rec_uni[2026-01-01], INDIRECT("tb_rec_uni[natureza]"),"pro.soluto", INDIRECT("tb_rec_uni[empresa]"),$B15) -> 0 | Q15: =SUMIFS(tb_rec_uni[2026-02-01], INDIRECT("tb_rec_uni[natureza]"),"pro.soluto", INDIRECT("tb_rec_uni[empresa]"),$B15) -> 0 | R15: =SUMIFS(tb_rec_uni[2026-03-01], INDIRECT("tb_rec_uni[natureza]"),"pro.soluto", INDIRECT("tb_rec_uni[empresa]"),$B15) -> 0 | S15: =SUMIFS(tb_rec_uni[2026-04-01], INDIRECT("tb_rec_uni[natureza]"),"pro.soluto", INDIRECT("tb_rec_uni[empresa]"),$B15) -> 0 | T15: =SUMIFS(tb_rec_uni[2026-05-01], INDIRECT("tb_rec_uni[natureza]"),"pro.soluto", INDIRECT("tb_rec_uni[empresa]"),$B15) -> 0 | U15: =SUMIFS(tb_rec_uni[2026-06-01], INDIRECT("tb_rec_uni[natureza]"),"pro.soluto", INDIRECT("tb_rec_uni[empresa]"),$B15) -> 0 | V15: =SUMIFS(tb_rec_uni[2026-07-01], INDIRECT("tb_rec_uni[natureza]"),"pro.soluto", INDIRECT("tb_rec_uni[empresa]"),$B15) -> 0 | W15: =SUMIFS(tb_rec_uni[2026-08-01], INDIRECT("tb_rec_uni[natureza]"),"pro.soluto", INDIRECT("tb_rec_uni[empresa]"),$B15) -> 0 | X15: =SUMIFS(tb_rec_uni[2026-09-01], INDIRECT("tb_rec_uni[natureza]"),"pro.soluto", INDIRECT("tb_rec_uni[empresa]"),$B15) -> 0 | Y15: =SUMIFS(tb_rec_uni[2026-10-01], INDIRECT("tb_rec_uni[natureza]"),"pro.soluto", INDIRECT("tb_rec_uni[empresa]"),$B15) -> 0 | Z15: =SUMIFS(tb_rec_uni[2026-11-01], INDIRECT("tb_rec_uni[natureza]"),"pro.soluto", INDIRECT("tb_rec_uni[empresa]"),$B15) -> 0 | AA15: =SUMIFS(tb_rec_uni[2026-12-01], INDIRECT("tb_rec_uni[natureza]"),"pro.soluto", INDIRECT("tb_rec_uni[empresa]"),$B15) -> 0 | AC15: =SUM($D15:INDEX($D15:$AA15,1,MATCH(DATE(YEAR(inputs!$A$1),MONTH(inputs!$A$1),1),$D$1:$AA$1,0))) -> 0 | AE15: =SUM(D15:AA15) -> 0
A16: 1.1.2.AMP. | B16: AMP | C16: IK | D16: =SUMIFS(tb_rec_uni[2025-01-01], INDIRECT("tb_rec_uni[natureza]"),"pro.soluto", INDIRECT("tb_rec_uni[empresa]"),$B16) -> 0 | E16: =SUMIFS(tb_rec_uni[2025-02-01], INDIRECT("tb_rec_uni[natureza]"),"pro.soluto", INDIRECT("tb_rec_uni[empresa]"),$B16) -> 0 | F16: =SUMIFS(tb_rec_uni[2025-03-01], INDIRECT("tb_rec_uni[natureza]"),"pro.soluto", INDIRECT("tb_rec_uni[empresa]"),$B16) -> 0 | G16: =SUMIFS(tb_rec_uni[2025-04-01], INDIRECT("tb_rec_uni[natureza]"),"pro.soluto", INDIRECT("tb_rec_uni[empresa]"),$B16) -> 0 | H16: =SUMIFS(tb_rec_uni[2025-05-01], INDIRECT("tb_rec_uni[natureza]"),"pro.soluto", INDIRECT("tb_rec_uni[empresa]"),$B16) -> 0 | I16: =SUMIFS(tb_rec_uni[2025-06-01], INDIRECT("tb_rec_uni[natureza]"),"pro.soluto", INDIRECT("tb_rec_uni[empresa]"),$B16) -> 0 | J16: =SUMIFS(tb_rec_uni[2025-07-01], INDIRECT("tb_rec_uni[natureza]"),"pro.soluto", INDIRECT("tb_rec_uni[empresa]"),$B16) -> 0 | K16: =SUMIFS(tb_rec_uni[2025-08-01], INDIRECT("tb_rec_uni[natureza]"),"pro.soluto", INDIRECT("tb_rec_uni[empresa]"),$B16) -> 0 | L16: =SUMIFS(tb_rec_uni[2025-09-01], INDIRECT("tb_rec_uni[natureza]"),"pro.soluto", INDIRECT("tb_rec_uni[empresa]"),$B16) -> 0 | M16: =SUMIFS(tb_rec_uni[2025-10-01], INDIRECT("tb_rec_uni[natureza]"),"pro.soluto", INDIRECT("tb_rec_uni[empresa]"),$B16) -> 0 | N16: =SUMIFS(tb_rec_uni[2025-11-01], INDIRECT("tb_rec_uni[natureza]"),"pro.soluto", INDIRECT("tb_rec_uni[empresa]"),$B16) -> 0 | O16: =SUMIFS(tb_rec_uni[2025-12-01], INDIRECT("tb_rec_uni[natureza]"),"pro.soluto", INDIRECT("tb_rec_uni[empresa]"),$B16) -> 0 | P16: =SUMIFS(tb_rec_uni[2026-01-01], INDIRECT("tb_rec_uni[natureza]"),"pro.soluto", INDIRECT("tb_rec_uni[empresa]"),$B16) -> 0 | Q16: =SUMIFS(tb_rec_uni[2026-02-01], INDIRECT("tb_rec_uni[natureza]"),"pro.soluto", INDIRECT("tb_rec_uni[empresa]"),$B16) -> 0 | R16: =SUMIFS(tb_rec_uni[2026-03-01], INDIRECT("tb_rec_uni[natureza]"),"pro.soluto", INDIRECT("tb_rec_uni[empresa]"),$B16) -> 0 | S16: =SUMIFS(tb_rec_uni[2026-04-01], INDIRECT("tb_rec_uni[natureza]"),"pro.soluto", INDIRECT("tb_rec_uni[empresa]"),$B16) -> 0 | T16: =SUMIFS(tb_rec_uni[2026-05-01], INDIRECT("tb_rec_uni[natureza]"),"pro.soluto", INDIRECT("tb_rec_uni[empresa]"),$B16) -> 0 | U16: =SUMIFS(tb_rec_uni[2026-06-01], INDIRECT("tb_rec_uni[natureza]"),"pro.soluto", INDIRECT("tb_rec_uni[empresa]"),$B16) -> 0 | V16: =SUMIFS(tb_rec_uni[2026-07-01], INDIRECT("tb_rec_uni[natureza]"),"pro.soluto", INDIRECT("tb_rec_uni[empresa]"),$B16) -> 0 | W16: =SUMIFS(tb_rec_uni[2026-08-01], INDIRECT("tb_rec_uni[natureza]"),"pro.soluto", INDIRECT("tb_rec_uni[empresa]"),$B16) -> 0 | X16: =SUMIFS(tb_rec_uni[2026-09-01], INDIRECT("tb_rec_uni[natureza]"),"pro.soluto", INDIRECT("tb_rec_uni[empresa]"),$B16) -> 0 | Y16: =SUMIFS(tb_rec_uni[2026-10-01], INDIRECT("tb_rec_uni[natureza]"),"pro.soluto", INDIRECT("tb_rec_uni[empresa]"),$B16) -> 0 | Z16: =SUMIFS(tb_rec_uni[2026-11-01], INDIRECT("tb_rec_uni[natureza]"),"pro.soluto", INDIRECT("tb_rec_uni[empresa]"),$B16) -> 0 | AA16: =SUMIFS(tb_rec_uni[2026-12-01], INDIRECT("tb_rec_uni[natureza]"),"pro.soluto", INDIRECT("tb_rec_uni[empresa]"),$B16) -> 0 | AC16: =SUM($D16:INDEX($D16:$AA16,1,MATCH(DATE(YEAR(inputs!$A$1),MONTH(inputs!$A$1),1),$D$1:$AA$1,0))) -> 0 | AE16: =SUM(D16:AA16) -> 0
A17: 1.1.2.POM. | B17: POM | C17: IK | D17: =SUMIFS(tb_rec_uni[2025-01-01], INDIRECT("tb_rec_uni[natureza]"),"pro.soluto", INDIRECT("tb_rec_uni[empresa]"),$B17) -> 0 | E17: =SUMIFS(tb_rec_uni[2025-02-01], INDIRECT("tb_rec_uni[natureza]"),"pro.soluto", INDIRECT("tb_rec_uni[empresa]"),$B17) -> 0 | F17: =SUMIFS(tb_rec_uni[2025-03-01], INDIRECT("tb_rec_uni[natureza]"),"pro.soluto", INDIRECT("tb_rec_uni[empresa]"),$B17) -> 0 | G17: =SUMIFS(tb_rec_uni[2025-04-01], INDIRECT("tb_rec_uni[natureza]"),"pro.soluto", INDIRECT("tb_rec_uni[empresa]"),$B17) -> 0 | H17: =SUMIFS(tb_rec_uni[2025-05-01], INDIRECT("tb_rec_uni[natureza]"),"pro.soluto", INDIRECT("tb_rec_uni[empresa]"),$B17) -> 0 | I17: =SUMIFS(tb_rec_uni[2025-06-01], INDIRECT("tb_rec_uni[natureza]"),"pro.soluto", INDIRECT("tb_rec_uni[empresa]"),$B17) -> 0 | J17: =SUMIFS(tb_rec_uni[2025-07-01], INDIRECT("tb_rec_uni[natureza]"),"pro.soluto", INDIRECT("tb_rec_uni[empresa]"),$B17) -> 0 | K17: =SUMIFS(tb_rec_uni[2025-08-01], INDIRECT("tb_rec_uni[natureza]"),"pro.soluto", INDIRECT("tb_rec_uni[empresa]"),$B17) -> 0 | L17: =SUMIFS(tb_rec_uni[2025-09-01], INDIRECT("tb_rec_uni[natureza]"),"pro.soluto", INDIRECT("tb_rec_uni[empresa]"),$B17) -> 0 | M17: =SUMIFS(tb_rec_uni[2025-10-01], INDIRECT("tb_rec_uni[natureza]"),"pro.soluto", INDIRECT("tb_rec_uni[empresa]"),$B17) -> 0 | N17: =SUMIFS(tb_rec_uni[2025-11-01], INDIRECT("tb_rec_uni[natureza]"),"pro.soluto", INDIRECT("tb_rec_uni[empresa]"),$B17) -> 0 | O17: =SUMIFS(tb_rec_uni[2025-12-01], INDIRECT("tb_rec_uni[natureza]"),"pro.soluto", INDIRECT("tb_rec_uni[empresa]"),$B17) -> 0 | P17: =SUMIFS(tb_rec_uni[2026-01-01], INDIRECT("tb_rec_uni[natureza]"),"pro.soluto", INDIRECT("tb_rec_uni[empresa]"),$B17) -> 0 | Q17: =SUMIFS(tb_rec_uni[2026-02-01], INDIRECT("tb_rec_uni[natureza]"),"pro.soluto", INDIRECT("tb_rec_uni[empresa]"),$B17) -> 0 | R17: =SUMIFS(tb_rec_uni[2026-03-01], INDIRECT("tb_rec_uni[natureza]"),"pro.soluto", INDIRECT("tb_rec_uni[empresa]"),$B17) -> 0 | S17: =SUMIFS(tb_rec_uni[2026-04-01], INDIRECT("tb_rec_uni[natureza]"),"pro.soluto", INDIRECT("tb_rec_uni[empresa]"),$B17) -> 0 | T17: =SUMIFS(tb_rec_uni[2026-05-01], INDIRECT("tb_rec_uni[natureza]"),"pro.soluto", INDIRECT("tb_rec_uni[empresa]"),$B17) -> 0 | U17: =SUMIFS(tb_rec_uni[2026-06-01], INDIRECT("tb_rec_uni[natureza]"),"pro.soluto", INDIRECT("tb_rec_uni[empresa]"),$B17) -> 0 | V17: =SUMIFS(tb_rec_uni[2026-07-01], INDIRECT("tb_rec_uni[natureza]"),"pro.soluto", INDIRECT("tb_rec_uni[empresa]"),$B17) -> 0 | W17: =SUMIFS(tb_rec_uni[2026-08-01], INDIRECT("tb_rec_uni[natureza]"),"pro.soluto", INDIRECT("tb_rec_uni[empresa]"),$B17) -> 0 | X17: =SUMIFS(tb_rec_uni[2026-09-01], INDIRECT("tb_rec_uni[natureza]"),"pro.soluto", INDIRECT("tb_rec_uni[empresa]"),$B17) -> 0 | Y17: =SUMIFS(tb_rec_uni[2026-10-01], INDIRECT("tb_rec_uni[natureza]"),"pro.soluto", INDIRECT("tb_rec_uni[empresa]"),$B17) -> 0 | Z17: =SUMIFS(tb_rec_uni[2026-11-01], INDIRECT("tb_rec_uni[natureza]"),"pro.soluto", INDIRECT("tb_rec_uni[empresa]"),$B17) -> 0 | AA17: =SUMIFS(tb_rec_uni[2026-12-01], INDIRECT("tb_rec_uni[natureza]"),"pro.soluto", INDIRECT("tb_rec_uni[empresa]"),$B17) -> 0 | AC17: =SUM($D17:INDEX($D17:$AA17,1,MATCH(DATE(YEAR(inputs!$A$1),MONTH(inputs!$A$1),1),$D$1:$AA$1,0))) -> 0 | AE17: =SUM(D17:AA17) -> 0
A18: 1.1.2.AVS. | B18: AVS | C18: IK | D18: =SUMIFS(tb_rec_uni[2025-01-01], INDIRECT("tb_rec_uni[natureza]"),"pro.soluto", INDIRECT("tb_rec_uni[empresa]"),$B18) -> 0 | E18: =SUMIFS(tb_rec_uni[2025-02-01], INDIRECT("tb_rec_uni[natureza]"),"pro.soluto", INDIRECT("tb_rec_uni[empresa]"),$B18) -> 0 | F18: =SUMIFS(tb_rec_uni[2025-03-01], INDIRECT("tb_rec_uni[natureza]"),"pro.soluto", INDIRECT("tb_rec_uni[empresa]"),$B18) -> 0 | G18: =SUMIFS(tb_rec_uni[2025-04-01], INDIRECT("tb_rec_uni[natureza]"),"pro.soluto", INDIRECT("tb_rec_uni[empresa]"),$B18) -> 0 | H18: =SUMIFS(tb_rec_uni[2025-05-01], INDIRECT("tb_rec_uni[natureza]"),"pro.soluto", INDIRECT("tb_rec_uni[empresa]"),$B18) -> 0 | I18: =SUMIFS(tb_rec_uni[2025-06-01], INDIRECT("tb_rec_uni[natureza]"),"pro.soluto", INDIRECT("tb_rec_uni[empresa]"),$B18) -> 0 | J18: =SUMIFS(tb_rec_uni[2025-07-01], INDIRECT("tb_rec_uni[natureza]"),"pro.soluto", INDIRECT("tb_rec_uni[empresa]"),$B18) -> 0 | K18: =SUMIFS(tb_rec_uni[2025-08-01], INDIRECT("tb_rec_uni[natureza]"),"pro.soluto", INDIRECT("tb_rec_uni[empresa]"),$B18) -> 0 | L18: =SUMIFS(tb_rec_uni[2025-09-01], INDIRECT("tb_rec_uni[natureza]"),"pro.soluto", INDIRECT("tb_rec_uni[empresa]"),$B18) -> 0 | M18: =SUMIFS(tb_rec_uni[2025-10-01], INDIRECT("tb_rec_uni[natureza]"),"pro.soluto", INDIRECT("tb_rec_uni[empresa]"),$B18) -> 0 | N18: =SUMIFS(tb_rec_uni[2025-11-01], INDIRECT("tb_rec_uni[natureza]"),"pro.soluto", INDIRECT("tb_rec_uni[empresa]"),$B18) -> 0 | O18: =SUMIFS(tb_rec_uni[2025-12-01], INDIRECT("tb_rec_uni[natureza]"),"pro.soluto", INDIRECT("tb_rec_uni[empresa]"),$B18) -> 0 | P18: =SUMIFS(tb_rec_uni[2026-01-01], INDIRECT("tb_rec_uni[natureza]"),"pro.soluto", INDIRECT("tb_rec_uni[empresa]"),$B18) -> 0 | Q18: =SUMIFS(tb_rec_uni[2026-02-01], INDIRECT("tb_rec_uni[natureza]"),"pro.soluto", INDIRECT("tb_rec_uni[empresa]"),$B18) -> 0 | R18: =SUMIFS(tb_rec_uni[2026-03-01], INDIRECT("tb_rec_uni[natureza]"),"pro.soluto", INDIRECT("tb_rec_uni[empresa]"),$B18) -> 0 | S18: =SUMIFS(tb_rec_uni[2026-04-01], INDIRECT("tb_rec_uni[natureza]"),"pro.soluto", INDIRECT("tb_rec_uni[empresa]"),$B18) -> 0 | T18: =SUMIFS(tb_rec_uni[2026-05-01], INDIRECT("tb_rec_uni[natureza]"),"pro.soluto", INDIRECT("tb_rec_uni[empresa]"),$B18) -> 0 | U18: =SUMIFS(tb_rec_uni[2026-06-01], INDIRECT("tb_rec_uni[natureza]"),"pro.soluto", INDIRECT("tb_rec_uni[empresa]"),$B18) -> 0 | V18: =SUMIFS(tb_rec_uni[2026-07-01], INDIRECT("tb_rec_uni[natureza]"),"pro.soluto", INDIRECT("tb_rec_uni[empresa]"),$B18) -> 0 | W18: =SUMIFS(tb_rec_uni[2026-08-01], INDIRECT("tb_rec_uni[natureza]"),"pro.soluto", INDIRECT("tb_rec_uni[empresa]"),$B18) -> 0 | X18: =SUMIFS(tb_rec_uni[2026-09-01], INDIRECT("tb_rec_uni[natureza]"),"pro.soluto", INDIRECT("tb_rec_uni[empresa]"),$B18) -> 0 | Y18: =SUMIFS(tb_rec_uni[2026-10-01], INDIRECT("tb_rec_uni[natureza]"),"pro.soluto", INDIRECT("tb_rec_uni[empresa]"),$B18) -> 0 | Z18: =SUMIFS(tb_rec_uni[2026-11-01], INDIRECT("tb_rec_uni[natureza]"),"pro.soluto", INDIRECT("tb_rec_uni[empresa]"),$B18) -> 0 | AA18: =SUMIFS(tb_rec_uni[2026-12-01], INDIRECT("tb_rec_uni[natureza]"),"pro.soluto", INDIRECT("tb_rec_uni[empresa]"),$B18) -> 0 | AC18: =SUM($D18:INDEX($D18:$AA18,1,MATCH(DATE(YEAR(inputs!$A$1),MONTH(inputs!$A$1),1),$D$1:$AA$1,0))) -> 0 | AE18: =SUM(D18:AA18) -> 0
A19: 1.1.2.LUC. | B19: LUC | C19: IK | D19: =SUMIFS(tb_rec_uni[2025-01-01], INDIRECT("tb_rec_uni[natureza]"),"pro.soluto", INDIRECT("tb_rec_uni[empresa]"),$B19) -> 0 | E19: =SUMIFS(tb_rec_uni[2025-02-01], INDIRECT("tb_rec_uni[natureza]"),"pro.soluto", INDIRECT("tb_rec_uni[empresa]"),$B19) -> 0 | F19: =SUMIFS(tb_rec_uni[2025-03-01], INDIRECT("tb_rec_uni[natureza]"),"pro.soluto", INDIRECT("tb_rec_uni[empresa]"),$B19) -> 0 | G19: =SUMIFS(tb_rec_uni[2025-04-01], INDIRECT("tb_rec_uni[natureza]"),"pro.soluto", INDIRECT("tb_rec_uni[empresa]"),$B19) -> 0 | H19: =SUMIFS(tb_rec_uni[2025-05-01], INDIRECT("tb_rec_uni[natureza]"),"pro.soluto", INDIRECT("tb_rec_uni[empresa]"),$B19) -> 0 | I19: =SUMIFS(tb_rec_uni[2025-06-01], INDIRECT("tb_rec_uni[natureza]"),"pro.soluto", INDIRECT("tb_rec_uni[empresa]"),$B19) -> 0 | J19: =SUMIFS(tb_rec_uni[2025-07-01], INDIRECT("tb_rec_uni[natureza]"),"pro.soluto", INDIRECT("tb_rec_uni[empresa]"),$B19) -> 0 | K19: =SUMIFS(tb_rec_uni[2025-08-01], INDIRECT("tb_rec_uni[natureza]"),"pro.soluto", INDIRECT("tb_rec_uni[empresa]"),$B19) -> 0 | L19: =SUMIFS(tb_rec_uni[2025-09-01], INDIRECT("tb_rec_uni[natureza]"),"pro.soluto", INDIRECT("tb_rec_uni[empresa]"),$B19) -> 0 | M19: =SUMIFS(tb_rec_uni[2025-10-01], INDIRECT("tb_rec_uni[natureza]"),"pro.soluto", INDIRECT("tb_rec_uni[empresa]"),$B19) -> 0 | N19: =SUMIFS(tb_rec_uni[2025-11-01], INDIRECT("tb_rec_uni[natureza]"),"pro.soluto", INDIRECT("tb_rec_uni[empresa]"),$B19) -> 0 | O19: =SUMIFS(tb_rec_uni[2025-12-01], INDIRECT("tb_rec_uni[natureza]"),"pro.soluto", INDIRECT("tb_rec_uni[empresa]"),$B19) -> 0 | P19: =SUMIFS(tb_rec_uni[2026-01-01], INDIRECT("tb_rec_uni[natureza]"),"pro.soluto", INDIRECT("tb_rec_uni[empresa]"),$B19) -> 0 | Q19: =SUMIFS(tb_rec_uni[2026-02-01], INDIRECT("tb_rec_uni[natureza]"),"pro.soluto", INDIRECT("tb_rec_uni[empresa]"),$B19) -> 0 | R19: =SUMIFS(tb_rec_uni[2026-03-01], INDIRECT("tb_rec_uni[natureza]"),"pro.soluto", INDIRECT("tb_rec_uni[empresa]"),$B19) -> 0 | S19: =SUMIFS(tb_rec_uni[2026-04-01], INDIRECT("tb_rec_uni[natureza]"),"pro.soluto", INDIRECT("tb_rec_uni[empresa]"),$B19) -> 0 | T19: =SUMIFS(tb_rec_uni[2026-05-01], INDIRECT("tb_rec_uni[natureza]"),"pro.soluto", INDIRECT("tb_rec_uni[empresa]"),$B19) -> 0 | U19: =SUMIFS(tb_rec_uni[2026-06-01], INDIRECT("tb_rec_uni[natureza]"),"pro.soluto", INDIRECT("tb_rec_uni[empresa]"),$B19) -> 0 | V19: =SUMIFS(tb_rec_uni[2026-07-01], INDIRECT("tb_rec_uni[natureza]"),"pro.soluto", INDIRECT("tb_rec_uni[empresa]"),$B19) -> 0 | W19: =SUMIFS(tb_rec_uni[2026-08-01], INDIRECT("tb_rec_uni[natureza]"),"pro.soluto", INDIRECT("tb_rec_uni[empresa]"),$B19) -> 0 | X19: =SUMIFS(tb_rec_uni[2026-09-01], INDIRECT("tb_rec_uni[natureza]"),"pro.soluto", INDIRECT("tb_rec_uni[empresa]"),$B19) -> 0 | Y19: =SUMIFS(tb_rec_uni[2026-10-01], INDIRECT("tb_rec_uni[natureza]"),"pro.soluto", INDIRECT("tb_rec_uni[empresa]"),$B19) -> 0 | Z19: =SUMIFS(tb_rec_uni[2026-11-01], INDIRECT("tb_rec_uni[natureza]"),"pro.soluto", INDIRECT("tb_rec_uni[empresa]"),$B19) -> 0 | AA19: =SUMIFS(tb_rec_uni[2026-12-01], INDIRECT("tb_rec_uni[natureza]"),"pro.soluto", INDIRECT("tb_rec_uni[empresa]"),$B19) -> 0 | AC19: =SUM($D19:INDEX($D19:$AA19,1,MATCH(DATE(YEAR(inputs!$A$1),MONTH(inputs!$A$1),1),$D$1:$AA$1,0))) -> 0 | AE19: =SUM(D19:AA19) -> 0
A20: 1.1.2.SAU. | B20: SAU | C20: IK | D20: =SUMIFS(tb_rec_uni[2025-01-01], INDIRECT("tb_rec_uni[natureza]"),"pro.soluto", INDIRECT("tb_rec_uni[empresa]"),$B20) -> 0 | E20: =SUMIFS(tb_rec_uni[2025-02-01], INDIRECT("tb_rec_uni[natureza]"),"pro.soluto", INDIRECT("tb_rec_uni[empresa]"),$B20) -> 0 | F20: =SUMIFS(tb_rec_uni[2025-03-01], INDIRECT("tb_rec_uni[natureza]"),"pro.soluto", INDIRECT("tb_rec_uni[empresa]"),$B20) -> 0 | G20: =SUMIFS(tb_rec_uni[2025-04-01], INDIRECT("tb_rec_uni[natureza]"),"pro.soluto", INDIRECT("tb_rec_uni[empresa]"),$B20) -> 0 | H20: =SUMIFS(tb_rec_uni[2025-05-01], INDIRECT("tb_rec_uni[natureza]"),"pro.soluto", INDIRECT("tb_rec_uni[empresa]"),$B20) -> 0 | I20: =SUMIFS(tb_rec_uni[2025-06-01], INDIRECT("tb_rec_uni[natureza]"),"pro.soluto", INDIRECT("tb_rec_uni[empresa]"),$B20) -> 0 | J20: =SUMIFS(tb_rec_uni[2025-07-01], INDIRECT("tb_rec_uni[natureza]"),"pro.soluto", INDIRECT("tb_rec_uni[empresa]"),$B20) -> 0 | K20: =SUMIFS(tb_rec_uni[2025-08-01], INDIRECT("tb_rec_uni[natureza]"),"pro.soluto", INDIRECT("tb_rec_uni[empresa]"),$B20) -> 0 | L20: =SUMIFS(tb_rec_uni[2025-09-01], INDIRECT("tb_rec_uni[natureza]"),"pro.soluto", INDIRECT("tb_rec_uni[empresa]"),$B20) -> 0 | M20: =SUMIFS(tb_rec_uni[2025-10-01], INDIRECT("tb_rec_uni[natureza]"),"pro.soluto", INDIRECT("tb_rec_uni[empresa]"),$B20) -> 0 | N20: =SUMIFS(tb_rec_uni[2025-11-01], INDIRECT("tb_rec_uni[natureza]"),"pro.soluto", INDIRECT("tb_rec_uni[empresa]"),$B20) -> 0 | O20: =SUMIFS(tb_rec_uni[2025-12-01], INDIRECT("tb_rec_uni[natureza]"),"pro.soluto", INDIRECT("tb_rec_uni[empresa]"),$B20) -> 0 | P20: =SUMIFS(tb_rec_uni[2026-01-01], INDIRECT("tb_rec_uni[natureza]"),"pro.soluto", INDIRECT("tb_rec_uni[empresa]"),$B20) -> 0 | Q20: =SUMIFS(tb_rec_uni[2026-02-01], INDIRECT("tb_rec_uni[natureza]"),"pro.soluto", INDIRECT("tb_rec_uni[empresa]"),$B20) -> 0 | R20: =SUMIFS(tb_rec_uni[2026-03-01], INDIRECT("tb_rec_uni[natureza]"),"pro.soluto", INDIRECT("tb_rec_uni[empresa]"),$B20) -> 0 | S20: =SUMIFS(tb_rec_uni[2026-04-01], INDIRECT("tb_rec_uni[natureza]"),"pro.soluto", INDIRECT("tb_rec_uni[empresa]"),$B20) -> 0 | T20: =SUMIFS(tb_rec_uni[2026-05-01], INDIRECT("tb_rec_uni[natureza]"),"pro.soluto", INDIRECT("tb_rec_uni[empresa]"),$B20) -> 0 | U20: =SUMIFS(tb_rec_uni[2026-06-01], INDIRECT("tb_rec_uni[natureza]"),"pro.soluto", INDIRECT("tb_rec_uni[empresa]"),$B20) -> 0 | V20: =SUMIFS(tb_rec_uni[2026-07-01], INDIRECT("tb_rec_uni[natureza]"),"pro.soluto", INDIRECT("tb_rec_uni[empresa]"),$B20) -> 0 | W20: =SUMIFS(tb_rec_uni[2026-08-01], INDIRECT("tb_rec_uni[natureza]"),"pro.soluto", INDIRECT("tb_rec_uni[empresa]"),$B20) -> 0 | X20: =SUMIFS(tb_rec_uni[2026-09-01], INDIRECT("tb_rec_uni[natureza]"),"pro.soluto", INDIRECT("tb_rec_uni[empresa]"),$B20) -> 0 | Y20: =SUMIFS(tb_rec_uni[2026-10-01], INDIRECT("tb_rec_uni[natureza]"),"pro.soluto", INDIRECT("tb_rec_uni[empresa]"),$B20) -> 0 | Z20: =SUMIFS(tb_rec_uni[2026-11-01], INDIRECT("tb_rec_uni[natureza]"),"pro.soluto", INDIRECT("tb_rec_uni[empresa]"),$B20) -> 0 | AA20: =SUMIFS(tb_rec_uni[2026-12-01], INDIRECT("tb_rec_uni[natureza]"),"pro.soluto", INDIRECT("tb_rec_uni[empresa]"),$B20) -> 0 | AC20: =SUM($D20:INDEX($D20:$AA20,1,MATCH(DATE(YEAR(inputs!$A$1),MONTH(inputs!$A$1),1),$D$1:$AA$1,0))) -> 0 | AE20: =SUM(D20:AA20) -> 0
A21: 1.1.2.AVR. | B21: AVR | C21: IK | D21: =SUMIFS(tb_rec_uni[2025-01-01], INDIRECT("tb_rec_uni[natureza]"),"pro.soluto", INDIRECT("tb_rec_uni[empresa]"),$B21) -> 0 | E21: =SUMIFS(tb_rec_uni[2025-02-01], INDIRECT("tb_rec_uni[natureza]"),"pro.soluto", INDIRECT("tb_rec_uni[empresa]"),$B21) -> 0 | F21: =SUMIFS(tb_rec_uni[2025-03-01], INDIRECT("tb_rec_uni[natureza]"),"pro.soluto", INDIRECT("tb_rec_uni[empresa]"),$B21) -> 0 | G21: =SUMIFS(tb_rec_uni[2025-04-01], INDIRECT("tb_rec_uni[natureza]"),"pro.soluto", INDIRECT("tb_rec_uni[empresa]"),$B21) -> 0 | H21: =SUMIFS(tb_rec_uni[2025-05-01], INDIRECT("tb_rec_uni[natureza]"),"pro.soluto", INDIRECT("tb_rec_uni[empresa]"),$B21) -> 0 | I21: =SUMIFS(tb_rec_uni[2025-06-01], INDIRECT("tb_rec_uni[natureza]"),"pro.soluto", INDIRECT("tb_rec_uni[empresa]"),$B21) -> 0 | J21: =SUMIFS(tb_rec_uni[2025-07-01], INDIRECT("tb_rec_uni[natureza]"),"pro.soluto", INDIRECT("tb_rec_uni[empresa]"),$B21) -> 0 | K21: =SUMIFS(tb_rec_uni[2025-08-01], INDIRECT("tb_rec_uni[natureza]"),"pro.soluto", INDIRECT("tb_rec_uni[empresa]"),$B21) -> 0 | L21: =SUMIFS(tb_rec_uni[2025-09-01], INDIRECT("tb_rec_uni[natureza]"),"pro.soluto", INDIRECT("tb_rec_uni[empresa]"),$B21) -> 0 | M21: =SUMIFS(tb_rec_uni[2025-10-01], INDIRECT("tb_rec_uni[natureza]"),"pro.soluto", INDIRECT("tb_rec_uni[empresa]"),$B21) -> 0 | N21: =SUMIFS(tb_rec_uni[2025-11-01], INDIRECT("tb_rec_uni[natureza]"),"pro.soluto", INDIRECT("tb_rec_uni[empresa]"),$B21) -> 0 | O21: =SUMIFS(tb_rec_uni[2025-12-01], INDIRECT("tb_rec_uni[natureza]"),"pro.soluto", INDIRECT("tb_rec_uni[empresa]"),$B21) -> 0 | P21: =SUMIFS(tb_rec_uni[2026-01-01], INDIRECT("tb_rec_uni[natureza]"),"pro.soluto", INDIRECT("tb_rec_uni[empresa]"),$B21) -> 0 | Q21: =SUMIFS(tb_rec_uni[2026-02-01], INDIRECT("tb_rec_uni[natureza]"),"pro.soluto", INDIRECT("tb_rec_uni[empresa]"),$B21) -> 0 | R21: =SUMIFS(tb_rec_uni[2026-03-01], INDIRECT("tb_rec_uni[natureza]"),"pro.soluto", INDIRECT("tb_rec_uni[empresa]"),$B21) -> 0 | S21: =SUMIFS(tb_rec_uni[2026-04-01], INDIRECT("tb_rec_uni[natureza]"),"pro.soluto", INDIRECT("tb_rec_uni[empresa]"),$B21) -> 0 | T21: =SUMIFS(tb_rec_uni[2026-05-01], INDIRECT("tb_rec_uni[natureza]"),"pro.soluto", INDIRECT("tb_rec_uni[empresa]"),$B21) -> 0 | U21: =SUMIFS(tb_rec_uni[2026-06-01], INDIRECT("tb_rec_uni[natureza]"),"pro.soluto", INDIRECT("tb_rec_uni[empresa]"),$B21) -> 0 | V21: =SUMIFS(tb_rec_uni[2026-07-01], INDIRECT("tb_rec_uni[natureza]"),"pro.soluto", INDIRECT("tb_rec_uni[empresa]"),$B21) -> 0 | W21: =SUMIFS(tb_rec_uni[2026-08-01], INDIRECT("tb_rec_uni[natureza]"),"pro.soluto", INDIRECT("tb_rec_uni[empresa]"),$B21) -> 0 | X21: =SUMIFS(tb_rec_uni[2026-09-01], INDIRECT("tb_rec_uni[natureza]"),"pro.soluto", INDIRECT("tb_rec_uni[empresa]"),$B21) -> 0 | Y21: =SUMIFS(tb_rec_uni[2026-10-01], INDIRECT("tb_rec_uni[natureza]"),"pro.soluto", INDIRECT("tb_rec_uni[empresa]"),$B21) -> 0 | Z21: =SUMIFS(tb_rec_uni[2026-11-01], INDIRECT("tb_rec_uni[natureza]"),"pro.soluto", INDIRECT("tb_rec_uni[empresa]"),$B21) -> 0 | AA21: =SUMIFS(tb_rec_uni[2026-12-01], INDIRECT("tb_rec_uni[natureza]"),"pro.soluto", INDIRECT("tb_rec_uni[empresa]"),$B21) -> 0 | AC21: =SUM($D21:INDEX($D21:$AA21,1,MATCH(DATE(YEAR(inputs!$A$1),MONTH(inputs!$A$1),1),$D$1:$AA$1,0))) -> 0 | AE21: =SUM(D21:AA21) -> 0
A22: 1.1.2.BUT. | B22: BUT | C22: IK | D22: =SUMIFS(tb_rec_uni[2025-01-01], INDIRECT("tb_rec_uni[natureza]"),"pro.soluto", INDIRECT("tb_rec_uni[empresa]"),$B22) -> 0 | E22: =SUMIFS(tb_rec_uni[2025-02-01], INDIRECT("tb_rec_uni[natureza]"),"pro.soluto", INDIRECT("tb_rec_uni[empresa]"),$B22) -> 0 | F22: =SUMIFS(tb_rec_uni[2025-03-01], INDIRECT("tb_rec_uni[natureza]"),"pro.soluto", INDIRECT("tb_rec_uni[empresa]"),$B22) -> 0 | G22: =SUMIFS(tb_rec_uni[2025-04-01], INDIRECT("tb_rec_uni[natureza]"),"pro.soluto", INDIRECT("tb_rec_uni[empresa]"),$B22) -> 0 | H22: =SUMIFS(tb_rec_uni[2025-05-01], INDIRECT("tb_rec_uni[natureza]"),"pro.soluto", INDIRECT("tb_rec_uni[empresa]"),$B22) -> 0 | I22: =SUMIFS(tb_rec_uni[2025-06-01], INDIRECT("tb_rec_uni[natureza]"),"pro.soluto", INDIRECT("tb_rec_uni[empresa]"),$B22) -> 0 | J22: =SUMIFS(tb_rec_uni[2025-07-01], INDIRECT("tb_rec_uni[natureza]"),"pro.soluto", INDIRECT("tb_rec_uni[empresa]"),$B22) -> 0 | K22: =SUMIFS(tb_rec_uni[2025-08-01], INDIRECT("tb_rec_uni[natureza]"),"pro.soluto", INDIRECT("tb_rec_uni[empresa]"),$B22) -> 0 | L22: =SUMIFS(tb_rec_uni[2025-09-01], INDIRECT("tb_rec_uni[natureza]"),"pro.soluto", INDIRECT("tb_rec_uni[empresa]"),$B22) -> 0 | M22: =SUMIFS(tb_rec_uni[2025-10-01], INDIRECT("tb_rec_uni[natureza]"),"pro.soluto", INDIRECT("tb_rec_uni[empresa]"),$B22) -> 0 | N22: =SUMIFS(tb_rec_uni[2025-11-01], INDIRECT("tb_rec_uni[natureza]"),"pro.soluto", INDIRECT("tb_rec_uni[empresa]"),$B22) -> 0 | O22: =SUMIFS(tb_rec_uni[2025-12-01], INDIRECT("tb_rec_uni[natureza]"),"pro.soluto", INDIRECT("tb_rec_uni[empresa]"),$B22) -> 0 | P22: =SUMIFS(tb_rec_uni[2026-01-01], INDIRECT("tb_rec_uni[natureza]"),"pro.soluto", INDIRECT("tb_rec_uni[empresa]"),$B22) -> 0 | Q22: =SUMIFS(tb_rec_uni[2026-02-01], INDIRECT("tb_rec_uni[natureza]"),"pro.soluto", INDIRECT("tb_rec_uni[empresa]"),$B22) -> 0 | R22: =SUMIFS(tb_rec_uni[2026-03-01], INDIRECT("tb_rec_uni[natureza]"),"pro.soluto", INDIRECT("tb_rec_uni[empresa]"),$B22) -> 0 | S22: =SUMIFS(tb_rec_uni[2026-04-01], INDIRECT("tb_rec_uni[natureza]"),"pro.soluto", INDIRECT("tb_rec_uni[empresa]"),$B22) -> 0 | T22: =SUMIFS(tb_rec_uni[2026-05-01], INDIRECT("tb_rec_uni[natureza]"),"pro.soluto", INDIRECT("tb_rec_uni[empresa]"),$B22) -> 0 | U22: =SUMIFS(tb_rec_uni[2026-06-01], INDIRECT("tb_rec_uni[natureza]"),"pro.soluto", INDIRECT("tb_rec_uni[empresa]"),$B22) -> 0 | V22: =SUMIFS(tb_rec_uni[2026-07-01], INDIRECT("tb_rec_uni[natureza]"),"pro.soluto", INDIRECT("tb_rec_uni[empresa]"),$B22) -> 0 | W22: =SUMIFS(tb_rec_uni[2026-08-01], INDIRECT("tb_rec_uni[natureza]"),"pro.soluto", INDIRECT("tb_rec_uni[empresa]"),$B22) -> 0 | X22: =SUMIFS(tb_rec_uni[2026-09-01], INDIRECT("tb_rec_uni[natureza]"),"pro.soluto", INDIRECT("tb_rec_uni[empresa]"),$B22) -> 0 | Y22: =SUMIFS(tb_rec_uni[2026-10-01], INDIRECT("tb_rec_uni[natureza]"),"pro.soluto", INDIRECT("tb_rec_uni[empresa]"),$B22) -> 0 | Z22: =SUMIFS(tb_rec_uni[2026-11-01], INDIRECT("tb_rec_uni[natureza]"),"pro.soluto", INDIRECT("tb_rec_uni[empresa]"),$B22) -> 0 | AA22: =SUMIFS(tb_rec_uni[2026-12-01], INDIRECT("tb_rec_uni[natureza]"),"pro.soluto", INDIRECT("tb_rec_uni[empresa]"),$B22) -> 0 | AC22: =SUM($D22:INDEX($D22:$AA22,1,MATCH(DATE(YEAR(inputs!$A$1),MONTH(inputs!$A$1),1),$D$1:$AA$1,0))) -> 0 | AE22: =SUM(D22:AA22) -> 0
A23: 1.1.3. | B23: Repasse ABC | C23: ABC | D23: =SUM(D$24) -> 66315.2 | E23: =SUM(E$24) -> 102314.88 | F23: =SUM(F$24) -> 247260.96 | G23: =SUM(G$24) -> 361891.52 | H23: =SUM(H$24) -> 806203.36 | I23: =SUM(I$24) -> 770203.68 | J23: =SUM(J$24) -> 1031675 | K23: =SUM(K$24) -> 400733.28 | ... AA23: =SUM(AA$24) -> 0 | AC23: =SUM($D23:INDEX($D23:$AA23,1,MATCH(DATE(YEAR(inputs!$A$1),MONTH(inputs!$A$1),1),$D$1:$AA$1,0))) -> 8746974.9 | AE23: =SUM(D23:AA23) -> 8746974.9
A24: 1.1.3.POM. | B24: POM | C24: ABC | D24: {=TRANSPOSE(_xlfn._xlws.FILTER(inputs!$BJ$51:$BJ$74,inputs!$BJ$51:$BJ$74<>""))} -> 66315.2 | E24: 102314.88 | F24: 247260.96 | G24: 361891.52 | H24: 806203.36 | I24: 770203.68 | J24: 1031675 | K24: 400733.28 | L24: 345786.4 | M24: 622415.52 | N24: 378944 | O24: 324944.48 | P24: 179998.4 | Q24: 272839.68 | R24: 640415.36 | S24: 389364.96 | T24: 566521.28 | U24: 390312.32 | V24: 610099.84 | W24: 238734.72 | AC24: =SUM($D24:INDEX($D24:$AA24,1,MATCH(DATE(YEAR(inputs!$A$1),MONTH(inputs!$A$1),1),$D$1:$AA$1,0))) -> 8746974.9 | AE24: =SUM(D24:AA24) -> 8746974.9
A25: 1.1.4. | B25: Taxas extras | C25: IK | D25: =SUM(D$26:D$32) -> 0 | E25: =SUM(E$26:E$32) -> 0 | F25: =SUM(F$26:F$32) -> 0 | G25: =SUM(G$26:G$32) -> 0 | H25: =SUM(H$26:H$32) -> 0 | I25: =SUM(I$26:I$32) -> 0 | J25: =SUM(J$26:J$32) -> 0 | K25: =SUM(K$26:K$32) -> 0 | ... AA25: =SUM(AA$26:AA$32) -> 0 | AC25: =SUM($D25:INDEX($D25:$AA25,1,MATCH(DATE(YEAR(inputs!$A$1),MONTH(inputs!$A$1),1),$D$1:$AA$1,0))) -> 0 | AE25: =SUM(D25:AA25) -> 0
A26: 1.1.4.SN2. | B26: SN2 | C26: Ik | D26: =SUMIFS(tb_rec_uni[2025-01-01], INDIRECT("tb_rec_uni[natureza]"),"taxa.extra", INDIRECT("tb_rec_uni[empresa]"),$B26) -> 0 | E26: =SUMIFS(tb_rec_uni[2025-02-01], INDIRECT("tb_rec_uni[natureza]"),"taxa.extra", INDIRECT("tb_rec_uni[empresa]"),$B26) -> 0 | F26: =SUMIFS(tb_rec_uni[2025-03-01], INDIRECT("tb_rec_uni[natureza]"),"taxa.extra", INDIRECT("tb_rec_uni[empresa]"),$B26) -> 0 | G26: =SUMIFS(tb_rec_uni[2025-04-01], INDIRECT("tb_rec_uni[natureza]"),"taxa.extra", INDIRECT("tb_rec_uni[empresa]"),$B26) -> 0 | H26: =SUMIFS(tb_rec_uni[2025-05-01], INDIRECT("tb_rec_uni[natureza]"),"taxa.extra", INDIRECT("tb_rec_uni[empresa]"),$B26) -> 0 | I26: =SUMIFS(tb_rec_uni[2025-06-01], INDIRECT("tb_rec_uni[natureza]"),"taxa.extra", INDIRECT("tb_rec_uni[empresa]"),$B26) -> 0 | J26: =SUMIFS(tb_rec_uni[2025-07-01], INDIRECT("tb_rec_uni[natureza]"),"taxa.extra", INDIRECT("tb_rec_uni[empresa]"),$B26) -> 0 | K26: =SUMIFS(tb_rec_uni[2025-08-01], INDIRECT("tb_rec_uni[natureza]"),"taxa.extra", INDIRECT("tb_rec_uni[empresa]"),$B26) -> 0 | L26: =SUMIFS(tb_rec_uni[2025-09-01], INDIRECT("tb_rec_uni[natureza]"),"taxa.extra", INDIRECT("tb_rec_uni[empresa]"),$B26) -> 0 | M26: =SUMIFS(tb_rec_uni[2025-10-01], INDIRECT("tb_rec_uni[natureza]"),"taxa.extra", INDIRECT("tb_rec_uni[empresa]"),$B26) -> 0 | N26: =SUMIFS(tb_rec_uni[2025-11-01], INDIRECT("tb_rec_uni[natureza]"),"taxa.extra", INDIRECT("tb_rec_uni[empresa]"),$B26) -> 0 | O26: =SUMIFS(tb_rec_uni[2025-12-01], INDIRECT("tb_rec_uni[natureza]"),"taxa.extra", INDIRECT("tb_rec_uni[empresa]"),$B26) -> 0 | P26: =SUMIFS(tb_rec_uni[2026-01-01], INDIRECT("tb_rec_uni[natureza]"),"taxa.extra", INDIRECT("tb_rec_uni[empresa]"),$B26) -> 0 | Q26: =SUMIFS(tb_rec_uni[2026-02-01], INDIRECT("tb_rec_uni[natureza]"),"taxa.extra", INDIRECT("tb_rec_uni[empresa]"),$B26) -> 0 | R26: =SUMIFS(tb_rec_uni[2026-03-01], INDIRECT("tb_rec_uni[natureza]"),"taxa.extra", INDIRECT("tb_rec_uni[empresa]"),$B26) -> 0 | S26: =SUMIFS(tb_rec_uni[2026-04-01], INDIRECT("tb_rec_uni[natureza]"),"taxa.extra", INDIRECT("tb_rec_uni[empresa]"),$B26) -> 0 | T26: =SUMIFS(tb_rec_uni[2026-05-01], INDIRECT("tb_rec_uni[natureza]"),"taxa.extra", INDIRECT("tb_rec_uni[empresa]"),$B26) -> 0 | U26: =SUMIFS(tb_rec_uni[2026-06-01], INDIRECT("tb_rec_uni[natureza]"),"taxa.extra", INDIRECT("tb_rec_uni[empresa]"),$B26) -> 0 | V26: =SUMIFS(tb_rec_uni[2026-07-01], INDIRECT("tb_rec_uni[natureza]"),"taxa.extra", INDIRECT("tb_rec_uni[empresa]"),$B26) -> 0 | W26: =SUMIFS(tb_rec_uni[2026-08-01], INDIRECT("tb_rec_uni[natureza]"),"taxa.extra", INDIRECT("tb_rec_uni[empresa]"),$B26) -> 0 | X26: =SUMIFS(tb_rec_uni[2026-09-01], INDIRECT("tb_rec_uni[natureza]"),"taxa.extra", INDIRECT("tb_rec_uni[empresa]"),$B26) -> 0 | Y26: =SUMIFS(tb_rec_uni[2026-10-01], INDIRECT("tb_rec_uni[natureza]"),"taxa.extra", INDIRECT("tb_rec_uni[empresa]"),$B26) -> 0 | Z26: =SUMIFS(tb_rec_uni[2026-11-01], INDIRECT("tb_rec_uni[natureza]"),"taxa.extra", INDIRECT("tb_rec_uni[empresa]"),$B26) -> 0 | AA26: =SUMIFS(tb_rec_uni[2026-12-01], INDIRECT("tb_rec_uni[natureza]"),"taxa.extra", INDIRECT("tb_rec_uni[empresa]"),$B26) -> 0 | AC26: =SUM($D26:INDEX($D26:$AA26,1,MATCH(DATE(YEAR(inputs!$A$1),MONTH(inputs!$A$1),1),$D$1:$AA$1,0))) -> 0 | AE26: =SUM(D26:AA26) -> 0
A27: 1.1.4.GRA. | B27: GRA | C27: Ik | D27: =SUMIFS(tb_rec_uni[2025-01-01], INDIRECT("tb_rec_uni[natureza]"),"taxa.extra", INDIRECT("tb_rec_uni[empresa]"),$B27) -> 0 | E27: =SUMIFS(tb_rec_uni[2025-02-01], INDIRECT("tb_rec_uni[natureza]"),"taxa.extra", INDIRECT("tb_rec_uni[empresa]"),$B27) -> 0 | F27: =SUMIFS(tb_rec_uni[2025-03-01], INDIRECT("tb_rec_uni[natureza]"),"taxa.extra", INDIRECT("tb_rec_uni[empresa]"),$B27) -> 0 | G27: =SUMIFS(tb_rec_uni[2025-04-01], INDIRECT("tb_rec_uni[natureza]"),"taxa.extra", INDIRECT("tb_rec_uni[empresa]"),$B27) -> 0 | H27: =SUMIFS(tb_rec_uni[2025-05-01], INDIRECT("tb_rec_uni[natureza]"),"taxa.extra", INDIRECT("tb_rec_uni[empresa]"),$B27) -> 0 | I27: =SUMIFS(tb_rec_uni[2025-06-01], INDIRECT("tb_rec_uni[natureza]"),"taxa.extra", INDIRECT("tb_rec_uni[empresa]"),$B27) -> 0 | J27: =SUMIFS(tb_rec_uni[2025-07-01], INDIRECT("tb_rec_uni[natureza]"),"taxa.extra", INDIRECT("tb_rec_uni[empresa]"),$B27) -> 0 | K27: =SUMIFS(tb_rec_uni[2025-08-01], INDIRECT("tb_rec_uni[natureza]"),"taxa.extra", INDIRECT("tb_rec_uni[empresa]"),$B27) -> 0 | L27: =SUMIFS(tb_rec_uni[2025-09-01], INDIRECT("tb_rec_uni[natureza]"),"taxa.extra", INDIRECT("tb_rec_uni[empresa]"),$B27) -> 0 | M27: =SUMIFS(tb_rec_uni[2025-10-01], INDIRECT("tb_rec_uni[natureza]"),"taxa.extra", INDIRECT("tb_rec_uni[empresa]"),$B27) -> 0 | N27: =SUMIFS(tb_rec_uni[2025-11-01], INDIRECT("tb_rec_uni[natureza]"),"taxa.extra", INDIRECT("tb_rec_uni[empresa]"),$B27) -> 0 | O27: =SUMIFS(tb_rec_uni[2025-12-01], INDIRECT("tb_rec_uni[natureza]"),"taxa.extra", INDIRECT("tb_rec_uni[empresa]"),$B27) -> 0 | P27: =SUMIFS(tb_rec_uni[2026-01-01], INDIRECT("tb_rec_uni[natureza]"),"taxa.extra", INDIRECT("tb_rec_uni[empresa]"),$B27) -> 0 | Q27: =SUMIFS(tb_rec_uni[2026-02-01], INDIRECT("tb_rec_uni[natureza]"),"taxa.extra", INDIRECT("tb_rec_uni[empresa]"),$B27) -> 0 | R27: =SUMIFS(tb_rec_uni[2026-03-01], INDIRECT("tb_rec_uni[natureza]"),"taxa.extra", INDIRECT("tb_rec_uni[empresa]"),$B27) -> 0 | S27: =SUMIFS(tb_rec_uni[2026-04-01], INDIRECT("tb_rec_uni[natureza]"),"taxa.extra", INDIRECT("tb_rec_uni[empresa]"),$B27) -> 0 | T27: =SUMIFS(tb_rec_uni[2026-05-01], INDIRECT("tb_rec_uni[natureza]"),"taxa.extra", INDIRECT("tb_rec_uni[empresa]"),$B27) -> 0 | U27: =SUMIFS(tb_rec_uni[2026-06-01], INDIRECT("tb_rec_uni[natureza]"),"taxa.extra", INDIRECT("tb_rec_uni[empresa]"),$B27) -> 0 | V27: =SUMIFS(tb_rec_uni[2026-07-01], INDIRECT("tb_rec_uni[natureza]"),"taxa.extra", INDIRECT("tb_rec_uni[empresa]"),$B27) -> 0 | W27: =SUMIFS(tb_rec_uni[2026-08-01], INDIRECT("tb_rec_uni[natureza]"),"taxa.extra", INDIRECT("tb_rec_uni[empresa]"),$B27) -> 0 | X27: =SUMIFS(tb_rec_uni[2026-09-01], INDIRECT("tb_rec_uni[natureza]"),"taxa.extra", INDIRECT("tb_rec_uni[empresa]"),$B27) -> 0 | Y27: =SUMIFS(tb_rec_uni[2026-10-01], INDIRECT("tb_rec_uni[natureza]"),"taxa.extra", INDIRECT("tb_rec_uni[empresa]"),$B27) -> 0 | Z27: =SUMIFS(tb_rec_uni[2026-11-01], INDIRECT("tb_rec_uni[natureza]"),"taxa.extra", INDIRECT("tb_rec_uni[empresa]"),$B27) -> 0 | AA27: =SUMIFS(tb_rec_uni[2026-12-01], INDIRECT("tb_rec_uni[natureza]"),"taxa.extra", INDIRECT("tb_rec_uni[empresa]"),$B27) -> 0 | AC27: =SUM($D27:INDEX($D27:$AA27,1,MATCH(DATE(YEAR(inputs!$A$1),MONTH(inputs!$A$1),1),$D$1:$AA$1,0))) -> 0 | AE27: =SUM(D27:AA27) -> 0
A28: 1.1.4.AVS. | B28: AVS | C28: Ik | D28: =SUMIFS(tb_rec_uni[2025-01-01], INDIRECT("tb_rec_uni[natureza]"),"taxa.extra", INDIRECT("tb_rec_uni[empresa]"),$B28) -> 0 | E28: =SUMIFS(tb_rec_uni[2025-02-01], INDIRECT("tb_rec_uni[natureza]"),"taxa.extra", INDIRECT("tb_rec_uni[empresa]"),$B28) -> 0 | F28: =SUMIFS(tb_rec_uni[2025-03-01], INDIRECT("tb_rec_uni[natureza]"),"taxa.extra", INDIRECT("tb_rec_uni[empresa]"),$B28) -> 0 | G28: =SUMIFS(tb_rec_uni[2025-04-01], INDIRECT("tb_rec_uni[natureza]"),"taxa.extra", INDIRECT("tb_rec_uni[empresa]"),$B28) -> 0 | H28: =SUMIFS(tb_rec_uni[2025-05-01], INDIRECT("tb_rec_uni[natureza]"),"taxa.extra", INDIRECT("tb_rec_uni[empresa]"),$B28) -> 0 | I28: =SUMIFS(tb_rec_uni[2025-06-01], INDIRECT("tb_rec_uni[natureza]"),"taxa.extra", INDIRECT("tb_rec_uni[empresa]"),$B28) -> 0 | J28: =SUMIFS(tb_rec_uni[2025-07-01], INDIRECT("tb_rec_uni[natureza]"),"taxa.extra", INDIRECT("tb_rec_uni[empresa]"),$B28) -> 0 | K28: =SUMIFS(tb_rec_uni[2025-08-01], INDIRECT("tb_rec_uni[natureza]"),"taxa.extra", INDIRECT("tb_rec_uni[empresa]"),$B28) -> 0 | L28: =SUMIFS(tb_rec_uni[2025-09-01], INDIRECT("tb_rec_uni[natureza]"),"taxa.extra", INDIRECT("tb_rec_uni[empresa]"),$B28) -> 0 | M28: =SUMIFS(tb_rec_uni[2025-10-01], INDIRECT("tb_rec_uni[natureza]"),"taxa.extra", INDIRECT("tb_rec_uni[empresa]"),$B28) -> 0 | N28: =SUMIFS(tb_rec_uni[2025-11-01], INDIRECT("tb_rec_uni[natureza]"),"taxa.extra", INDIRECT("tb_rec_uni[empresa]"),$B28) -> 0 | O28: =SUMIFS(tb_rec_uni[2025-12-01], INDIRECT("tb_rec_uni[natureza]"),"taxa.extra", INDIRECT("tb_rec_uni[empresa]"),$B28) -> 0 | P28: =SUMIFS(tb_rec_uni[2026-01-01], INDIRECT("tb_rec_uni[natureza]"),"taxa.extra", INDIRECT("tb_rec_uni[empresa]"),$B28) -> 0 | Q28: =SUMIFS(tb_rec_uni[2026-02-01], INDIRECT("tb_rec_uni[natureza]"),"taxa.extra", INDIRECT("tb_rec_uni[empresa]"),$B28) -> 0 | R28: =SUMIFS(tb_rec_uni[2026-03-01], INDIRECT("tb_rec_uni[natureza]"),"taxa.extra", INDIRECT("tb_rec_uni[empresa]"),$B28) -> 0 | S28: =SUMIFS(tb_rec_uni[2026-04-01], INDIRECT("tb_rec_uni[natureza]"),"taxa.extra", INDIRECT("tb_rec_uni[empresa]"),$B28) -> 0 | T28: =SUMIFS(tb_rec_uni[2026-05-01], INDIRECT("tb_rec_uni[natureza]"),"taxa.extra", INDIRECT("tb_rec_uni[empresa]"),$B28) -> 0 | U28: =SUMIFS(tb_rec_uni[2026-06-01], INDIRECT("tb_rec_uni[natureza]"),"taxa.extra", INDIRECT("tb_rec_uni[empresa]"),$B28) -> 0 | V28: =SUMIFS(tb_rec_uni[2026-07-01], INDIRECT("tb_rec_uni[natureza]"),"taxa.extra", INDIRECT("tb_rec_uni[empresa]"),$B28) -> 0 | W28: =SUMIFS(tb_rec_uni[2026-08-01], INDIRECT("tb_rec_uni[natureza]"),"taxa.extra", INDIRECT("tb_rec_uni[empresa]"),$B28) -> 0 | X28: =SUMIFS(tb_rec_uni[2026-09-01], INDIRECT("tb_rec_uni[natureza]"),"taxa.extra", INDIRECT("tb_rec_uni[empresa]"),$B28) -> 0 | Y28: =SUMIFS(tb_rec_uni[2026-10-01], INDIRECT("tb_rec_uni[natureza]"),"taxa.extra", INDIRECT("tb_rec_uni[empresa]"),$B28) -> 0 | Z28: =SUMIFS(tb_rec_uni[2026-11-01], INDIRECT("tb_rec_uni[natureza]"),"taxa.extra", INDIRECT("tb_rec_uni[empresa]"),$B28) -> 0 | AA28: =SUMIFS(tb_rec_uni[2026-12-01], INDIRECT("tb_rec_uni[natureza]"),"taxa.extra", INDIRECT("tb_rec_uni[empresa]"),$B28) -> 0 | AC28: =SUM($D28:INDEX($D28:$AA28,1,MATCH(DATE(YEAR(inputs!$A$1),MONTH(inputs!$A$1),1),$D$1:$AA$1,0))) -> 0 | AE28: =SUM(D28:AA28) -> 0
A29: 1.1.4.AMP. | B29: AMP | C29: Ik | D29: =SUMIFS(tb_rec_uni[2025-01-01], INDIRECT("tb_rec_uni[natureza]"),"taxa.extra", INDIRECT("tb_rec_uni[empresa]"),$B29) -> 0 | E29: =SUMIFS(tb_rec_uni[2025-02-01], INDIRECT("tb_rec_uni[natureza]"),"taxa.extra", INDIRECT("tb_rec_uni[empresa]"),$B29) -> 0 | F29: =SUMIFS(tb_rec_uni[2025-03-01], INDIRECT("tb_rec_uni[natureza]"),"taxa.extra", INDIRECT("tb_rec_uni[empresa]"),$B29) -> 0 | G29: =SUMIFS(tb_rec_uni[2025-04-01], INDIRECT("tb_rec_uni[natureza]"),"taxa.extra", INDIRECT("tb_rec_uni[empresa]"),$B29) -> 0 | H29: =SUMIFS(tb_rec_uni[2025-05-01], INDIRECT("tb_rec_uni[natureza]"),"taxa.extra", INDIRECT("tb_rec_uni[empresa]"),$B29) -> 0 | I29: =SUMIFS(tb_rec_uni[2025-06-01], INDIRECT("tb_rec_uni[natureza]"),"taxa.extra", INDIRECT("tb_rec_uni[empresa]"),$B29) -> 0 | J29: =SUMIFS(tb_rec_uni[2025-07-01], INDIRECT("tb_rec_uni[natureza]"),"taxa.extra", INDIRECT("tb_rec_uni[empresa]"),$B29) -> 0 | K29: =SUMIFS(tb_rec_uni[2025-08-01], INDIRECT("tb_rec_uni[natureza]"),"taxa.extra", INDIRECT("tb_rec_uni[empresa]"),$B29) -> 0 | L29: =SUMIFS(tb_rec_uni[2025-09-01], INDIRECT("tb_rec_uni[natureza]"),"taxa.extra", INDIRECT("tb_rec_uni[empresa]"),$B29) -> 0 | M29: =SUMIFS(tb_rec_uni[2025-10-01], INDIRECT("tb_rec_uni[natureza]"),"taxa.extra", INDIRECT("tb_rec_uni[empresa]"),$B29) -> 0 | N29: =SUMIFS(tb_rec_uni[2025-11-01], INDIRECT("tb_rec_uni[natureza]"),"taxa.extra", INDIRECT("tb_rec_uni[empresa]"),$B29) -> 0 | O29: =SUMIFS(tb_rec_uni[2025-12-01], INDIRECT("tb_rec_uni[natureza]"),"taxa.extra", INDIRECT("tb_rec_uni[empresa]"),$B29) -> 0 | P29: =SUMIFS(tb_rec_uni[2026-01-01], INDIRECT("tb_rec_uni[natureza]"),"taxa.extra", INDIRECT("tb_rec_uni[empresa]"),$B29) -> 0 | Q29: =SUMIFS(tb_rec_uni[2026-02-01], INDIRECT("tb_rec_uni[natureza]"),"taxa.extra", INDIRECT("tb_rec_uni[empresa]"),$B29) -> 0 | R29: =SUMIFS(tb_rec_uni[2026-03-01], INDIRECT("tb_rec_uni[natureza]"),"taxa.extra", INDIRECT("tb_rec_uni[empresa]"),$B29) -> 0 | S29: =SUMIFS(tb_rec_uni[2026-04-01], INDIRECT("tb_rec_uni[natureza]"),"taxa.extra", INDIRECT("tb_rec_uni[empresa]"),$B29) -> 0 | T29: =SUMIFS(tb_rec_uni[2026-05-01], INDIRECT("tb_rec_uni[natureza]"),"taxa.extra", INDIRECT("tb_rec_uni[empresa]"),$B29) -> 0 | U29: =SUMIFS(tb_rec_uni[2026-06-01], INDIRECT("tb_rec_uni[natureza]"),"taxa.extra", INDIRECT("tb_rec_uni[empresa]"),$B29) -> 0 | V29: =SUMIFS(tb_rec_uni[2026-07-01], INDIRECT("tb_rec_uni[natureza]"),"taxa.extra", INDIRECT("tb_rec_uni[empresa]"),$B29) -> 0 | W29: =SUMIFS(tb_rec_uni[2026-08-01], INDIRECT("tb_rec_uni[natureza]"),"taxa.extra", INDIRECT("tb_rec_uni[empresa]"),$B29) -> 0 | X29: =SUMIFS(tb_rec_uni[2026-09-01], INDIRECT("tb_rec_uni[natureza]"),"taxa.extra", INDIRECT("tb_rec_uni[empresa]"),$B29) -> 0 | Y29: =SUMIFS(tb_rec_uni[2026-10-01], INDIRECT("tb_rec_uni[natureza]"),"taxa.extra", INDIRECT("tb_rec_uni[empresa]"),$B29) -> 0 | Z29: =SUMIFS(tb_rec_uni[2026-11-01], INDIRECT("tb_rec_uni[natureza]"),"taxa.extra", INDIRECT("tb_rec_uni[empresa]"),$B29) -> 0 | AA29: =SUMIFS(tb_rec_uni[2026-12-01], INDIRECT("tb_rec_uni[natureza]"),"taxa.extra", INDIRECT("tb_rec_uni[empresa]"),$B29) -> 0 | AC29: =SUM($D29:INDEX($D29:$AA29,1,MATCH(DATE(YEAR(inputs!$A$1),MONTH(inputs!$A$1),1),$D$1:$AA$1,0))) -> 0 | AE29: =SUM(D29:AA29) -> 0
A30: 1.1.4.LUC. | B30: LUC | C30: Ik | D30: =SUMIFS(tb_rec_uni[2025-01-01], INDIRECT("tb_rec_uni[natureza]"),"taxa.extra", INDIRECT("tb_rec_uni[empresa]"),$B30) -> 0 | E30: =SUMIFS(tb_rec_uni[2025-02-01], INDIRECT("tb_rec_uni[natureza]"),"taxa.extra", INDIRECT("tb_rec_uni[empresa]"),$B30) -> 0 | F30: =SUMIFS(tb_rec_uni[2025-03-01], INDIRECT("tb_rec_uni[natureza]"),"taxa.extra", INDIRECT("tb_rec_uni[empresa]"),$B30) -> 0 | G30: =SUMIFS(tb_rec_uni[2025-04-01], INDIRECT("tb_rec_uni[natureza]"),"taxa.extra", INDIRECT("tb_rec_uni[empresa]"),$B30) -> 0 | H30: =SUMIFS(tb_rec_uni[2025-05-01], INDIRECT("tb_rec_uni[natureza]"),"taxa.extra", INDIRECT("tb_rec_uni[empresa]"),$B30) -> 0 | I30: =SUMIFS(tb_rec_uni[2025-06-01], INDIRECT("tb_rec_uni[natureza]"),"taxa.extra", INDIRECT("tb_rec_uni[empresa]"),$B30) -> 0 | J30: =SUMIFS(tb_rec_uni[2025-07-01], INDIRECT("tb_rec_uni[natureza]"),"taxa.extra", INDIRECT("tb_rec_uni[empresa]"),$B30) -> 0 | K30: =SUMIFS(tb_rec_uni[2025-08-01], INDIRECT("tb_rec_uni[natureza]"),"taxa.extra", INDIRECT("tb_rec_uni[empresa]"),$B30) -> 0 | L30: =SUMIFS(tb_rec_uni[2025-09-01], INDIRECT("tb_rec_uni[natureza]"),"taxa.extra", INDIRECT("tb_rec_uni[empresa]"),$B30) -> 0 | M30: =SUMIFS(tb_rec_uni[2025-10-01], INDIRECT("tb_rec_uni[natureza]"),"taxa.extra", INDIRECT("tb_rec_uni[empresa]"),$B30) -> 0 | N30: =SUMIFS(tb_rec_uni[2025-11-01], INDIRECT("tb_rec_uni[natureza]"),"taxa.extra", INDIRECT("tb_rec_uni[empresa]"),$B30) -> 0 | O30: =SUMIFS(tb_rec_uni[2025-12-01], INDIRECT("tb_rec_uni[natureza]"),"taxa.extra", INDIRECT("tb_rec_uni[empresa]"),$B30) -> 0 | P30: =SUMIFS(tb_rec_uni[2026-01-01], INDIRECT("tb_rec_uni[natureza]"),"taxa.extra", INDIRECT("tb_rec_uni[empresa]"),$B30) -> 0 | Q30: =SUMIFS(tb_rec_uni[2026-02-01], INDIRECT("tb_rec_uni[natureza]"),"taxa.extra", INDIRECT("tb_rec_uni[empresa]"),$B30) -> 0 | R30: =SUMIFS(tb_rec_uni[2026-03-01], INDIRECT("tb_rec_uni[natureza]"),"taxa.extra", INDIRECT("tb_rec_uni[empresa]"),$B30) -> 0 | S30: =SUMIFS(tb_rec_uni[2026-04-01], INDIRECT("tb_rec_uni[natureza]"),"taxa.extra", INDIRECT("tb_rec_uni[empresa]"),$B30) -> 0 | T30: =SUMIFS(tb_rec_uni[2026-05-01], INDIRECT("tb_rec_uni[natureza]"),"taxa.extra", INDIRECT("tb_rec_uni[empresa]"),$B30) -> 0 | U30: =SUMIFS(tb_rec_uni[2026-06-01], INDIRECT("tb_rec_uni[natureza]"),"taxa.extra", INDIRECT("tb_rec_uni[empresa]"),$B30) -> 0 | V30: =SUMIFS(tb_rec_uni[2026-07-01], INDIRECT("tb_rec_uni[natureza]"),"taxa.extra", INDIRECT("tb_rec_uni[empresa]"),$B30) -> 0 | W30: =SUMIFS(tb_rec_uni[2026-08-01], INDIRECT("tb_rec_uni[natureza]"),"taxa.extra", INDIRECT("tb_rec_uni[empresa]"),$B30) -> 0 | X30: =SUMIFS(tb_rec_uni[2026-09-01], INDIRECT("tb_rec_uni[natureza]"),"taxa.extra", INDIRECT("tb_rec_uni[empresa]"),$B30) -> 0 | Y30: =SUMIFS(tb_rec_uni[2026-10-01], INDIRECT("tb_rec_uni[natureza]"),"taxa.extra", INDIRECT("tb_rec_uni[empresa]"),$B30) -> 0 | Z30: =SUMIFS(tb_rec_uni[2026-11-01], INDIRECT("tb_rec_uni[natureza]"),"taxa.extra", INDIRECT("tb_rec_uni[empresa]"),$B30) -> 0 | AA30: =SUMIFS(tb_rec_uni[2026-12-01], INDIRECT("tb_rec_uni[natureza]"),"taxa.extra", INDIRECT("tb_rec_uni[empresa]"),$B30) -> 0 | AC30: =SUM($D30:INDEX($D30:$AA30,1,MATCH(DATE(YEAR(inputs!$A$1),MONTH(inputs!$A$1),1),$D$1:$AA$1,0))) -> 0 | AE30: =SUM(D30:AA30) -> 0
A31: 1.1.4.SN4. | B31: SN4 | C31: Ik | D31: =SUMIFS(tb_rec_uni[2025-01-01], INDIRECT("tb_rec_uni[natureza]"),"taxa.extra", INDIRECT("tb_rec_uni[empresa]"),$B31) -> 0 | E31: =SUMIFS(tb_rec_uni[2025-02-01], INDIRECT("tb_rec_uni[natureza]"),"taxa.extra", INDIRECT("tb_rec_uni[empresa]"),$B31) -> 0 | F31: =SUMIFS(tb_rec_uni[2025-03-01], INDIRECT("tb_rec_uni[natureza]"),"taxa.extra", INDIRECT("tb_rec_uni[empresa]"),$B31) -> 0 | G31: =SUMIFS(tb_rec_uni[2025-04-01], INDIRECT("tb_rec_uni[natureza]"),"taxa.extra", INDIRECT("tb_rec_uni[empresa]"),$B31) -> 0 | H31: =SUMIFS(tb_rec_uni[2025-05-01], INDIRECT("tb_rec_uni[natureza]"),"taxa.extra", INDIRECT("tb_rec_uni[empresa]"),$B31) -> 0 | I31: =SUMIFS(tb_rec_uni[2025-06-01], INDIRECT("tb_rec_uni[natureza]"),"taxa.extra", INDIRECT("tb_rec_uni[empresa]"),$B31) -> 0 | J31: =SUMIFS(tb_rec_uni[2025-07-01], INDIRECT("tb_rec_uni[natureza]"),"taxa.extra", INDIRECT("tb_rec_uni[empresa]"),$B31) -> 0 | K31: =SUMIFS(tb_rec_uni[2025-08-01], INDIRECT("tb_rec_uni[natureza]"),"taxa.extra", INDIRECT("tb_rec_uni[empresa]"),$B31) -> 0 | L31: =SUMIFS(tb_rec_uni[2025-09-01], INDIRECT("tb_rec_uni[natureza]"),"taxa.extra", INDIRECT("tb_rec_uni[empresa]"),$B31) -> 0 | M31: =SUMIFS(tb_rec_uni[2025-10-01], INDIRECT("tb_rec_uni[natureza]"),"taxa.extra", INDIRECT("tb_rec_uni[empresa]"),$B31) -> 0 | N31: =SUMIFS(tb_rec_uni[2025-11-01], INDIRECT("tb_rec_uni[natureza]"),"taxa.extra", INDIRECT("tb_rec_uni[empresa]"),$B31) -> 0 | O31: =SUMIFS(tb_rec_uni[2025-12-01], INDIRECT("tb_rec_uni[natureza]"),"taxa.extra", INDIRECT("tb_rec_uni[empresa]"),$B31) -> 0 | P31: =SUMIFS(tb_rec_uni[2026-01-01], INDIRECT("tb_rec_uni[natureza]"),"taxa.extra", INDIRECT("tb_rec_uni[empresa]"),$B31) -> 0 | Q31: =SUMIFS(tb_rec_uni[2026-02-01], INDIRECT("tb_rec_uni[natureza]"),"taxa.extra", INDIRECT("tb_rec_uni[empresa]"),$B31) -> 0 | R31: =SUMIFS(tb_rec_uni[2026-03-01], INDIRECT("tb_rec_uni[natureza]"),"taxa.extra", INDIRECT("tb_rec_uni[empresa]"),$B31) -> 0 | S31: =SUMIFS(tb_rec_uni[2026-04-01], INDIRECT("tb_rec_uni[natureza]"),"taxa.extra", INDIRECT("tb_rec_uni[empresa]"),$B31) -> 0 | T31: =SUMIFS(tb_rec_uni[2026-05-01], INDIRECT("tb_rec_uni[natureza]"),"taxa.extra", INDIRECT("tb_rec_uni[empresa]"),$B31) -> 0 | U31: =SUMIFS(tb_rec_uni[2026-06-01], INDIRECT("tb_rec_uni[natureza]"),"taxa.extra", INDIRECT("tb_rec_uni[empresa]"),$B31) -> 0 | V31: =SUMIFS(tb_rec_uni[2026-07-01], INDIRECT("tb_rec_uni[natureza]"),"taxa.extra", INDIRECT("tb_rec_uni[empresa]"),$B31) -> 0 | W31: =SUMIFS(tb_rec_uni[2026-08-01], INDIRECT("tb_rec_uni[natureza]"),"taxa.extra", INDIRECT("tb_rec_uni[empresa]"),$B31) -> 0 | X31: =SUMIFS(tb_rec_uni[2026-09-01], INDIRECT("tb_rec_uni[natureza]"),"taxa.extra", INDIRECT("tb_rec_uni[empresa]"),$B31) -> 0 | Y31: =SUMIFS(tb_rec_uni[2026-10-01], INDIRECT("tb_rec_uni[natureza]"),"taxa.extra", INDIRECT("tb_rec_uni[empresa]"),$B31) -> 0 | Z31: =SUMIFS(tb_rec_uni[2026-11-01], INDIRECT("tb_rec_uni[natureza]"),"taxa.extra", INDIRECT("tb_rec_uni[empresa]"),$B31) -> 0 | AA31: =SUMIFS(tb_rec_uni[2026-12-01], INDIRECT("tb_rec_uni[natureza]"),"taxa.extra", INDIRECT("tb_rec_uni[empresa]"),$B31) -> 0 | AC31: =SUM($D31:INDEX($D31:$AA31,1,MATCH(DATE(YEAR(inputs!$A$1),MONTH(inputs!$A$1),1),$D$1:$AA$1,0))) -> 0 | AE31: =SUM(D31:AA31) -> 0
A32: 1.1.4.SAU. | B32: SAU | C32: Ik | D32: =SUMIFS(tb_rec_uni[2025-01-01], INDIRECT("tb_rec_uni[natureza]"),"taxa.extra", INDIRECT("tb_rec_uni[empresa]"),$B32) -> 0 | E32: =SUMIFS(tb_rec_uni[2025-02-01], INDIRECT("tb_rec_uni[natureza]"),"taxa.extra", INDIRECT("tb_rec_uni[empresa]"),$B32) -> 0 | F32: =SUMIFS(tb_rec_uni[2025-03-01], INDIRECT("tb_rec_uni[natureza]"),"taxa.extra", INDIRECT("tb_rec_uni[empresa]"),$B32) -> 0 | G32: =SUMIFS(tb_rec_uni[2025-04-01], INDIRECT("tb_rec_uni[natureza]"),"taxa.extra", INDIRECT("tb_rec_uni[empresa]"),$B32) -> 0 | H32: =SUMIFS(tb_rec_uni[2025-05-01], INDIRECT("tb_rec_uni[natureza]"),"taxa.extra", INDIRECT("tb_rec_uni[empresa]"),$B32) -> 0 | I32: =SUMIFS(tb_rec_uni[2025-06-01], INDIRECT("tb_rec_uni[natureza]"),"taxa.extra", INDIRECT("tb_rec_uni[empresa]"),$B32) -> 0 | J32: =SUMIFS(tb_rec_uni[2025-07-01], INDIRECT("tb_rec_uni[natureza]"),"taxa.extra", INDIRECT("tb_rec_uni[empresa]"),$B32) -> 0 | K32: =SUMIFS(tb_rec_uni[2025-08-01], INDIRECT("tb_rec_uni[natureza]"),"taxa.extra", INDIRECT("tb_rec_uni[empresa]"),$B32) -> 0 | L32: =SUMIFS(tb_rec_uni[2025-09-01], INDIRECT("tb_rec_uni[natureza]"),"taxa.extra", INDIRECT("tb_rec_uni[empresa]"),$B32) -> 0 | M32: =SUMIFS(tb_rec_uni[2025-10-01], INDIRECT("tb_rec_uni[natureza]"),"taxa.extra", INDIRECT("tb_rec_uni[empresa]"),$B32) -> 0 | N32: =SUMIFS(tb_rec_uni[2025-11-01], INDIRECT("tb_rec_uni[natureza]"),"taxa.extra", INDIRECT("tb_rec_uni[empresa]"),$B32) -> 0 | O32: =SUMIFS(tb_rec_uni[2025-12-01], INDIRECT("tb_rec_uni[natureza]"),"taxa.extra", INDIRECT("tb_rec_uni[empresa]"),$B32) -> 0 | P32: =SUMIFS(tb_rec_uni[2026-01-01], INDIRECT("tb_rec_uni[natureza]"),"taxa.extra", INDIRECT("tb_rec_uni[empresa]"),$B32) -> 0 | Q32: =SUMIFS(tb_rec_uni[2026-02-01], INDIRECT("tb_rec_uni[natureza]"),"taxa.extra", INDIRECT("tb_rec_uni[empresa]"),$B32) -> 0 | R32: =SUMIFS(tb_rec_uni[2026-03-01], INDIRECT("tb_rec_uni[natureza]"),"taxa.extra", INDIRECT("tb_rec_uni[empresa]"),$B32) -> 0 | S32: =SUMIFS(tb_rec_uni[2026-04-01], INDIRECT("tb_rec_uni[natureza]"),"taxa.extra", INDIRECT("tb_rec_uni[empresa]"),$B32) -> 0 | T32: =SUMIFS(tb_rec_uni[2026-05-01], INDIRECT("tb_rec_uni[natureza]"),"taxa.extra", INDIRECT("tb_rec_uni[empresa]"),$B32) -> 0 | U32: =SUMIFS(tb_rec_uni[2026-06-01], INDIRECT("tb_rec_uni[natureza]"),"taxa.extra", INDIRECT("tb_rec_uni[empresa]"),$B32) -> 0 | V32: =SUMIFS(tb_rec_uni[2026-07-01], INDIRECT("tb_rec_uni[natureza]"),"taxa.extra", INDIRECT("tb_rec_uni[empresa]"),$B32) -> 0 | W32: =SUMIFS(tb_rec_uni[2026-08-01], INDIRECT("tb_rec_uni[natureza]"),"taxa.extra", INDIRECT("tb_rec_uni[empresa]"),$B32) -> 0 | X32: =SUMIFS(tb_rec_uni[2026-09-01], INDIRECT("tb_rec_uni[natureza]"),"taxa.extra", INDIRECT("tb_rec_uni[empresa]"),$B32) -> 0 | Y32: =SUMIFS(tb_rec_uni[2026-10-01], INDIRECT("tb_rec_uni[natureza]"),"taxa.extra", INDIRECT("tb_rec_uni[empresa]"),$B32) -> 0 | Z32: =SUMIFS(tb_rec_uni[2026-11-01], INDIRECT("tb_rec_uni[natureza]"),"taxa.extra", INDIRECT("tb_rec_uni[empresa]"),$B32) -> 0 | AA32: =SUMIFS(tb_rec_uni[2026-12-01], INDIRECT("tb_rec_uni[natureza]"),"taxa.extra", INDIRECT("tb_rec_uni[empresa]"),$B32) -> 0 | AC32: =SUM($D32:INDEX($D32:$AA32,1,MATCH(DATE(YEAR(inputs!$A$1),MONTH(inputs!$A$1),1),$D$1:$AA$1,0))) -> 0 | AE32: =SUM(D32:AA32) -> 0
A33: 1.2. | B33: Saídas de atividades operacionais | C33: IK | D33: =SUM(D$34,D$53,D$69,D$79,D$88,D$83,D$90,D$106,D$129,D$156,D$167,D$169,D$119,D$173) -> 0 | E33: =SUM(E$34,E$53,E$69,E$79,E$88,E$83,E$90,E$106,E$129,E$156,E$167,E$169,E$119,E$173) -> 0 | F33: =SUM(F$34,F$53,F$69,F$79,F$88,F$83,F$90,F$106,F$129,F$156,F$167,F$169,F$119,F$173) -> 0 | G33: =SUM(G$34,G$53,G$69,G$79,G$88,G$83,G$90,G$106,G$129,G$156,G$167,G$169,G$119,G$173) -> 0 | H33: =SUM(H$34,H$53,H$69,H$79,H$88,H$83,H$90,H$106,H$129,H$156,H$167,H$169,H$119,H$173) -> 0 | I33: =SUM(I$34,I$53,I$69,I$79,I$88,I$83,I$90,I$106,I$129,I$156,I$167,I$169,I$119,I$173) -> 0 | J33: =SUM(J$34,J$53,J$69,J$79,J$88,J$83,J$90,J$106,J$129,J$156,J$167,J$169,J$119,J$173) -> 0 | K33: =SUM(K$34,K$53,K$69,K$79,K$88,K$83,K$90,K$106,K$129,K$156,K$167,K$169,K$119,K$173) -> 0 | ... AA33: =SUM(AA$34,AA$53,AA$69,AA$79,AA$88,AA$83,AA$90,AA$106,AA$129,AA$156,AA$167,AA$169,AA$119,AA$173) -> 0 | AC33: =SUM($D33:INDEX($D33:$AA33,1,MATCH(DATE(YEAR(inputs!$A$1),MONTH(inputs!$A$1),1),$D$1:$AA$1,0))) -> 0 | AE33: =SUM(D33:AA33) -> 0
A34: 1.2.1. | B34: Custo Obra | C34: IK | D34: =SUM(D$35:D$52) -> 0 | E34: =SUM(E$35:E$52) -> 0 | F34: =SUM(F$35:F$52) -> 0 | G34: =SUM(G$35:G$52) -> 0 | H34: =SUM(H$35:H$52) -> 0 | I34: =SUM(I$35:I$52) -> 0 | J34: =SUM(J$35:J$52) -> 0 | K34: =SUM(K$35:K$52) -> 0 | ... AA34: =SUM(AA$35:AA$52) -> 0 | AC34: =SUM($D34:INDEX($D34:$AA34,1,MATCH(DATE(YEAR(inputs!$A$1),MONTH(inputs!$A$1),1),$D$1:$AA$1,0))) -> 0 | AE34: =SUM(D34:AA34) -> 0
A35: 1.2.1.SN2. | B35: UP ESTAÇÃO VILA SONIA | C35: IK | D35: =-SUMIFS( desp.m.ik[valor], desp.m.ik[nucleo], $B35, desp.m.ik[centro.negocio], $B$34, desp.m.ik[mes], ">="&D$1, desp.m.ik[mes], "<"&EOMONTH(D$1,0)+1 ) -> 0 | E35: =-SUMIFS( desp.m.ik[valor], desp.m.ik[nucleo], $B35, desp.m.ik[centro.negocio], $B$34, desp.m.ik[mes], ">="&E$1, desp.m.ik[mes], "<"&EOMONTH(E$1,0)+1 ) -> 0 | F35: =-SUMIFS( desp.m.ik[valor], desp.m.ik[nucleo], $B35, desp.m.ik[centro.negocio], $B$34, desp.m.ik[mes], ">="&F$1, desp.m.ik[mes], "<"&EOMONTH(F$1,0)+1 ) -> 0 | G35: =-SUMIFS( desp.m.ik[valor], desp.m.ik[nucleo], $B35, desp.m.ik[centro.negocio], $B$34, desp.m.ik[mes], ">="&G$1, desp.m.ik[mes], "<"&EOMONTH(G$1,0)+1 ) -> 0 | H35: =-SUMIFS( desp.m.ik[valor], desp.m.ik[nucleo], $B35, desp.m.ik[centro.negocio], $B$34, desp.m.ik[mes], ">="&H$1, desp.m.ik[mes], "<"&EOMONTH(H$1,0)+1 ) -> 0 | I35: =-SUMIFS( desp.m.ik[valor], desp.m.ik[nucleo], $B35, desp.m.ik[centro.negocio], $B$34, desp.m.ik[mes], ">="&I$1, desp.m.ik[mes], "<"&EOMONTH(I$1,0)+1 ) -> 0 | J35: =-SUMIFS( desp.m.ik[valor], desp.m.ik[nucleo], $B35, desp.m.ik[centro.negocio], $B$34, desp.m.ik[mes], ">="&J$1, desp.m.ik[mes], "<"&EOMONTH(J$1,0)+1 ) -> 0 | K35: =-SUMIFS( desp.m.ik[valor], desp.m.ik[nucleo], $B35, desp.m.ik[centro.negocio], $B$34, desp.m.ik[mes], ">="&K$1, desp.m.ik[mes], "<"&EOMONTH(K$1,0)+1 ) -> 0 | ... AA35: =-SUMIFS( desp.m.ik[valor], desp.m.ik[nucleo], $B35, desp.m.ik[centro.negocio], $B$34, desp.m.ik[mes], ">="&AA$1, desp.m.ik[mes], "<"&EOMONTH(AA$1,0)+1 ) -> 0 | AC35: =SUM($D35:INDEX($D35:$AA35,1,MATCH(DATE(YEAR(inputs!$A$1),MONTH(inputs!$A$1),1),$D$1:$AA$1,0))) -> 0 | AE35: =SUM(D35:AA35) -> 0
A36: 1.2.1.GRA. | B36: UP SELECT VILA SONIA | C36: IK | D36: =-SUMIFS( desp.m.ik[valor], desp.m.ik[nucleo], $B36, desp.m.ik[centro.negocio], $B$34, desp.m.ik[mes], ">="&D$1, desp.m.ik[mes], "<"&EOMONTH(D$1,0)+1 ) -> 0 | E36: =-SUMIFS( desp.m.ik[valor], desp.m.ik[nucleo], $B36, desp.m.ik[centro.negocio], $B$34, desp.m.ik[mes], ">="&E$1, desp.m.ik[mes], "<"&EOMONTH(E$1,0)+1 ) -> 0 | F36: =-SUMIFS( desp.m.ik[valor], desp.m.ik[nucleo], $B36, desp.m.ik[centro.negocio], $B$34, desp.m.ik[mes], ">="&F$1, desp.m.ik[mes], "<"&EOMONTH(F$1,0)+1 ) -> 0 | G36: =-SUMIFS( desp.m.ik[valor], desp.m.ik[nucleo], $B36, desp.m.ik[centro.negocio], $B$34, desp.m.ik[mes], ">="&G$1, desp.m.ik[mes], "<"&EOMONTH(G$1,0)+1 ) -> 0 | H36: =-SUMIFS( desp.m.ik[valor], desp.m.ik[nucleo], $B36, desp.m.ik[centro.negocio], $B$34, desp.m.ik[mes], ">="&H$1, desp.m.ik[mes], "<"&EOMONTH(H$1,0)+1 ) -> 0 | I36: =-SUMIFS( desp.m.ik[valor], desp.m.ik[nucleo], $B36, desp.m.ik[centro.negocio], $B$34, desp.m.ik[mes], ">="&I$1, desp.m.ik[mes], "<"&EOMONTH(I$1,0)+1 ) -> 0 | J36: =-SUMIFS( desp.m.ik[valor], desp.m.ik[nucleo], $B36, desp.m.ik[centro.negocio], $B$34, desp.m.ik[mes], ">="&J$1, desp.m.ik[mes], "<"&EOMONTH(J$1,0)+1 ) -> 0 | K36: =-SUMIFS( desp.m.ik[valor], desp.m.ik[nucleo], $B36, desp.m.ik[centro.negocio], $B$34, desp.m.ik[mes], ">="&K$1, desp.m.ik[mes], "<"&EOMONTH(K$1,0)+1 ) -> 0 | ... AA36: =-SUMIFS( desp.m.ik[valor], desp.m.ik[nucleo], $B36, desp.m.ik[centro.negocio], $B$34, desp.m.ik[mes], ">="&AA$1, desp.m.ik[mes], "<"&EOMONTH(AA$1,0)+1 ) -> 0 | AC36: =SUM($D36:INDEX($D36:$AA36,1,MATCH(DATE(YEAR(inputs!$A$1),MONTH(inputs!$A$1),1),$D$1:$AA$1,0))) -> 0 | AE36: =SUM(D36:AA36) -> 0
A37: 1.2.1.POM. | B37: UP POMPEIA | C37: IK | D37: =-SUMIFS( desp.m.ik[valor], desp.m.ik[nucleo], $B37, desp.m.ik[centro.negocio], $B$34, desp.m.ik[mes], ">="&D$1, desp.m.ik[mes], "<"&EOMONTH(D$1,0)+1 ) -> 0 | E37: =-SUMIFS( desp.m.ik[valor], desp.m.ik[nucleo], $B37, desp.m.ik[centro.negocio], $B$34, desp.m.ik[mes], ">="&E$1, desp.m.ik[mes], "<"&EOMONTH(E$1,0)+1 ) -> 0 | F37: =-SUMIFS( desp.m.ik[valor], desp.m.ik[nucleo], $B37, desp.m.ik[centro.negocio], $B$34, desp.m.ik[mes], ">="&F$1, desp.m.ik[mes], "<"&EOMONTH(F$1,0)+1 ) -> 0 | G37: =-SUMIFS( desp.m.ik[valor], desp.m.ik[nucleo], $B37, desp.m.ik[centro.negocio], $B$34, desp.m.ik[mes], ">="&G$1, desp.m.ik[mes], "<"&EOMONTH(G$1,0)+1 ) -> 0 | H37: =-SUMIFS( desp.m.ik[valor], desp.m.ik[nucleo], $B37, desp.m.ik[centro.negocio], $B$34, desp.m.ik[mes], ">="&H$1, desp.m.ik[mes], "<"&EOMONTH(H$1,0)+1 ) -> 0 | I37: =-SUMIFS( desp.m.ik[valor], desp.m.ik[nucleo], $B37, desp.m.ik[centro.negocio], $B$34, desp.m.ik[mes], ">="&I$1, desp.m.ik[mes], "<"&EOMONTH(I$1,0)+1 ) -> 0 | J37: =-SUMIFS( desp.m.ik[valor], desp.m.ik[nucleo], $B37, desp.m.ik[centro.negocio], $B$34, desp.m.ik[mes], ">="&J$1, desp.m.ik[mes], "<"&EOMONTH(J$1,0)+1 ) -> 0 | K37: =-SUMIFS( desp.m.ik[valor], desp.m.ik[nucleo], $B37, desp.m.ik[centro.negocio], $B$34, desp.m.ik[mes], ">="&K$1, desp.m.ik[mes], "<"&EOMONTH(K$1,0)+1 ) -> 0 | ... AA37: =-SUMIFS( desp.m.ik[valor], desp.m.ik[nucleo], $B37, desp.m.ik[centro.negocio], $B$34, desp.m.ik[mes], ">="&AA$1, desp.m.ik[mes], "<"&EOMONTH(AA$1,0)+1 ) -> 0 | AC37: =SUM($D37:INDEX($D37:$AA37,1,MATCH(DATE(YEAR(inputs!$A$1),MONTH(inputs!$A$1),1),$D$1:$AA$1,0))) -> 0 | AE37: =SUM(D37:AA37) -> 0
A38: 1.2.1.AMP. | B38: UP JARDIM PRUDENCIA | C38: IK | D38: =-SUMIFS( desp.m.ik[valor], desp.m.ik[nucleo], $B38, desp.m.ik[centro.negocio], $B$34, desp.m.ik[mes], ">="&D$1, desp.m.ik[mes], "<"&EOMONTH(D$1,0)+1 ) -> 0 | E38: =-SUMIFS( desp.m.ik[valor], desp.m.ik[nucleo], $B38, desp.m.ik[centro.negocio], $B$34, desp.m.ik[mes], ">="&E$1, desp.m.ik[mes], "<"&EOMONTH(E$1,0)+1 ) -> 0 | F38: =-SUMIFS( desp.m.ik[valor], desp.m.ik[nucleo], $B38, desp.m.ik[centro.negocio], $B$34, desp.m.ik[mes], ">="&F$1, desp.m.ik[mes], "<"&EOMONTH(F$1,0)+1 ) -> 0 | G38: =-SUMIFS( desp.m.ik[valor], desp.m.ik[nucleo], $B38, desp.m.ik[centro.negocio], $B$34, desp.m.ik[mes], ">="&G$1, desp.m.ik[mes], "<"&EOMONTH(G$1,0)+1 ) -> 0 | H38: =-SUMIFS( desp.m.ik[valor], desp.m.ik[nucleo], $B38, desp.m.ik[centro.negocio], $B$34, desp.m.ik[mes], ">="&H$1, desp.m.ik[mes], "<"&EOMONTH(H$1,0)+1 ) -> 0 | I38: =-SUMIFS( desp.m.ik[valor], desp.m.ik[nucleo], $B38, desp.m.ik[centro.negocio], $B$34, desp.m.ik[mes], ">="&I$1, desp.m.ik[mes], "<"&EOMONTH(I$1,0)+1 ) -> 0 | J38: =-SUMIFS( desp.m.ik[valor], desp.m.ik[nucleo], $B38, desp.m.ik[centro.negocio], $B$34, desp.m.ik[mes], ">="&J$1, desp.m.ik[mes], "<"&EOMONTH(J$1,0)+1 ) -> 0 | K38: =-SUMIFS( desp.m.ik[valor], desp.m.ik[nucleo], $B38, desp.m.ik[centro.negocio], $B$34, desp.m.ik[mes], ">="&K$1, desp.m.ik[mes], "<"&EOMONTH(K$1,0)+1 ) -> 0 | ... AA38: =-SUMIFS( desp.m.ik[valor], desp.m.ik[nucleo], $B38, desp.m.ik[centro.negocio], $B$34, desp.m.ik[mes], ">="&AA$1, desp.m.ik[mes], "<"&EOMONTH(AA$1,0)+1 ) -> 0 | AC38: =SUM($D38:INDEX($D38:$AA38,1,MATCH(DATE(YEAR(inputs!$A$1),MONTH(inputs!$A$1),1),$D$1:$AA$1,0))) -> 0 | AE38: =SUM(D38:AA38) -> 0
A39: 1.2.1.LUC. | B39: UP ESTAÇÃO SÃO LUCAS | C39: IK | D39: =-SUMIFS( desp.m.ik[valor], desp.m.ik[nucleo], $B39, desp.m.ik[centro.negocio], $B$34, desp.m.ik[mes], ">="&D$1, desp.m.ik[mes], "<"&EOMONTH(D$1,0)+1 ) -> 0 | E39: =-SUMIFS( desp.m.ik[valor], desp.m.ik[nucleo], $B39, desp.m.ik[centro.negocio], $B$34, desp.m.ik[mes], ">="&E$1, desp.m.ik[mes], "<"&EOMONTH(E$1,0)+1 ) -> 0 | F39: =-SUMIFS( desp.m.ik[valor], desp.m.ik[nucleo], $B39, desp.m.ik[centro.negocio], $B$34, desp.m.ik[mes], ">="&F$1, desp.m.ik[mes], "<"&EOMONTH(F$1,0)+1 ) -> 0 | G39: =-SUMIFS( desp.m.ik[valor], desp.m.ik[nucleo], $B39, desp.m.ik[centro.negocio], $B$34, desp.m.ik[mes], ">="&G$1, desp.m.ik[mes], "<"&EOMONTH(G$1,0)+1 ) -> 0 | H39: =-SUMIFS( desp.m.ik[valor], desp.m.ik[nucleo], $B39, desp.m.ik[centro.negocio], $B$34, desp.m.ik[mes], ">="&H$1, desp.m.ik[mes], "<"&EOMONTH(H$1,0)+1 ) -> 0 | I39: =-SUMIFS( desp.m.ik[valor], desp.m.ik[nucleo], $B39, desp.m.ik[centro.negocio], $B$34, desp.m.ik[mes], ">="&I$1, desp.m.ik[mes], "<"&EOMONTH(I$1,0)+1 ) -> 0 | J39: =-SUMIFS( desp.m.ik[valor], desp.m.ik[nucleo], $B39, desp.m.ik[centro.negocio], $B$34, desp.m.ik[mes], ">="&J$1, desp.m.ik[mes], "<"&EOMONTH(J$1,0)+1 ) -> 0 | K39: =-SUMIFS( desp.m.ik[valor], desp.m.ik[nucleo], $B39, desp.m.ik[centro.negocio], $B$34, desp.m.ik[mes], ">="&K$1, desp.m.ik[mes], "<"&EOMONTH(K$1,0)+1 ) -> 0 | ... AA39: =-SUMIFS( desp.m.ik[valor], desp.m.ik[nucleo], $B39, desp.m.ik[centro.negocio], $B$34, desp.m.ik[mes], ">="&AA$1, desp.m.ik[mes], "<"&EOMONTH(AA$1,0)+1 ) -> 0 | AC39: =SUM($D39:INDEX($D39:$AA39,1,MATCH(DATE(YEAR(inputs!$A$1),MONTH(inputs!$A$1),1),$D$1:$AA$1,0))) -> 0 | AE39: =SUM(D39:AA39) -> 0
A40: 1.2.1.AVS. | B40: UP VILA SONIA | C40: IK | D40: =-SUMIFS( desp.m.ik[valor], desp.m.ik[nucleo], $B40, desp.m.ik[centro.negocio], $B$34, desp.m.ik[mes], ">="&D$1, desp.m.ik[mes], "<"&EOMONTH(D$1,0)+1 ) -> 0 | E40: =-SUMIFS( desp.m.ik[valor], desp.m.ik[nucleo], $B40, desp.m.ik[centro.negocio], $B$34, desp.m.ik[mes], ">="&E$1, desp.m.ik[mes], "<"&EOMONTH(E$1,0)+1 ) -> 0 | F40: =-SUMIFS( desp.m.ik[valor], desp.m.ik[nucleo], $B40, desp.m.ik[centro.negocio], $B$34, desp.m.ik[mes], ">="&F$1, desp.m.ik[mes], "<"&EOMONTH(F$1,0)+1 ) -> 0 | G40: =-SUMIFS( desp.m.ik[valor], desp.m.ik[nucleo], $B40, desp.m.ik[centro.negocio], $B$34, desp.m.ik[mes], ">="&G$1, desp.m.ik[mes], "<"&EOMONTH(G$1,0)+1 ) -> 0 | H40: =-SUMIFS( desp.m.ik[valor], desp.m.ik[nucleo], $B40, desp.m.ik[centro.negocio], $B$34, desp.m.ik[mes], ">="&H$1, desp.m.ik[mes], "<"&EOMONTH(H$1,0)+1 ) -> 0 | I40: =-SUMIFS( desp.m.ik[valor], desp.m.ik[nucleo], $B40, desp.m.ik[centro.negocio], $B$34, desp.m.ik[mes], ">="&I$1, desp.m.ik[mes], "<"&EOMONTH(I$1,0)+1 ) -> 0 | J40: =-SUMIFS( desp.m.ik[valor], desp.m.ik[nucleo], $B40, desp.m.ik[centro.negocio], $B$34, desp.m.ik[mes], ">="&J$1, desp.m.ik[mes], "<"&EOMONTH(J$1,0)+1 ) -> 0 | K40: =-SUMIFS( desp.m.ik[valor], desp.m.ik[nucleo], $B40, desp.m.ik[centro.negocio], $B$34, desp.m.ik[mes], ">="&K$1, desp.m.ik[mes], "<"&EOMONTH(K$1,0)+1 ) -> 0 | ... AA40: =-SUMIFS( desp.m.ik[valor], desp.m.ik[nucleo], $B40, desp.m.ik[centro.negocio], $B$34, desp.m.ik[mes], ">="&AA$1, desp.m.ik[mes], "<"&EOMONTH(AA$1,0)+1 ) -> 0 | AC40: =SUM($D40:INDEX($D40:$AA40,1,MATCH(DATE(YEAR(inputs!$A$1),MONTH(inputs!$A$1),1),$D$1:$AA$1,0))) -> 0 | AE40: =SUM(D40:AA40) -> 0
A41: 1.2.1.SN4. | B41: UP MOVE VILA SONIA | C41: IK | D41: =-SUMIFS( desp.m.ik[valor], desp.m.ik[nucleo], $B41, desp.m.ik[centro.negocio], $B$34, desp.m.ik[mes], ">="&D$1, desp.m.ik[mes], "<"&EOMONTH(D$1,0)+1 ) -> 0 | E41: =-SUMIFS( desp.m.ik[valor], desp.m.ik[nucleo], $B41, desp.m.ik[centro.negocio], $B$34, desp.m.ik[mes], ">="&E$1, desp.m.ik[mes], "<"&EOMONTH(E$1,0)+1 ) -> 0 | F41: =-SUMIFS( desp.m.ik[valor], desp.m.ik[nucleo], $B41, desp.m.ik[centro.negocio], $B$34, desp.m.ik[mes], ">="&F$1, desp.m.ik[mes], "<"&EOMONTH(F$1,0)+1 ) -> 0 | G41: =-SUMIFS( desp.m.ik[valor], desp.m.ik[nucleo], $B41, desp.m.ik[centro.negocio], $B$34, desp.m.ik[mes], ">="&G$1, desp.m.ik[mes], "<"&EOMONTH(G$1,0)+1 ) -> 0 | H41: =-SUMIFS( desp.m.ik[valor], desp.m.ik[nucleo], $B41, desp.m.ik[centro.negocio], $B$34, desp.m.ik[mes], ">="&H$1, desp.m.ik[mes], "<"&EOMONTH(H$1,0)+1 ) -> 0 | I41: =-SUMIFS( desp.m.ik[valor], desp.m.ik[nucleo], $B41, desp.m.ik[centro.negocio], $B$34, desp.m.ik[mes], ">="&I$1, desp.m.ik[mes], "<"&EOMONTH(I$1,0)+1 ) -> 0 | J41: =-SUMIFS( desp.m.ik[valor], desp.m.ik[nucleo], $B41, desp.m.ik[centro.negocio], $B$34, desp.m.ik[mes], ">="&J$1, desp.m.ik[mes], "<"&EOMONTH(J$1,0)+1 ) -> 0 | K41: =-SUMIFS( desp.m.ik[valor], desp.m.ik[nucleo], $B41, desp.m.ik[centro.negocio], $B$34, desp.m.ik[mes], ">="&K$1, desp.m.ik[mes], "<"&EOMONTH(K$1,0)+1 ) -> 0 | ... AA41: =-SUMIFS( desp.m.ik[valor], desp.m.ik[nucleo], $B41, desp.m.ik[centro.negocio], $B$34, desp.m.ik[mes], ">="&AA$1, desp.m.ik[mes], "<"&EOMONTH(AA$1,0)+1 ) -> 0 | AC41: =SUM($D41:INDEX($D41:$AA41,1,MATCH(DATE(YEAR(inputs!$A$1),MONTH(inputs!$A$1),1),$D$1:$AA$1,0))) -> 0 | AE41: =SUM(D41:AA41) -> 0
A42: 1.2.1.JRP. | B42: UP SPORT HOME - JURUPITÉ | C42: IK | D42: =-SUMIFS( desp.m.ik[valor], desp.m.ik[nucleo], $B42, desp.m.ik[centro.negocio], $B$34, desp.m.ik[mes], ">="&D$1, desp.m.ik[mes], "<"&EOMONTH(D$1,0)+1 ) -> 0 | E42: =-SUMIFS( desp.m.ik[valor], desp.m.ik[nucleo], $B42, desp.m.ik[centro.negocio], $B$34, desp.m.ik[mes], ">="&E$1, desp.m.ik[mes], "<"&EOMONTH(E$1,0)+1 ) -> 0 | F42: =-SUMIFS( desp.m.ik[valor], desp.m.ik[nucleo], $B42, desp.m.ik[centro.negocio], $B$34, desp.m.ik[mes], ">="&F$1, desp.m.ik[mes], "<"&EOMONTH(F$1,0)+1 ) -> 0 | G42: =-SUMIFS( desp.m.ik[valor], desp.m.ik[nucleo], $B42, desp.m.ik[centro.negocio], $B$34, desp.m.ik[mes], ">="&G$1, desp.m.ik[mes], "<"&EOMONTH(G$1,0)+1 ) -> 0 | H42: =-SUMIFS( desp.m.ik[valor], desp.m.ik[nucleo], $B42, desp.m.ik[centro.negocio], $B$34, desp.m.ik[mes], ">="&H$1, desp.m.ik[mes], "<"&EOMONTH(H$1,0)+1 ) -> 0 | I42: =-SUMIFS( desp.m.ik[valor], desp.m.ik[nucleo], $B42, desp.m.ik[centro.negocio], $B$34, desp.m.ik[mes], ">="&I$1, desp.m.ik[mes], "<"&EOMONTH(I$1,0)+1 ) -> 0 | J42: =-SUMIFS( desp.m.ik[valor], desp.m.ik[nucleo], $B42, desp.m.ik[centro.negocio], $B$34, desp.m.ik[mes], ">="&J$1, desp.m.ik[mes], "<"&EOMONTH(J$1,0)+1 ) -> 0 | K42: =-SUMIFS( desp.m.ik[valor], desp.m.ik[nucleo], $B42, desp.m.ik[centro.negocio], $B$34, desp.m.ik[mes], ">="&K$1, desp.m.ik[mes], "<"&EOMONTH(K$1,0)+1 ) -> 0 | ... AA42: =-SUMIFS( desp.m.ik[valor], desp.m.ik[nucleo], $B42, desp.m.ik[centro.negocio], $B$34, desp.m.ik[mes], ">="&AA$1, desp.m.ik[mes], "<"&EOMONTH(AA$1,0)+1 ) -> 0 | AC42: =SUM($D42:INDEX($D42:$AA42,1,MATCH(DATE(YEAR(inputs!$A$1),MONTH(inputs!$A$1),1),$D$1:$AA$1,0))) -> 0 | AE42: =SUM(D42:AA42) -> 0
A43: 1.2.1.SAU. | B43: UP SAUDE | C43: IK | D43: =-SUMIFS( desp.m.ik[valor], desp.m.ik[nucleo], $B43, desp.m.ik[centro.negocio], $B$34, desp.m.ik[mes], ">="&D$1, desp.m.ik[mes], "<"&EOMONTH(D$1,0)+1 ) -> 0 | E43: =-SUMIFS( desp.m.ik[valor], desp.m.ik[nucleo], $B43, desp.m.ik[centro.negocio], $B$34, desp.m.ik[mes], ">="&E$1, desp.m.ik[mes], "<"&EOMONTH(E$1,0)+1 ) -> 0 | F43: =-SUMIFS( desp.m.ik[valor], desp.m.ik[nucleo], $B43, desp.m.ik[centro.negocio], $B$34, desp.m.ik[mes], ">="&F$1, desp.m.ik[mes], "<"&EOMONTH(F$1,0)+1 ) -> 0 | G43: =-SUMIFS( desp.m.ik[valor], desp.m.ik[nucleo], $B43, desp.m.ik[centro.negocio], $B$34, desp.m.ik[mes], ">="&G$1, desp.m.ik[mes], "<"&EOMONTH(G$1,0)+1 ) -> 0 | H43: =-SUMIFS( desp.m.ik[valor], desp.m.ik[nucleo], $B43, desp.m.ik[centro.negocio], $B$34, desp.m.ik[mes], ">="&H$1, desp.m.ik[mes], "<"&EOMONTH(H$1,0)+1 ) -> 0 | I43: =-SUMIFS( desp.m.ik[valor], desp.m.ik[nucleo], $B43, desp.m.ik[centro.negocio], $B$34, desp.m.ik[mes], ">="&I$1, desp.m.ik[mes], "<"&EOMONTH(I$1,0)+1 ) -> 0 | J43: =-SUMIFS( desp.m.ik[valor], desp.m.ik[nucleo], $B43, desp.m.ik[centro.negocio], $B$34, desp.m.ik[mes], ">="&J$1, desp.m.ik[mes], "<"&EOMONTH(J$1,0)+1 ) -> 0 | K43: =-SUMIFS( desp.m.ik[valor], desp.m.ik[nucleo], $B43, desp.m.ik[centro.negocio], $B$34, desp.m.ik[mes], ">="&K$1, desp.m.ik[mes], "<"&EOMONTH(K$1,0)+1 ) -> 0 | ... AA43: =-SUMIFS( desp.m.ik[valor], desp.m.ik[nucleo], $B43, desp.m.ik[centro.negocio], $B$34, desp.m.ik[mes], ">="&AA$1, desp.m.ik[mes], "<"&EOMONTH(AA$1,0)+1 ) -> 0 | AC43: =SUM($D43:INDEX($D43:$AA43,1,MATCH(DATE(YEAR(inputs!$A$1),MONTH(inputs!$A$1),1),$D$1:$AA$1,0))) -> 0 | AE43: =SUM(D43:AA43) -> 0
A44: 1.2.1.CBL. | B44: Up Stay Congonhas | C44: IK | D44: =-SUMIFS( desp.m.ik[valor], desp.m.ik[nucleo], $B44, desp.m.ik[centro.negocio], $B$34, desp.m.ik[mes], ">="&D$1, desp.m.ik[mes], "<"&EOMONTH(D$1,0)+1 ) -> 0 | E44: =-SUMIFS( desp.m.ik[valor], desp.m.ik[nucleo], $B44, desp.m.ik[centro.negocio], $B$34, desp.m.ik[mes], ">="&E$1, desp.m.ik[mes], "<"&EOMONTH(E$1,0)+1 ) -> 0 | F44: =-SUMIFS( desp.m.ik[valor], desp.m.ik[nucleo], $B44, desp.m.ik[centro.negocio], $B$34, desp.m.ik[mes], ">="&F$1, desp.m.ik[mes], "<"&EOMONTH(F$1,0)+1 ) -> 0 | G44: =-SUMIFS( desp.m.ik[valor], desp.m.ik[nucleo], $B44, desp.m.ik[centro.negocio], $B$34, desp.m.ik[mes], ">="&G$1, desp.m.ik[mes], "<"&EOMONTH(G$1,0)+1 ) -> 0 | H44: =-SUMIFS( desp.m.ik[valor], desp.m.ik[nucleo], $B44, desp.m.ik[centro.negocio], $B$34, desp.m.ik[mes], ">="&H$1, desp.m.ik[mes], "<"&EOMONTH(H$1,0)+1 ) -> 0 | I44: =-SUMIFS( desp.m.ik[valor], desp.m.ik[nucleo], $B44, desp.m.ik[centro.negocio], $B$34, desp.m.ik[mes], ">="&I$1, desp.m.ik[mes], "<"&EOMONTH(I$1,0)+1 ) -> 0 | J44: =-SUMIFS( desp.m.ik[valor], desp.m.ik[nucleo], $B44, desp.m.ik[centro.negocio], $B$34, desp.m.ik[mes], ">="&J$1, desp.m.ik[mes], "<"&EOMONTH(J$1,0)+1 ) -> 0 | K44: =-SUMIFS( desp.m.ik[valor], desp.m.ik[nucleo], $B44, desp.m.ik[centro.negocio], $B$34, desp.m.ik[mes], ">="&K$1, desp.m.ik[mes], "<"&EOMONTH(K$1,0)+1 ) -> 0 | ... AA44: =-SUMIFS( desp.m.ik[valor], desp.m.ik[nucleo], $B44, desp.m.ik[centro.negocio], $B$34, desp.m.ik[mes], ">="&AA$1, desp.m.ik[mes], "<"&EOMONTH(AA$1,0)+1 ) -> 0 | AC44: =SUM($D44:INDEX($D44:$AA44,1,MATCH(DATE(YEAR(inputs!$A$1),MONTH(inputs!$A$1),1),$D$1:$AA$1,0))) -> 0 | AE44: =SUM(D44:AA44) -> 0
